Workbook

Sheet Cover
A1: Institutional client review: independent case
A2: Anchor | B2: Hypothetical UK pension; US fund used only as a public research proxy
A3: Call | B3: ESCALATE for further due diligence; no mandate approval
A4: Quarter excess, bp | B4: =Performance!D2 -> 18
A5: 1-year excess, bp | B5: =Performance!D4 -> -51
A6: Open requests | B6: =COUNTIF(Requests!C2:C9,"Open") -> 5
A7: Total sample requests | B7: =COUNTA(Requests!A2:A9) -> 8
A8: Scope | B8: As of30 June2026. No real client meetings, requests or replies are implied
A9: Gate | B9: Do not use US fund results as a GBP-hedged institutional mandate record

Sheet Performance
A1: Performance: Class I vs benchmark | B1: Fund % | C1: Benchmark % | D1: Arithmetic excess bp
A2: =Inputs!A2 -> 3 months | B2: =Inputs!B2 -> 1.05 | C2: =Inputs!C2 -> 0.87 | D2: =(B2-C2)*100 -> 18
A3: =Inputs!A3 -> YTD | B3: =Inputs!B3 -> -0.26 | C3: =Inputs!C3 -> -0.21 | D3: =(B3-C3)*100 -> -5
A4: =Inputs!A4 -> 1 year | B4: =Inputs!B4 -> 0.11 | C4: =Inputs!C4 -> 0.62 | D4: =(B4-C4)*100 -> -51
A5: =Inputs!A5 -> 3 years annualised | B5: =Inputs!B5 -> 3.28 | C5: =Inputs!C5 -> 3.41 | D5: =(B5-C5)*100 -> -13
A6: =Inputs!A6 -> 5 years annualised | B6: =Inputs!B6 -> -2.01 | C6: =Inputs!C6 -> -1.55 | D6: =(B6-C6)*100 -> -46
A7: =Inputs!A7 -> 10 years annualised | B7: =Inputs!B7 -> 0.72 | C7: =Inputs!C7 -> 0.38 | D7: =(B7-C7)*100 -> 34
A8: Convention | B8: 3m/YTD cumulative; 1y and longer annualised. Excess is arithmetic difference, not geometric or risk-adjusted alpha
A9: Use | B9: Do not blend these horizons or infer return contributions from sector weights

Sheet Exposure
A1: Sector | B1: Fund % | C1: Benchmark % | D1: Active percentage points
A2: =Inputs!E2 -> Global Treasuries | B2: =Inputs!F2 -> 40.7 | C2: =Inputs!G2 -> 53.7 | D2: =B2-C2 -> -13
A3: =Inputs!E3 -> Corporates | B3: =Inputs!F3 -> 31.9 | C3: =Inputs!G3 -> 18.4 | D3: =B3-C3 -> 13.5
A4: =Inputs!E4 -> Securitized | B4: =Inputs!F4 -> 12.8 | C4: =Inputs!G4 -> 12.7 | D4: =B4-C4 -> 0.1
A5: =Inputs!E5 -> Government Related | B5: =Inputs!F5 -> 10.9 | C5: =Inputs!G5 -> 15.1 | D5: =B5-C5 -> -4.2
A6: =Inputs!E6 -> Cash & Equivalents | B6: =Inputs!F6 -> 3.7 | C6: =Inputs!G6 -> 0 | D6: =B6-C6 -> 3.7
A7: Total | B7: =SUM(B2:B6) -> 100 | C7: =SUM(C2:C6) -> 99.9 | D7: =SUM(D2:D6) -> 0.1
A8: Benchmark rounding residual | B8: =100-C7 -> 0.1
A9: Caution | B9: Exposure differences are not measured return attribution. Benchmark source sums99.9%; residual0.1pp is not allocated

Sheet Requests
A1: ID | B1: Consultant question | C1: Status | D1: Evidence / gap | E1: Suggested role owner | F1: Due day, illustrative
A2: Q1 | B2: Performance periods and fee basis | C2: Supported | D2: Factsheet p1 and commentary p1: Class I net returns, identical 30 Jun 2026 end date | E2: Research analyst | F2: 5
A3: Q2 | B3: Benchmark identity | C3: Supported | D3: Bloomberg Global Aggregate Index, factsheet p1 | E3: Research analyst | F3: 5
A4: Q3 | B4: Share-class costs and waiver | C4: Supported | D4: 0.67% net and 0.79% gross, waiver 31 Jan 2027, factsheet p1 | E4: Client service | F4: 5
A5: Q4 | B5: Numerical return attribution | C5: Open | D5: Commentary p2 names contributors but does not quantify contributions | E5: Investment team | F5: 5
A6: Q5 | B6: GBP-hedged mandate suitability | C6: Open | D6: US mutual fund snapshot does not establish GBP-hedged institutional mandate terms | E6: Investment director | F6: 5
A7: Q6 | B7: Institutional client access | C7: Open | D7: Hypothetical UK pension eligibility and appropriate vehicle require confirmation | E7: Client service | F7: 5
A8: Q7 | B8: Holdings and process consistency | C8: Open | D8: Aggregate sectors cannot establish trading decisions or security-level discipline | E8: Investment team | F8: 5
A9: Q8 | B9: Class R identifier inconsistency | C9: Open | D9: Factsheet header LSGBXR differs from fund-facts table LSGLX | E9: Client service | F9: 5

Sheet Inputs
A1: Inputs: 30 June 2026 Class I | B1: Fund return % | C1: Benchmark return % | E1: Sector | F1: Fund weight % | G1: Benchmark weight %
A2: 3 months | B2: 1.05 | C2: 0.87 | E2: Global Treasuries | F2: 40.7 | G2: 53.7
A3: YTD | B3: -0.26 | C3: -0.21 | E3: Corporates | F3: 31.9 | G3: 18.4
A4: 1 year | B4: 0.11 | C4: 0.62 | E4: Securitized | F4: 12.8 | G4: 12.7
A5: 3 years annualised | B5: 3.28 | C5: 3.41 | E5: Government Related | F5: 10.9 | G5: 15.1
A6: 5 years annualised | B6: -2.01 | C6: -1.55 | E6: Cash & Equivalents | F6: 3.7 | G6: 0
A7: 10 years annualised | B7: 0.72 | C7: 0.38

Sheet Sources
A1: Sources | B1: Document | C1: Page/date
A2: Factsheet | B2: https://www.loomissayles.com/wp-content/uploads/2026/07/GlobalBondFund-FactSheet.pdf | C2: p1 returns; p2 sectors, 30 Jun 2026
A3: Commentary | B3: https://www.loomissayles.com/wp-content/uploads/2026/07/GlobalBondFund-Commentary.pdf | C3: p1 return cross-check, p2 qualitative attribution
A4: Basis | B4: USD US fund Class I vs Bloomberg Global Aggregate, not a strategy composite | C4: Same end date
A5: Assumptions | B5: Sample questions, owner roles and five-day target are illustrative workflow fields | C5: No live requests
A6: Cash benchmark | B6: Dash interpreted as0 in displayed sector table, source benchmark total99.9 with0.1pp rounding residual | C6: Explicit interpretation
