Workbook

Sheet Cover
A1: UK gilts / GBP | B1: 27 October 2026
A2: Trade | B2: 2s10s steepener
A3: 12m priced cuts bp | B3: =Trade!B3 -> -123.43327
A4: 3m carry + roll bp | B4: =Trade!B14 -> 10.829944
A5: Stop fitted spread bp | B5: =Trade!B7 -> 43.402509
A6: Target fitted spread bp | B6: =Trade!B8 -> 83.402509
A7: Gross DV01 GBP/bp | B7: =Inputs!B4 -> 1000000
A8: Call | B8: Conditional steepener; reject passive GBP carry
A9: Limit | B9: Funding, term premia and global FX shocks can overwhelm the view

Sheet Inputs
A1: Driver | B1: Value | C1: Tag / reason
A2: Bank Rate % | B2: 3.75 | C2: S: BoE
A3: Bank Rate less SONIA bp | B3: 5 | C3: A: constant basis
A4: Gross DV01 GBP/bp | B4: 1000000 | C4: A: sum of absolute legs
A5: Horizon years | B5: 0.25 | C5: A: 3 months
A6: Scenario terminal Bank Rate % | B6: 3.75 | C6: A: hold, inflation above target
A7: Stop adverse bp | B7: 15 | C7: A: risk limit
A8: Target favourable bp | B8: 25 | C8: A: risk/reward
A9: OIS 1y forward % | B9: 4.9339992 | C9: S: BoE continuous forward
A10: Gilt 2y spot % | B10: 4.7382296 | C10: S: BoE fitted zero
A11: Gilt 10y spot % | B11: 5.3222547 | C11: S: BoE fitted zero
A12: Snapshot date | B12: 2026-10-27 | C12: S: BoE; FX latest 23 Oct 2026
A13: Curve-priced proxies, not quoted bond yields | B13: ISIN | C13: Coupon % | D13: Maturity
A14: S: DMO Annex A p7 | B14: GB00BFX0ZL78 | C14: 1.625 | D14: 2028-10-22
A15: S: DMO Annex A p7 | B15: GB00BWBR1N39 | C15: 4.875 | D15: 2036-07-31

Sheet Policy path
A1: MPC start | B1: End | C1: t1 years | D1: t2 years | E1: Zero at t1 % D | F1: Zero at t2 % D | G1: Continuous interval % | H1: Implied Bank Rate % | I1: Scenario %
A2: 2026-11-05 | B2: 2026-12-17 | C2: 0.024657534 | D2: 0.13972603 | E2: 3.8993903 | F2: 3.9374862 | G2: =(D2*F2-C2*E2)/(D2-C2) -> 3.9456497 | H2: =365*(EXP(G2/100/365)-1)*100+Inputs!B3/100 -> 3.9958629 | I2: =Inputs!B6 -> 3.75
A3: 2026-12-17 | B3: 2027-02-04 | C3: 0.13972603 | D3: 0.2739726 | E3: 3.9374862 | F3: 4.0261328 | G3: =(D3*F3-C3*E3)/(D3-C3) -> 4.1183975 | H3: =365*(EXP(G3/100/365)-1)*100+Inputs!B3/100 -> 4.1686299 | I3: =Inputs!B6 -> 3.75
A4: 2027-02-04 | B4: 2027-03-18 | C4: 0.2739726 | D4: 0.3890411 | E4: 4.0261328 | F4: 4.1064165 | G4: =(D4*F4-C4*E4)/(D4-C4) -> 4.2975684 | H4: =365*(EXP(G4/100/365)-1)*100+Inputs!B3/100 -> 4.3478214 | I4: =Inputs!B6 -> 3.75
A5: 2027-03-18 | B5: 2027-04-29 | C5: 0.3890411 | D5: 0.50410959 | E5: 4.1064165 | F5: 4.1882783 | G5: =(D5*F5-C5*E5)/(D5-C5) -> 4.4650491 | H5: =365*(EXP(G5/100/365)-1)*100+Inputs!B3/100 -> 4.5153222 | I5: =Inputs!B6 -> 3.75
A6: 2027-04-29 | B6: 2027-06-17 | C6: 0.50410959 | D6: 0.63835616 | E6: 4.1882783 | F6: 4.278754 | G6: =(D6*F6-C6*E6)/(D6-C6) -> 4.6184992 | H6: =365*(EXP(G6/100/365)-1)*100+Inputs!B3/100 -> 4.6687914 | I6: =Inputs!B6 -> 3.75
A7: 2027-06-17 | B7: 2027-07-29 | C7: 0.63835616 | D7: 0.75342466 | E7: 4.278754 | F7: 4.3498046 | G7: =(D7*F7-C7*E7)/(D7-C7) -> 4.7439664 | H7: =365*(EXP(G7/100/365)-1)*100+Inputs!B3/100 -> 4.7942747 | I7: =Inputs!B6 -> 3.75
A8: 2027-07-29 | B8: 2027-09-16 | C8: 0.75342466 | D8: 0.88767123 | E8: 4.3498046 | F8: 4.4230122 | G8: =(D8*F8-C8*E8)/(D8-C8) -> 4.8338716 | H8: =365*(EXP(G8/100/365)-1)*100+Inputs!B3/100 -> 4.8841917 | I8: =Inputs!B6 -> 3.75
A9: 2027-09-16 | B9: 2027-10-27 | C9: 0.88767123 | D9: 1 | E9: 4.4230122 | F9: 4.4778207 | G9: =(D9*F9-C9*E9)/(D9-C9) -> 4.9109412 | H9: =365*(EXP(G9/100/365)-1)*100+Inputs!B3/100 -> 4.9612716 | I9: =Inputs!B6 -> 3.75
A10: D: linear zero interpolation. Piecewise meeting approximation; risk-neutral plus premia, not a forecast.

Sheet Cash flows
A1: Leg | B1: Time years D | C1: Cash per100 S/D | D1: Zero % D | E1: Aged zero % D | F1: PV | G1: PV -1bp | H1: PV +1bp | I1: Carry PV | J1: Roll PV | K1: Received by horizon
A2: 1 | B2: 0.48493151 | C2: 0.8125 | D2: 4.2349676 | E2: 4.2349676 | F2: =C2*EXP(-D2/100*B2) -> 0.79598411 | G2: =C2*EXP(-(D2/100-0.0001)*B2) -> 0.79602271 | H2: =C2*EXP(-(D2/100+0.0001)*B2) -> 0.79594551 | I2: =IF(B2>Inputs!B5,C2*EXP(-D2/100*(B2-Inputs!B5)),0) -> 0.8044563 | J2: =IF(B2>Inputs!B5,C2*EXP(-E2/100*(B2-Inputs!B5)),0) -> 0.8044563 | K2: =IF(B2<=Inputs!B5,C2,0) -> 0
A3: 1 | B3: 0.98630137 | C3: 0.8125 | D3: 4.4613408 | E3: 4.3449658 | F3: =C3*EXP(-D3/100*B3) -> 0.77752333 | G3: =C3*EXP(-(D3/100-0.0001)*B3) -> 0.77760002 | H3: =C3*EXP(-(D3/100+0.0001)*B3) -> 0.77744665 | I3: =IF(B3>Inputs!B5,C3*EXP(-D3/100*(B3-Inputs!B5)),0) -> 0.78624386 | J3: =IF(B3>Inputs!B5,C3*EXP(-E3/100*(B3-Inputs!B5)),0) -> 0.78691786 | K3: =IF(B3<=Inputs!B5,C3,0) -> 0
A4: 1 | B4: 1.4876712 | C4: 0.8125 | D4: 4.6335727 | E4: 4.5485486 | F4: =C4*EXP(-D4/100*B4) -> 0.75837925 | G4: =C4*EXP(-(D4/100-0.0001)*B4) -> 0.75849208 | H4: =C4*EXP(-(D4/100+0.0001)*B4) -> 0.75826643 | I4: =IF(B4>Inputs!B5,C4*EXP(-D4/100*(B4-Inputs!B5)),0) -> 0.76721534 | J4: =IF(B4>Inputs!B5,C4*EXP(-E4/100*(B4-Inputs!B5)),0) -> 0.76802312 | K4: =IF(B4<=Inputs!B5,C4,0) -> 0
A5: 1 | B5: 1.9890411 | C5: 100.8125 | D5: 4.7360277 | E5: 4.6857957 | F5: =C5*EXP(-D5/100*B5) -> 91.749388 | G5: =C5*EXP(-(D5/100-0.0001)*B5) -> 91.767639 | H5: =C5*EXP(-(D5/100+0.0001)*B5) -> 91.731141 | I5: =IF(B5>Inputs!B5,C5*EXP(-D5/100*(B5-Inputs!B5)),0) -> 92.842164 | J5: =IF(B5>Inputs!B5,C5*EXP(-E5/100*(B5-Inputs!B5)),0) -> 92.923302 | K5: =IF(B5<=Inputs!B5,C5,0) -> 0
A6: 2 | B6: 0.2630137 | C6: 2.4375 | D6: 4.2349676 | E6: 4.2349676 | F6: =C6*EXP(-D6/100*B6) -> 2.4105004 | G6: =C6*EXP(-(D6/100-0.0001)*B6) -> 2.4105638 | H6: =C6*EXP(-(D6/100+0.0001)*B6) -> 2.410437 | I6: =IF(B6>Inputs!B5,C6*EXP(-D6/100*(B6-Inputs!B5)),0) -> 2.436157 | J6: =IF(B6>Inputs!B5,C6*EXP(-E6/100*(B6-Inputs!B5)),0) -> 2.436157 | K6: =IF(B6<=Inputs!B5,C6,0) -> 0
A7: 2 | B7: 0.75890411 | C7: 2.4375 | D7: 4.3554874 | E7: 4.2391124 | F7: =C7*EXP(-D7/100*B7) -> 2.358248 | G7: =C7*EXP(-(D7/100-0.0001)*B7) -> 2.3584269 | H7: =C7*EXP(-(D7/100+0.0001)*B7) -> 2.358069 | I7: =IF(B7>Inputs!B5,C7*EXP(-D7/100*(B7-Inputs!B5)),0) -> 2.3840666 | J7: =IF(B7>Inputs!B5,C7*EXP(-E7/100*(B7-Inputs!B5)),0) -> 2.3854789 | K7: =IF(B7<=Inputs!B5,C7,0) -> 0
A8: 2 | B8: 1.2630137 | C8: 2.4375 | D8: 4.5571675 | E8: 4.4721434 | F8: =C8*EXP(-D8/100*B8) -> 2.3011644 | G8: =C8*EXP(-(D8/100-0.0001)*B8) -> 2.3014551 | H8: =C8*EXP(-(D8/100+0.0001)*B8) -> 2.3008738 | I8: =IF(B8>Inputs!B5,C8*EXP(-D8/100*(B8-Inputs!B5)),0) -> 2.3275313 | J8: =IF(B8>Inputs!B5,C8*EXP(-E8/100*(B8-Inputs!B5)),0) -> 2.3295369 | K8: =IF(B8<=Inputs!B5,C8,0) -> 0
A9: 2 | B9: 1.7616438 | C9: 2.4375 | D9: 4.6903372 | E9: 4.6401053 | F9: =C9*EXP(-D9/100*B9) -> 2.2441928 | G9: =C9*EXP(-(D9/100-0.0001)*B9) -> 2.2445881 | H9: =C9*EXP(-(D9/100+0.0001)*B9) -> 2.2437975 | I9: =IF(B9>Inputs!B5,C9*EXP(-D9/100*(B9-Inputs!B5)),0) -> 2.2706627 | J9: =IF(B9>Inputs!B5,C9*EXP(-E9/100*(B9-Inputs!B5)),0) -> 2.2723875 | K9: =IF(B9<=Inputs!B5,C9,0) -> 0
A10: 2 | B10: 2.2657534 | C10: 2.4375 | D10: 4.7711261 | E10: 4.7401797 | F10: =C10*EXP(-D10/100*B10) -> 2.1877442 | G10: =C10*EXP(-(D10/100-0.0001)*B10) -> 2.18824 | H10: =C10*EXP(-(D10/100+0.0001)*B10) -> 2.1872486 | I10: =IF(B10>Inputs!B5,C10*EXP(-D10/100*(B10-Inputs!B5)),0) -> 2.2139955 | J10: =IF(B10>Inputs!B5,C10*EXP(-E10/100*(B10-Inputs!B5)),0) -> 2.215377 | K10: =IF(B10<=Inputs!B5,C10,0) -> 0
A11: 2 | B11: 2.7616438 | C11: 2.4375 | D11: 4.8223461 | E11: 4.8011115 | F11: =C11*EXP(-D11/100*B11) -> 2.1335706 | G11: =C11*EXP(-(D11/100-0.0001)*B11) -> 2.1341599 | H11: =C11*EXP(-(D11/100+0.0001)*B11) -> 2.1329814 | I11: =IF(B11>Inputs!B5,C11*EXP(-D11/100*(B11-Inputs!B5)),0) -> 2.1594483 | J11: =IF(B11>Inputs!B5,C11*EXP(-E11/100*(B11-Inputs!B5)),0) -> 2.1606003 | K11: =IF(B11<=Inputs!B5,C11,0) -> 0
A12: 2 | B12: 3.2657534 | C12: 2.4375 | D12: 4.8602103 | E12: 4.8436361 | F12: =C12*EXP(-D12/100*B12) -> 2.0797557 | G12: =C12*EXP(-(D12/100-0.0001)*B12) -> 2.080435 | H12: =C12*EXP(-(D12/100+0.0001)*B12) -> 2.0790766 | I12: =IF(B12>Inputs!B5,C12*EXP(-D12/100*(B12-Inputs!B5)),0) -> 2.10518 | J12: =IF(B12>Inputs!B5,C12*EXP(-E12/100*(B12-Inputs!B5)),0) -> 2.1062325 | K12: =IF(B12<=Inputs!B5,C12,0) -> 0
A13: 2 | B13: 3.7616438 | C13: 2.4375 | D13: 4.891144 | E13: 4.8764256 | F13: =C13*EXP(-D13/100*B13) -> 2.027869 | G13: =C13*EXP(-(D13/100-0.0001)*B13) -> 2.028632 | H13: =C13*EXP(-(D13/100+0.0001)*B13) -> 2.0271064 | I13: =IF(B13>Inputs!B5,C13*EXP(-D13/100*(B13-Inputs!B5)),0) -> 2.0528178 | J13: =IF(B13>Inputs!B5,C13*EXP(-E13/100*(B13-Inputs!B5)),0) -> 2.0538791 | K13: =IF(B13<=Inputs!B5,C13,0) -> 0
A14: 2 | B14: 4.2657534 | C14: 2.4375 | D14: 4.9204844 | E14: 4.9060844 | F14: =C14*EXP(-D14/100*B14) -> 1.9760051 | G14: =C14*EXP(-(D14/100-0.0001)*B14) -> 1.9768482 | H14: =C14*EXP(-(D14/100+0.0001)*B14) -> 1.9751624 | I14: =IF(B14>Inputs!B5,C14*EXP(-D14/100*(B14-Inputs!B5)),0) -> 2.0004625 | J14: =IF(B14>Inputs!B5,C14*EXP(-E14/100*(B14-Inputs!B5)),0) -> 2.0016196 | K14: =IF(B14<=Inputs!B5,C14,0) -> 0
A15: 2 | B15: 4.7616438 | C15: 2.4375 | D15: 4.9495156 | E15: 4.9346686 | F15: =C15*EXP(-D15/100*B15) -> 1.9257098 | G15: =C15*EXP(-(D15/100-0.0001)*B15) -> 1.926627 | H15: =C15*EXP(-(D15/100+0.0001)*B15) -> 1.924793 | I15: =IF(B15>Inputs!B5,C15*EXP(-D15/100*(B15-Inputs!B5)),0) -> 1.9496861 | J15: =IF(B15>Inputs!B5,C15*EXP(-E15/100*(B15-Inputs!B5)),0) -> 1.9509926 | K15: =IF(B15<=Inputs!B5,C15,0) -> 0
A16: 2 | B16: 5.2657534 | C16: 2.4375 | D16: 4.9802604 | E16: 4.9646545 | F16: =C16*EXP(-D16/100*B16) -> 1.8752176 | G16: =C16*EXP(-(D16/100-0.0001)*B16) -> 1.8762053 | H16: =C16*EXP(-(D16/100+0.0001)*B16) -> 1.8742304 | I16: =IF(B16>Inputs!B5,C16*EXP(-D16/100*(B16-Inputs!B5)),0) -> 1.8987112 | J16: =IF(B16>Inputs!B5,C16*EXP(-E16/100*(B16-Inputs!B5)),0) -> 1.900198 | K16: =IF(B16<=Inputs!B5,C16,0) -> 0
A17: 2 | B17: 5.7643836 | C17: 2.4375 | D17: 5.0122586 | E17: 4.9958283 | F17: =C17*EXP(-D17/100*B17) -> 1.8258527 | G17: =C17*EXP(-(D17/100-0.0001)*B17) -> 1.8269055 | H17: =C17*EXP(-(D17/100+0.0001)*B17) -> 1.8248005 | I17: =IF(B17>Inputs!B5,C17*EXP(-D17/100*(B17-Inputs!B5)),0) -> 1.8488758 | J17: =IF(B17>Inputs!B5,C17*EXP(-E17/100*(B17-Inputs!B5)),0) -> 1.8505517 | K17: =IF(B17<=Inputs!B5,C17,0) -> 0
A18: 2 | B18: 6.2684932 | C18: 2.4375 | D18: 5.0462102 | E18: 5.0290154 | F18: =C18*EXP(-D18/100*B18) -> 1.7765115 | G18: =C18*EXP(-(D18/100-0.0001)*B18) -> 1.7776254 | H18: =C18*EXP(-(D18/100+0.0001)*B18) -> 1.7753982 | I18: =IF(B18>Inputs!B5,C18*EXP(-D18/100*(B18-Inputs!B5)),0) -> 1.799065 | J18: =IF(B18>Inputs!B5,C18*EXP(-E18/100*(B18-Inputs!B5)),0) -> 1.8009278 | K18: =IF(B18<=Inputs!B5,C18,0) -> 0
A19: 2 | B19: 6.7643836 | C19: 2.4375 | D19: 5.0809983 | E19: 5.0631594 | F19: =C19*EXP(-D19/100*B19) -> 1.7285358 | G19: =C19*EXP(-(D19/100-0.0001)*B19) -> 1.7297055 | H19: =C19*EXP(-(D19/100+0.0001)*B19) -> 1.727367 | I19: =IF(B19>Inputs!B5,C19*EXP(-D19/100*(B19-Inputs!B5)),0) -> 1.7506326 | J19: =IF(B19>Inputs!B5,C19*EXP(-E19/100*(B19-Inputs!B5)),0) -> 1.7526682 | K19: =IF(B19<=Inputs!B5,C19,0) -> 0
A20: 2 | B20: 7.2684932 | C20: 2.4375 | D20: 5.1175065 | E20: 5.0991676 | F20: =C20*EXP(-D20/100*B20) -> 1.6803588 | G20: =C20*EXP(-(D20/100-0.0001)*B20) -> 1.6815806 | H20: =C20*EXP(-(D20/100+0.0001)*B20) -> 1.6791378 | I20: =IF(B20>Inputs!B5,C20*EXP(-D20/100*(B20-Inputs!B5)),0) -> 1.701995 | J20: =IF(B20>Inputs!B5,C20*EXP(-E20/100*(B20-Inputs!B5)),0) -> 1.7041871 | K20: =IF(B20<=Inputs!B5,C20,0) -> 0
A21: 2 | B21: 7.7643836 | C21: 2.4375 | D21: 5.1542491 | E21: 5.1355639 | F21: =C21*EXP(-D21/100*B21) -> 1.6335854 | G21: =C21*EXP(-(D21/100-0.0001)*B21) -> 1.6348543 | H21: =C21*EXP(-(D21/100+0.0001)*B21) -> 1.6323175 | I21: =IF(B21>Inputs!B5,C21*EXP(-D21/100*(B21-Inputs!B5)),0) -> 1.6547714 | J21: =IF(B21>Inputs!B5,C21*EXP(-E21/100*(B21-Inputs!B5)),0) -> 1.6570965 | K21: =IF(B21<=Inputs!B5,C21,0) -> 0
A22: 2 | B22: 8.2684932 | C22: 2.4375 | D22: 5.1921325 | E22: 5.1732557 | F22: =C22*EXP(-D22/100*B22) -> 1.5867086 | G22: =C22*EXP(-(D22/100-0.0001)*B22) -> 1.5880211 | H22: =C22*EXP(-(D22/100+0.0001)*B22) -> 1.5853972 | I22: =IF(B22>Inputs!B5,C22*EXP(-D22/100*(B22-Inputs!B5)),0) -> 1.6074388 | J22: =IF(B22>Inputs!B5,C22*EXP(-E22/100*(B22-Inputs!B5)),0) -> 1.6098738 | K22: =IF(B22<=Inputs!B5,C22,0) -> 0
A23: 2 | B23: 8.7643836 | C23: 2.4375 | D23: 5.2296195 | E23: 5.2107014 | F23: =C23*EXP(-D23/100*B23) -> 1.5413043 | G23: =C23*EXP(-(D23/100-0.0001)*B23) -> 1.5426558 | H23: =C23*EXP(-(D23/100+0.0001)*B23) -> 1.539954 | I23: =IF(B23>Inputs!B5,C23*EXP(-D23/100*(B23-Inputs!B5)),0) -> 1.5615877 | J23: =IF(B23>Inputs!B5,C23*EXP(-E23/100*(B23-Inputs!B5)),0) -> 1.5641051 | K23: =IF(B23<=Inputs!B5,C23,0) -> 0
A24: 2 | B24: 9.2684932 | C24: 2.4375 | D24: 5.2676584 | E24: 5.2488412 | F24: =C24*EXP(-D24/100*B24) -> 1.4959185 | G24: =C24*EXP(-(D24/100-0.0001)*B24) -> 1.4973056 | H24: =C24*EXP(-(D24/100+0.0001)*B24) -> 1.4945326 | I24: =IF(B24>Inputs!B5,C24*EXP(-D24/100*(B24-Inputs!B5)),0) -> 1.5157487 | J24: =IF(B24>Inputs!B5,C24*EXP(-E24/100*(B24-Inputs!B5)),0) -> 1.5183232 | K24: =IF(B24<=Inputs!B5,C24,0) -> 0
A25: 2 | B25: 9.7671233 | C25: 102.4375 | D25: 5.3049422 | E25: 5.2863566 | F25: =C25*EXP(-D25/100*B25) -> 61.014566 | G25: =C25*EXP(-(D25/100-0.0001)*B25) -> 61.074188 | H25: =C25*EXP(-(D25/100+0.0001)*B25) -> 60.955001 | I25: =IF(B25>Inputs!B5,C25*EXP(-D25/100*(B25-Inputs!B5)),0) -> 61.829152 | J25: =IF(B25>Inputs!B5,C25*EXP(-E25/100*(B25-Inputs!B5)),0) -> 61.938613 | K25: =IF(B25<=Inputs!B5,C25,0) -> 0

Sheet Trade
A1: Metric | B1: Value | C1: Unit / convention
A2: 12m implied Bank Rate | B2: =365*(EXP(Inputs!B9/100/365)-1)*100+Inputs!B3/100 -> 4.9843327 | C2: %
A3: Implied cuts | B3: =(Inputs!B2-B2)*100 -> -123.43327 | C3: bp; negative = hikes
A4: Scenario cuts | B4: =(Inputs!B2-Inputs!B6)*100 -> 0 | C4: bp
A5: 2s10s entry | B5: =(Inputs!B11-Inputs!B10)*100 -> 58.402509 | C5: bp fitted zero spread
A6: Direction | B6: =IF(Inputs!B6<B2,1,-1) -> 1 | C6: 1 steepener; -1 flattener
A7: Stop | B7: =B5-B6*Inputs!B7 -> 43.402509 | C7: bp
A8: Target | B8: =B5+B6*Inputs!B8 -> 83.402509 | C8: bp
A9: Leg | B9: Price /100 | C9: DV01 /100 | D9: Signed nominal GBP | E9: Carry /100 net funding | F9: Roll /100
A10: GB00BFX0ZL78 | B10: =SUM('Cash flows'!F2:F5) -> 94.081275 | C10: =(SUM('Cash flows'!G2:G5)-SUM('Cash flows'!H2:H5))/2 -> 0.018477439 | D10: =Inputs!B4/2/C10*100*$B$6*1 -> 2.7060027e+09 | E10: =SUM('Cash flows'!I2:I5)+SUM('Cash flows'!K2:K5)-B10-B10*Inputs!B2/100*Inputs!B5 -> 0.23679247 | F10: =SUM('Cash flows'!J2:J5)-SUM('Cash flows'!I2:I5) -> 0.082619929
A11: GB00BWBR1N39 | B11: =SUM('Cash flows'!F6:F25) -> 97.803319 | C11: =(SUM('Cash flows'!G6:G25)-SUM('Cash flows'!H6:H25))/2 -> 0.075670679 | D11: =Inputs!B4/2/C11*100*$B$6*-1 -> -6.6075791e+08 | E11: =SUM('Cash flows'!I6:I25)+SUM('Cash flows'!K6:K25)-B11-B11*Inputs!B2/100*Inputs!B5 -> 0.34776131 | F11: =SUM('Cash flows'!J6:J25)-SUM('Cash flows'!I6:I25) -> 0.14081947
A12: Carry GBP | B12: =D10/100*E10+D11/100*E11 -> 4109750.2 | C12: net financing at Bank Rate both legs
A13: Roll GBP | B13: =D10/100*F10+D11/100*F11 -> 1305221.7 | C13: unchanged spot curve
A14: Carry + roll bp | B14: =(B12+B13)/(Inputs!B4/2) -> 10.829944 | C14: spread-equivalent bp, one leg DV01
A15: Net parallel DV01 | B15: =D10/100*C10+D11/100*C11 -> 0 | C15: GBP/bp
A16: Net cash invested | B16: =D10/100*B10+D11/100*B11 -> 1.8995986e+09 | C16: GBP, financed; short proceeds usable assumed

Sheet Sensitivity
A1: Spread move bp | B1: Linear P&L GBP | C1: Carry + roll GBP | D1: Total GBP
A2: -50 | B2: =A2*Trade!B6*Inputs!B4/2 -> -25000000 | C2: =Trade!B12+Trade!B13 -> 5414971.9 | D2: =B2+C2 -> -19585028
A3: -25 | B3: =A3*Trade!B6*Inputs!B4/2 -> -12500000 | C3: =Trade!B12+Trade!B13 -> 5414971.9 | D3: =B3+C3 -> -7085028.1
A4: 0 | B4: =A4*Trade!B6*Inputs!B4/2 -> 0 | C4: =Trade!B12+Trade!B13 -> 5414971.9 | D4: =B4+C4 -> 5414971.9
A5: 25 | B5: =A5*Trade!B6*Inputs!B4/2 -> 12500000 | C5: =Trade!B12+Trade!B13 -> 5414971.9 | D5: =B5+C5 -> 17914972
A6: 50 | B6: =A6*Trade!B6*Inputs!B4/2 -> 25000000 | C6: =Trade!B12+Trade!B13 -> 5414971.9 | D6: =B6+C6 -> 30414972
A7: LDI replay | B7: 2y shock bp | C7: 10y shock bp | D7: Full reprice GBP; no carry
A8: peak | B8: 148.94162 | C8: 146.52021 | D8: -4730617.4
A9: end | B9: 91.008773 | C9: 141.79064 | D9: 21478028
A10: Replay prices current bonds under historical tenor shocks; not a 2022 investable return.

Sheet GBP research
A1: Pair / sample | B1: Slope % per10bp D | C1: HAC t D | D1: R-squared D | E1: N
A2: GBP_USD full | B2: -0.10074037 | C2: -3.0969348 | D2: 0.019638094 | E2: 1658
A3: GBP_USD ex2022 | B3: -0.050506358 | C3: -2.2223962 | D3: 0.0044548061 | E3: 1417
A4: GBP_USD LDI | B4: -0.36719353 | C4: -6.2293364 | D4: 0.46458411 | E4: 29
A5: GBP_USD MPC | B5: -0.053353495 | C5: -0.48406307 | D5: 0.013621595 | E5: 13
A6: GBP_USD CPI | B6: -0.015454845 | C6: -0.1967455 | D6: 0.0028561084 | E6: 9
A7: GBP_EUR full | B7: 0.0051352702 | C7: 0.23496979 | D7: 0.00010549096 | E7: 1658
A8: GBP_EUR ex2022 | B8: 0.052037121 | C8: 2.9290736 | D8: 0.0091483893 | E8: 1417
A9: GBP_EUR LDI | B9: -0.14597412 | C9: -3.1758385 | D9: 0.20849638 | E9: 29
A10: GBP_EUR MPC | B10: 0.0595355 | C10: 1.4360743 | D10: 0.066878503 | E10: 13
A11: GBP_EUR CPI | B11: 0.034566682 | C11: 0.85981694 | D11: 0.025261797 | E11: 9
A12: Carry snapshot | B12: Foreign overnight % S | C12: Annual vol % D | D12: GBP carry % | E12: Carry / vol
A13: GBP_USD | B13: 3.92 | C13: 6.2135164 | D13: =Inputs!B2-B13 -> -0.17 | E13: =D13/C13 -> -0.027359709
A14: GBP_EUR | B14: 2.442 | C14: 3.6264342 | D14: =Inputs!B2-B14 -> 1.308 | E14: =D14/C14 -> 0.36068488
A15: Historical regressions fixed Python research outputs; rerun engine after data refresh.
A16: MPC event calendar: 2025-26; CPI: Feb-Oct 2026, n=9; descriptive only.
A17: GBP_EUR is GBP appreciation, inverse EUR/GBP. No causal or executable forward-return claim.

Sheet Sources
A1: Source | B1: URL / method
A2: curves | B2: https://www.bankofengland.co.uk/statistics/yield-curves
A3: bank_rate | B3: https://www.bankofengland.co.uk/boeapps/database/Bank-Rate.asp
A4: mpc | B4: https://www.bankofengland.co.uk/monetary-policy/upcoming-mpc-dates
A5: dmo | B5: https://www.dmo.gov.uk/media/r2ejghpr/apr-jun-2026a.pdf
A6: cpi | B6: https://www.ons.gov.uk/economy/inflationandpriceindices/bulletins/consumerpriceinflation/september2026
A7: fx | B7: https://fred.stlouisfed.org/series/DEXUSUK
A8: eurusd | B8: https://fred.stlouisfed.org/series/DEXUSEU
A9: sofr | B9: https://fred.stlouisfed.org/series/SOFR
A10: estr | B10: https://fred.stlouisfed.org/series/ECBESTRVOLWGTTRMDMNRT
A11: Data audit | B11: policy/data/manifest.json: archive hashes, extraction and retrieval date
A12: Curve interpolation D | B12: Linear zero rates; flat below shortest maturity; ACT/365 proxy for gilts
... A14: Scenario A | B14: 2y -50bp / 10y -10bp gives +40bp spread; inflation / fiscal shock breaks this
