Workbook

Sheet Summary
A1: Sterling receiver options | Project 12
A4: Independent research | Synthetic SONIA receiver comparison. No executable swaption quote or post-Budget curve is supplied. Model values are not trade recommendations.
A7: Input state | B7: =IF(NOT(AND(Pricing!B4,Pricing!E4)),"BLOCKED: INVALID / MISSING INPUTS",IF(Inputs!B15=0,"ILLUSTRATIVE VOLATILITY","DEALER VOL INPUTS: VERIFY CONVENTIONS")) -> ILLUSTRATIVE VOLATILITY
A8: Curve date | B8: =Inputs!B24 -> 2026-10-27
A9: Forward swap rate | B9: =Pricing!B24 -> 0.049528497
A10: Discount annuity | B10: =Pricing!B22 -> 1.8431333
A11: PV01 (£/bp) | B11: =Pricing!B23 -> 18431.333
A13: Outright premium (rate bp) | B13: =Pricing!B33*10000 -> 15.957691
A14: Spread premium (rate bp) | B14: =Pricing!B35*10000 -> 9.4808907
A15: Spread maximum loss incl costs | B15: =IF(Pricing!B36,(B14+Inputs!B12)*B11,NA()) -> 193176.78
A16: Spread maximum profit incl costs | B16: =IF(Pricing!B36,(Inputs!B9-B14-Inputs!B12)*B11,NA()) -> 267606.53
A17: Spread break-even rally (bp) | B17: =IF(Pricing!B36,B14+Inputs!B12,NA()) -> 10.480891
A18: Outright wins beyond rally (bp) | B18: =IF(Pricing!B36,Inputs!B9+B13-B14,NA()) -> 31.476801
A20: Selected rate shift (bp) | B20: =Inputs!B21 -> -25
A21: Linear receiver P&L | B21: =(-B20-Inputs!B12)*B11 -> 442351.98
A22: Outright receiver P&L | B22: =(MAX(-B20,0)-B13-Inputs!B12)*B11 -> 148230.47
A23: Receiver spread P&L | B23: =IF(Pricing!B36,(MIN(MAX(-B20,0),Inputs!B9)-B14-Inputs!B12)*B11,NA()) -> 267606.53
A25: Structure state | B25: =IF(NOT(AND(Pricing!B4,Pricing!E4)),"BLOCKED",IF(NOT(Pricing!B36),"PASS: INCONSISTENT STRIKE VOLS",IF(B16<=0,"PASS: COST EXCEEDS CAPPED PAYOFF","CONDITIONAL COMPARISON; NO TRADE SIGNAL"))) -> CONDITIONAL COMPARISON; NO TRADE SIGNAL
A28: Compare same notional, not equal delta or risk. Expiry P&L is present-value-equivalent with frozen initial annuity. Costs are an assumed all-in rate-bp allowance per strategy. No probability-weighted return, collateral, calendar or early-exit valuation.
A31: Research call: pass an unconditional cash steepener. A bounded-rally view may favour a receiver spread, subject to premium, skew and costs. Larger rallies favour the outright receiver. Current data do not establish option cheapness.

Sheet Inputs
A1: Project 12 | Inputs
A4: Blue = editable | S sourced, A assumption, D derived
A5: Input | B5: Value | C5: Tag | D5: Meaning / units
A6: Notional (£) | B6: 100000000 | C6: A | D6: Illustrative sizing, not a proposed allocation
A7: expiry | B7: 0.25 | C7: A | D7: Synthetic quarter-year option expiry
A8: tenor | B8: 2 | C8: A | D8: Annual fixed payments; whole years, 1 to 10
A9: width_bp | B9: 25 | C9: A | D9: Sold receiver strike 25bp below ATM
A10: long_vol_bp | B10: 80 | C10: A | D10: Sensitivity assumption, not an observed option quote
A11: short_vol_bp | B11: 80 | C11: A | D11: Separate input permits skew sensitivity
A12: cost_bp | B12: 1 | C12: A | D12: All-in incremental cost per strategy, rate bp; replace with quote-based costs
A13: forward_mode | B13: 0 | C13: A | D13: 0 curve-derived; 1 dealer forward
A14: dealer_forward | C14: S | D14: Enter decimal forward for the same underlying schedule
A15: vol_mode | B15: 0 | C15: A | D15: 0 assumed; 1 dealer strike-specific normal vols
A16: dealer_long_vol_bp | C16: S | D16: Missing; no public executable quote found
A17: dealer_short_vol_bp | C17: S | D17: Missing; no public executable quote found
A18: quote_time | C18: S | D18: Missing; timestamp and timezone required for dealer mode
A19: quote_source | C19: S | D19: Missing; source and quote side required for dealer mode
A20: curve_shock_bp | B20: 0 | C20: A | D20: Parallel shock to all OIS zero rates
A21: scenario_shift_bp | B21: -25 | C21: A | D21: Expiry shift relative to selected forward, not a forecast
A24: Curve date | B24: 2026-10-27 | C24: S
A26: Default volatilities and costs are assumptions. Quote cells are blank. Mode 1 requires source and timestamp; missing data blocks valuation. Dealer mode does not establish an executable or attractive trade.

Sheet Curve
A1: Project 12 | Curve
A5: Years | B5: Zero rate (% continuous) | D5: S | BoE fitted OIS zero curve; percent continuous. Linear interpolation. No extrapolation. Source URL, retrieval date and hash are in Sources and data/curves.json.
A6: 0.08333333 | B6: 3.8993903
A7: 0.16666667 | B7: 3.9556859
A8: 0.25 | B8: 4.009726
A9: 0.33333333 | B9: 4.0667591
A10: 0.41666667 | B10: 4.1260827
A11: 0.5 | B11: 4.1854465
A12: 0.58333333 | B12: 4.2428703
A13: 0.66666667 | B13: 4.2972169
A14: 0.75 | B14: 4.3478766
A15: 0.83333333 | B15: 4.3947902
A16: 0.91666667 | B16: 4.4380719
A17: 1 | B17: 4.4778207
... A105: 25 | B105: 5.1237954

Sheet Pricing
A1: Project 12 | Pricing
A4: Basic inputs valid | B4: =AND(ISNUMBER(Inputs!B6),Inputs!B6>0,ISNUMBER(Inputs!B7),Inputs!B7>=1/12,Inputs!B7<=2,ISNUMBER(Inputs!B8),Inputs!B8=INT(Inputs!B8),Inputs!B8>=1,Inputs!B8<=10,ISNUMBER(Inputs!B9),Inputs!B9>0,ISNUMBER(Inputs!B10),Inputs!B10>=0,ISNUMBER(Inputs!B11),Inputs!B11>=0,ISNUMBER(Inputs!B12),Inputs!B12>=0,ISNUMBER(Inputs!B20),ISNUMBER(Inputs!B21),OR(Inputs!B13=0,Inputs!B13=1),OR(Inputs!B15=0,Inputs!B15=1)) -> TRUE | D4: Dealer fields valid | E4: =AND(IF(OR(Inputs!B13=1,Inputs!B15=1),AND(Inputs!B18<>"",Inputs!B19<>""),TRUE()),IF(Inputs!B13=1,ISNUMBER(Inputs!B14),TRUE()),IF(Inputs!B15=1,AND(ISNUMBER(Inputs!B16),Inputs!B16>=0,ISNUMBER(Inputs!B17),Inputs!B17>=0),TRUE())) -> TRUE
A5: Cash flow | B5: Time | C5: Index | D5: Lower t | E5: Upper t | F5: Lower z % | G5: Upper z % | H5: Zero % | I5: DF | J5: Alpha | K5: DF x alpha
A6: Option expiry | B6: =Inputs!B7 -> 0.25 | C6: =IF(AND(B6>=MIN(Curve!$A$6:$A$105),B6<=MAX(Curve!$A$6:$A$105)),MIN(ROWS(Curve!$A$6:$A$105)-1,MATCH(B6,Curve!$A$6:$A$105,1)),NA()) -> 3 | D6: =INDEX(Curve!$A$6:$A$105,C6) -> 0.25 | E6: =INDEX(Curve!$A$6:$A$105,C6+1) -> 0.33333333 | F6: =INDEX(Curve!$B$6:$B$105,C6) -> 4.009726 | G6: =INDEX(Curve!$B$6:$B$105,C6+1) -> 4.0667591 | H6: =F6+(G6-F6)*(B6-D6)/(E6-D6)+Inputs!B20/100 -> 4.009726 | I6: =EXP(-H6/100*B6) -> 0.99002576 | J6: =0 -> 0 | K6: =I6*J6 -> 0
A7: Payment 1 | B7: =IF(1<=Inputs!B8,Inputs!B7+1,Inputs!B7) -> 1.25 | C7: =IF(AND(B7>=MIN(Curve!$A$6:$A$105),B7<=MAX(Curve!$A$6:$A$105)),MIN(ROWS(Curve!$A$6:$A$105)-1,MATCH(B7,Curve!$A$6:$A$105,1)),NA()) -> 15 | D7: =INDEX(Curve!$A$6:$A$105,C7) -> 1.25 | E7: =INDEX(Curve!$A$6:$A$105,C7+1) -> 1.3333333 | F7: =INDEX(Curve!$B$6:$B$105,C7) -> 4.5768507 | G7: =INDEX(Curve!$B$6:$B$105,C7+1) -> 4.603534 | H7: =F7+(G7-F7)*(B7-D7)/(E7-D7)+Inputs!B20/100 -> 4.5768507 | I7: =EXP(-H7/100*B7) -> 0.94439513 | J7: =IF(1<=Inputs!B8,1,0) -> 1 | K7: =I7*J7 -> 0.94439513
A8: Payment 2 | B8: =IF(2<=Inputs!B8,Inputs!B7+2,Inputs!B7) -> 2.25 | C8: =IF(AND(B8>=MIN(Curve!$A$6:$A$105),B8<=MAX(Curve!$A$6:$A$105)),MIN(ROWS(Curve!$A$6:$A$105)-1,MATCH(B8,Curve!$A$6:$A$105,1)),NA()) -> 27 | D8: =INDEX(Curve!$A$6:$A$105,C8) -> 2.25 | E8: =INDEX(Curve!$A$6:$A$105,C8+1) -> 2.3333333 | F8: =INDEX(Curve!$B$6:$B$105,C8) -> 4.7450474 | G8: =INDEX(Curve!$B$6:$B$105,C8+1) -> 4.7487921 | H8: =F8+(G8-F8)*(B8-D8)/(E8-D8)+Inputs!B20/100 -> 4.7450474 | I8: =EXP(-H8/100*B8) -> 0.89873814 | J8: =IF(2<=Inputs!B8,1,0) -> 1 | K8: =I8*J8 -> 0.89873814
A9: Payment 3 | B9: =IF(3<=Inputs!B8,Inputs!B7+3,Inputs!B7) -> 0.25 | C9: =IF(AND(B9>=MIN(Curve!$A$6:$A$105),B9<=MAX(Curve!$A$6:$A$105)),MIN(ROWS(Curve!$A$6:$A$105)-1,MATCH(B9,Curve!$A$6:$A$105,1)),NA()) -> 3 | D9: =INDEX(Curve!$A$6:$A$105,C9) -> 0.25 | E9: =INDEX(Curve!$A$6:$A$105,C9+1) -> 0.33333333 | F9: =INDEX(Curve!$B$6:$B$105,C9) -> 4.009726 | G9: =INDEX(Curve!$B$6:$B$105,C9+1) -> 4.0667591 | H9: =F9+(G9-F9)*(B9-D9)/(E9-D9)+Inputs!B20/100 -> 4.009726 | I9: =EXP(-H9/100*B9) -> 0.99002576 | J9: =IF(3<=Inputs!B8,1,0) -> 0 | K9: =I9*J9 -> 0
A10: Payment 4 | B10: =IF(4<=Inputs!B8,Inputs!B7+4,Inputs!B7) -> 0.25 | C10: =IF(AND(B10>=MIN(Curve!$A$6:$A$105),B10<=MAX(Curve!$A$6:$A$105)),MIN(ROWS(Curve!$A$6:$A$105)-1,MATCH(B10,Curve!$A$6:$A$105,1)),NA()) -> 3 | D10: =INDEX(Curve!$A$6:$A$105,C10) -> 0.25 | E10: =INDEX(Curve!$A$6:$A$105,C10+1) -> 0.33333333 | F10: =INDEX(Curve!$B$6:$B$105,C10) -> 4.009726 | G10: =INDEX(Curve!$B$6:$B$105,C10+1) -> 4.0667591 | H10: =F10+(G10-F10)*(B10-D10)/(E10-D10)+Inputs!B20/100 -> 4.009726 | I10: =EXP(-H10/100*B10) -> 0.99002576 | J10: =IF(4<=Inputs!B8,1,0) -> 0 | K10: =I10*J10 -> 0
A11: Payment 5 | B11: =IF(5<=Inputs!B8,Inputs!B7+5,Inputs!B7) -> 0.25 | C11: =IF(AND(B11>=MIN(Curve!$A$6:$A$105),B11<=MAX(Curve!$A$6:$A$105)),MIN(ROWS(Curve!$A$6:$A$105)-1,MATCH(B11,Curve!$A$6:$A$105,1)),NA()) -> 3 | D11: =INDEX(Curve!$A$6:$A$105,C11) -> 0.25 | E11: =INDEX(Curve!$A$6:$A$105,C11+1) -> 0.33333333 | F11: =INDEX(Curve!$B$6:$B$105,C11) -> 4.009726 | G11: =INDEX(Curve!$B$6:$B$105,C11+1) -> 4.0667591 | H11: =F11+(G11-F11)*(B11-D11)/(E11-D11)+Inputs!B20/100 -> 4.009726 | I11: =EXP(-H11/100*B11) -> 0.99002576 | J11: =IF(5<=Inputs!B8,1,0) -> 0 | K11: =I11*J11 -> 0
A12: Payment 6 | B12: =IF(6<=Inputs!B8,Inputs!B7+6,Inputs!B7) -> 0.25 | C12: =IF(AND(B12>=MIN(Curve!$A$6:$A$105),B12<=MAX(Curve!$A$6:$A$105)),MIN(ROWS(Curve!$A$6:$A$105)-1,MATCH(B12,Curve!$A$6:$A$105,1)),NA()) -> 3 | D12: =INDEX(Curve!$A$6:$A$105,C12) -> 0.25 | E12: =INDEX(Curve!$A$6:$A$105,C12+1) -> 0.33333333 | F12: =INDEX(Curve!$B$6:$B$105,C12) -> 4.009726 | G12: =INDEX(Curve!$B$6:$B$105,C12+1) -> 4.0667591 | H12: =F12+(G12-F12)*(B12-D12)/(E12-D12)+Inputs!B20/100 -> 4.009726 | I12: =EXP(-H12/100*B12) -> 0.99002576 | J12: =IF(6<=Inputs!B8,1,0) -> 0 | K12: =I12*J12 -> 0
A13: Payment 7 | B13: =IF(7<=Inputs!B8,Inputs!B7+7,Inputs!B7) -> 0.25 | C13: =IF(AND(B13>=MIN(Curve!$A$6:$A$105),B13<=MAX(Curve!$A$6:$A$105)),MIN(ROWS(Curve!$A$6:$A$105)-1,MATCH(B13,Curve!$A$6:$A$105,1)),NA()) -> 3 | D13: =INDEX(Curve!$A$6:$A$105,C13) -> 0.25 | E13: =INDEX(Curve!$A$6:$A$105,C13+1) -> 0.33333333 | F13: =INDEX(Curve!$B$6:$B$105,C13) -> 4.009726 | G13: =INDEX(Curve!$B$6:$B$105,C13+1) -> 4.0667591 | H13: =F13+(G13-F13)*(B13-D13)/(E13-D13)+Inputs!B20/100 -> 4.009726 | I13: =EXP(-H13/100*B13) -> 0.99002576 | J13: =IF(7<=Inputs!B8,1,0) -> 0 | K13: =I13*J13 -> 0
A14: Payment 8 | B14: =IF(8<=Inputs!B8,Inputs!B7+8,Inputs!B7) -> 0.25 | C14: =IF(AND(B14>=MIN(Curve!$A$6:$A$105),B14<=MAX(Curve!$A$6:$A$105)),MIN(ROWS(Curve!$A$6:$A$105)-1,MATCH(B14,Curve!$A$6:$A$105,1)),NA()) -> 3 | D14: =INDEX(Curve!$A$6:$A$105,C14) -> 0.25 | E14: =INDEX(Curve!$A$6:$A$105,C14+1) -> 0.33333333 | F14: =INDEX(Curve!$B$6:$B$105,C14) -> 4.009726 | G14: =INDEX(Curve!$B$6:$B$105,C14+1) -> 4.0667591 | H14: =F14+(G14-F14)*(B14-D14)/(E14-D14)+Inputs!B20/100 -> 4.009726 | I14: =EXP(-H14/100*B14) -> 0.99002576 | J14: =IF(8<=Inputs!B8,1,0) -> 0 | K14: =I14*J14 -> 0
A15: Payment 9 | B15: =IF(9<=Inputs!B8,Inputs!B7+9,Inputs!B7) -> 0.25 | C15: =IF(AND(B15>=MIN(Curve!$A$6:$A$105),B15<=MAX(Curve!$A$6:$A$105)),MIN(ROWS(Curve!$A$6:$A$105)-1,MATCH(B15,Curve!$A$6:$A$105,1)),NA()) -> 3 | D15: =INDEX(Curve!$A$6:$A$105,C15) -> 0.25 | E15: =INDEX(Curve!$A$6:$A$105,C15+1) -> 0.33333333 | F15: =INDEX(Curve!$B$6:$B$105,C15) -> 4.009726 | G15: =INDEX(Curve!$B$6:$B$105,C15+1) -> 4.0667591 | H15: =F15+(G15-F15)*(B15-D15)/(E15-D15)+Inputs!B20/100 -> 4.009726 | I15: =EXP(-H15/100*B15) -> 0.99002576 | J15: =IF(9<=Inputs!B8,1,0) -> 0 | K15: =I15*J15 -> 0
A16: Payment 10 | B16: =IF(10<=Inputs!B8,Inputs!B7+10,Inputs!B7) -> 0.25 | C16: =IF(AND(B16>=MIN(Curve!$A$6:$A$105),B16<=MAX(Curve!$A$6:$A$105)),MIN(ROWS(Curve!$A$6:$A$105)-1,MATCH(B16,Curve!$A$6:$A$105,1)),NA()) -> 3 | D16: =INDEX(Curve!$A$6:$A$105,C16) -> 0.25 | E16: =INDEX(Curve!$A$6:$A$105,C16+1) -> 0.33333333 | F16: =INDEX(Curve!$B$6:$B$105,C16) -> 4.009726 | G16: =INDEX(Curve!$B$6:$B$105,C16+1) -> 4.0667591 | H16: =F16+(G16-F16)*(B16-D16)/(E16-D16)+Inputs!B20/100 -> 4.009726 | I16: =EXP(-H16/100*B16) -> 0.99002576 | J16: =IF(10<=Inputs!B8,1,0) -> 0 | K16: =I16*J16 -> 0
A17: Underlying maturity | B17: =Inputs!B7+Inputs!B8 -> 2.25 | C17: =IF(AND(B17>=MIN(Curve!$A$6:$A$105),B17<=MAX(Curve!$A$6:$A$105)),MIN(ROWS(Curve!$A$6:$A$105)-1,MATCH(B17,Curve!$A$6:$A$105,1)),NA()) -> 27 | D17: =INDEX(Curve!$A$6:$A$105,C17) -> 2.25 | E17: =INDEX(Curve!$A$6:$A$105,C17+1) -> 2.3333333 | F17: =INDEX(Curve!$B$6:$B$105,C17) -> 4.7450474 | G17: =INDEX(Curve!$B$6:$B$105,C17+1) -> 4.7487921 | H17: =F17+(G17-F17)*(B17-D17)/(E17-D17)+Inputs!B20/100 -> 4.7450474 | I17: =EXP(-H17/100*B17) -> 0.89873814 | J17: =0 -> 0 | K17: =I17*J17 -> 0
A21: Curve forward | B21: =(I6-I17)/B22 -> 0.049528497 | D21: Synthetic annual-pay swap. Dealer forward must reference the same underlying. Annuity is curve-derived even in dealer mode. Zero-vol kink delta uses half-delta convention. A negative vertical value flags inconsistent strike vols, not an arbitrage trade.
A22: Discount annuity | B22: =SUM(K7:K16) -> 1.8431333
A23: PV01 (£ per bp) | B23: =Inputs!B6*B22/10000 -> 18431.333
A24: Selected forward | B24: =IF(AND(B4,E4),IF(Inputs!B13=1,Inputs!B14,B21),NA()) -> 0.049528497
A25: Long normal vol (bp) | B25: =IF(AND(B4,E4),IF(Inputs!B15=1,Inputs!B16,Inputs!B10),NA()) -> 80
A26: Short normal vol (bp) | B26: =IF(AND(B4,E4),IF(Inputs!B15=1,Inputs!B17,Inputs!B11),NA()) -> 80
A27: Long strike | B27: =B24 -> 0.049528497
A28: Short strike | B28: =B27-Inputs!B9/10000 -> 0.047028497
A29: Long rate std dev | B29: =B25/10000*SQRT(Inputs!B7) -> 0.004
A30: Short rate std dev | B30: =B26/10000*SQRT(Inputs!B7) -> 0.004
A31: Long d | B31: =IF(B29=0,0,(B27-B24)/B29) -> 0
A32: Short d | B32: =IF(B30=0,0,(B28-B24)/B30) -> -0.625
A33: Long receiver value (rate) | B33: =IF(B29=0,MAX(B27-B24,0),(B27-B24)*NORMSDIST(B31)+B29*EXP(-(B31^2)/2)/SQRT(2*PI())) -> 0.0015957691
A34: Sold receiver value (rate) | B34: =IF(B30=0,MAX(B28-B24,0),(B28-B24)*NORMSDIST(B32)+B30*EXP(-(B32^2)/2)/SQRT(2*PI())) -> 0.00064768005
A35: Spread value (rate) | B35: =B33-B34 -> 0.00094808907
A36: Vertical bounds valid | B36: =AND(B35>=0,B35<=Inputs!B9/10000) -> TRUE
A38: Outright delta (£ / rate bp) | B38: =IF(B29=0,-0.5,-NORMSDIST(B31))*B23 -> -9215.6663
A39: Spread delta (£ / rate bp) | B39: =B38-IF(B30=0,0,-NORMSDIST(B32)*B23) -> -4313.1986
A40: Outright vega (£ / norm bp) | B40: =IF(B29=0,0,Inputs!B6*B22*SQRT(Inputs!B7)*EXP(-(B31^2)/2)/SQRT(2*PI())/10000) -> 3676.5189
A41: Spread parallel vega | B41: =B40-IF(B30=0,0,Inputs!B6*B22*SQRT(Inputs!B7)*EXP(-(B32^2)/2)/SQRT(2*PI())/10000) -> 652.29695

Sheet Scenarios
A1: Project 12 | Scenarios
A5: Rate shift (bp) | B5: Linear £ | C5: Outright £ | D5: Spread £ | E5: Spread - outright £
A6: -100 | B6: =(-A6-Inputs!$B$12)*Pricing!$B$23 -> 1824701.9 | C6: =(MAX(-A6,0)-Summary!$B$13-Inputs!$B$12)*Pricing!$B$23 -> 1530580.4 | D6: =IF(Pricing!$B$36,(MIN(MAX(-A6,0),Inputs!$B$9)-Summary!$B$14-Inputs!$B$12)*Pricing!$B$23,NA()) -> 267606.53 | E6: =D6-C6 -> -1262973.9
A7: -75 | B7: =(-A7-Inputs!$B$12)*Pricing!$B$23 -> 1363918.6 | C7: =(MAX(-A7,0)-Summary!$B$13-Inputs!$B$12)*Pricing!$B$23 -> 1069797.1 | D7: =IF(Pricing!$B$36,(MIN(MAX(-A7,0),Inputs!$B$9)-Summary!$B$14-Inputs!$B$12)*Pricing!$B$23,NA()) -> 267606.53 | E7: =D7-C7 -> -802190.57
A8: -50 | B8: =(-A8-Inputs!$B$12)*Pricing!$B$23 -> 903135.3 | C8: =(MAX(-A8,0)-Summary!$B$13-Inputs!$B$12)*Pricing!$B$23 -> 609013.79 | D8: =IF(Pricing!$B$36,(MIN(MAX(-A8,0),Inputs!$B$9)-Summary!$B$14-Inputs!$B$12)*Pricing!$B$23,NA()) -> 267606.53 | E8: =D8-C8 -> -341407.25
A9: -25 | B9: =(-A9-Inputs!$B$12)*Pricing!$B$23 -> 442351.98 | C9: =(MAX(-A9,0)-Summary!$B$13-Inputs!$B$12)*Pricing!$B$23 -> 148230.47 | D9: =IF(Pricing!$B$36,(MIN(MAX(-A9,0),Inputs!$B$9)-Summary!$B$14-Inputs!$B$12)*Pricing!$B$23,NA()) -> 267606.53 | E9: =D9-C9 -> 119376.06
A10: -10 | B10: =(-A10-Inputs!$B$12)*Pricing!$B$23 -> 165881.99 | C10: =(MAX(-A10,0)-Summary!$B$13-Inputs!$B$12)*Pricing!$B$23 -> -128239.52 | D10: =IF(Pricing!$B$36,(MIN(MAX(-A10,0),Inputs!$B$9)-Summary!$B$14-Inputs!$B$12)*Pricing!$B$23,NA()) -> -8863.4565 | E10: =D10-C10 -> 119376.06
A11: 0 | B11: =(-A11-Inputs!$B$12)*Pricing!$B$23 -> -18431.333 | C11: =(MAX(-A11,0)-Summary!$B$13-Inputs!$B$12)*Pricing!$B$23 -> -312552.85 | D11: =IF(Pricing!$B$36,(MIN(MAX(-A11,0),Inputs!$B$9)-Summary!$B$14-Inputs!$B$12)*Pricing!$B$23,NA()) -> -193176.78 | E11: =D11-C11 -> 119376.06
A12: 10 | B12: =(-A12-Inputs!$B$12)*Pricing!$B$23 -> -202744.66 | C12: =(MAX(-A12,0)-Summary!$B$13-Inputs!$B$12)*Pricing!$B$23 -> -312552.85 | D12: =IF(Pricing!$B$36,(MIN(MAX(-A12,0),Inputs!$B$9)-Summary!$B$14-Inputs!$B$12)*Pricing!$B$23,NA()) -> -193176.78 | E12: =D12-C12 -> 119376.06
A13: 25 | B13: =(-A13-Inputs!$B$12)*Pricing!$B$23 -> -479214.65 | C13: =(MAX(-A13,0)-Summary!$B$13-Inputs!$B$12)*Pricing!$B$23 -> -312552.85 | D13: =IF(Pricing!$B$36,(MIN(MAX(-A13,0),Inputs!$B$9)-Summary!$B$14-Inputs!$B$12)*Pricing!$B$23,NA()) -> -193176.78 | E13: =D13-C13 -> 119376.06
A14: 50 | B14: =(-A14-Inputs!$B$12)*Pricing!$B$23 -> -939997.97 | C14: =(MAX(-A14,0)-Summary!$B$13-Inputs!$B$12)*Pricing!$B$23 -> -312552.85 | D14: =IF(Pricing!$B$36,(MIN(MAX(-A14,0),Inputs!$B$9)-Summary!$B$14-Inputs!$B$12)*Pricing!$B$23,NA()) -> -193176.78 | E14: =D14-C14 -> 119376.06
A15: 75 | B15: =(-A15-Inputs!$B$12)*Pricing!$B$23 -> -1400781.3 | C15: =(MAX(-A15,0)-Summary!$B$13-Inputs!$B$12)*Pricing!$B$23 -> -312552.85 | D15: =IF(Pricing!$B$36,(MIN(MAX(-A15,0),Inputs!$B$9)-Summary!$B$14-Inputs!$B$12)*Pricing!$B$23,NA()) -> -193176.78 | E15: =D15-C15 -> 119376.06
A16: 100 | B16: =(-A16-Inputs!$B$12)*Pricing!$B$23 -> -1861564.6 | C16: =(MAX(-A16,0)-Summary!$B$13-Inputs!$B$12)*Pricing!$B$23 -> -312552.85 | D16: =IF(Pricing!$B$36,(MIN(MAX(-A16,0),Inputs!$B$9)-Summary!$B$14-Inputs!$B$12)*Pricing!$B$23,NA()) -> -193176.78 | E16: =D16-C16 -> 119376.06
A39: Rate shifts are scenarios, not forecasts. Premium deducted once; frozen-annuity PV-equivalent outputs. A linear swap has uncapped loss; receiver spread loss is capped at debit only when vertical bounds are valid.

Sheet Sensitivity
A1: Project 12 | Sensitivity
A5: Flat normal vol (bp) | B5: ATM cost bp | C5: OTM cost bp | D5: Spread cost bp | E5: Max net gain bp | F5: Crossover rally bp
A6: 0 | B6: =A6*SQRT(Inputs!$B$7)/SQRT(2*PI()) -> 0 | C6: =IF(A6=0,0,-Inputs!$B$9*NORMSDIST(-Inputs!$B$9/(A6*SQRT(Inputs!$B$7)))+A6*SQRT(Inputs!$B$7)*EXP(-0.5*(Inputs!$B$9/(A6*SQRT(Inputs!$B$7)))^2)/SQRT(2*PI())) -> 0 | D6: =B6-C6 -> 0 | E6: =Inputs!$B$9-D6-Inputs!$B$12 -> 24 | F6: =Inputs!$B$9+B6-D6 -> 25
A7: 40 | B7: =A7*SQRT(Inputs!$B$7)/SQRT(2*PI()) -> 7.9788456 | C7: =IF(A7=0,0,-Inputs!$B$9*NORMSDIST(-Inputs!$B$9/(A7*SQRT(Inputs!$B$7)))+A7*SQRT(Inputs!$B$7)*EXP(-0.5*(Inputs!$B$9/(A7*SQRT(Inputs!$B$7)))^2)/SQRT(2*PI())) -> 1.0117374 | D7: =B7-C7 -> 6.9671082 | E7: =Inputs!$B$9-D7-Inputs!$B$12 -> 17.032892 | F7: =Inputs!$B$9+B7-D7 -> 26.011737
A8: 60 | B8: =A8*SQRT(Inputs!$B$7)/SQRT(2*PI()) -> 11.968268 | C8: =IF(A8=0,0,-Inputs!$B$9*NORMSDIST(-Inputs!$B$9/(A8*SQRT(Inputs!$B$7)))+A8*SQRT(Inputs!$B$7)*EXP(-0.5*(Inputs!$B$9/(A8*SQRT(Inputs!$B$7)))^2)/SQRT(2*PI())) -> 3.3991467 | D8: =B8-C8 -> 8.5691217 | E8: =Inputs!$B$9-D8-Inputs!$B$12 -> 15.430878 | F8: =Inputs!$B$9+B8-D8 -> 28.399147
A9: 80 | B9: =A9*SQRT(Inputs!$B$7)/SQRT(2*PI()) -> 15.957691 | C9: =IF(A9=0,0,-Inputs!$B$9*NORMSDIST(-Inputs!$B$9/(A9*SQRT(Inputs!$B$7)))+A9*SQRT(Inputs!$B$7)*EXP(-0.5*(Inputs!$B$9/(A9*SQRT(Inputs!$B$7)))^2)/SQRT(2*PI())) -> 6.4768005 | D9: =B9-C9 -> 9.4808907 | E9: =Inputs!$B$9-D9-Inputs!$B$12 -> 14.519109 | F9: =Inputs!$B$9+B9-D9 -> 31.476801
A10: 100 | B10: =A10*SQRT(Inputs!$B$7)/SQRT(2*PI()) -> 19.947114 | C10: =IF(A10=0,0,-Inputs!$B$9*NORMSDIST(-Inputs!$B$9/(A10*SQRT(Inputs!$B$7)))+A10*SQRT(Inputs!$B$7)*EXP(-0.5*(Inputs!$B$9/(A10*SQRT(Inputs!$B$7)))^2)/SQRT(2*PI())) -> 9.8898279 | D10: =B10-C10 -> 10.057286 | E10: =Inputs!$B$9-D10-Inputs!$B$12 -> 13.942714 | F10: =Inputs!$B$9+B10-D10 -> 34.889828
A11: 120 | B11: =A11*SQRT(Inputs!$B$7)/SQRT(2*PI()) -> 23.936537 | C11: =IF(A11=0,0,-Inputs!$B$9*NORMSDIST(-Inputs!$B$9/(A11*SQRT(Inputs!$B$7)))+A11*SQRT(Inputs!$B$7)*EXP(-0.5*(Inputs!$B$9/(A11*SQRT(Inputs!$B$7)))^2)/SQRT(2*PI())) -> 13.484814 | D11: =B11-C11 -> 10.451723 | E11: =Inputs!$B$9-D11-Inputs!$B$12 -> 13.548277 | F11: =Inputs!$B$9+B11-D11 -> 38.484814
A12: 160 | B12: =A12*SQRT(Inputs!$B$7)/SQRT(2*PI()) -> 31.915382 | C12: =IF(A12=0,0,-Inputs!$B$9*NORMSDIST(-Inputs!$B$9/(A12*SQRT(Inputs!$B$7)))+A12*SQRT(Inputs!$B$7)*EXP(-0.5*(Inputs!$B$9/(A12*SQRT(Inputs!$B$7)))^2)/SQRT(2*PI())) -> 20.961191 | D12: =B12-C12 -> 10.954191 | E12: =Inputs!$B$9-D12-Inputs!$B$12 -> 13.045809 | F12: =Inputs!$B$9+B12-D12 -> 45.961191
A15: Sensitivity grid assumes the same vol for both strikes. Active pricing permits different long/short vols on Inputs. No calibration or observed market vol is claimed.

Sheet Sources
A1: Project 12 | Sources
A5: Tag | B5: Source | C5: Data date | D5: URL | E5: Use / limitation
A6: S | B6: BoE OIS continuous zero curve | C6: 2026-10-27 | D6: https://www.bankofengland.co.uk/-/media/boe/files/statistics/yield-curves/latest-yield-curve-data.zip?download=1 | E6: Downloaded 28 Oct 2026. Fitted and revisable; not dealer quotes.
A7: S | B7: BoE curve methodology | C7: 2026-10-28 | D7: https://www.bankofengland.co.uk/statistics/yield-curves | E7: Rates percent continuous; publication normally following business day.
A8: S | B8: Budget 2026, section 8.3/Table A.1 | C8: 2026-10-28 | D8: https://www.gov.uk/government/publications/budget-2026-document/budget-2026-html | E8: April-to-Budget allocation comparison is not an announcement surprise.
A9: S | B9: ONS September CPI | C9: 2026-10-21 | D9: https://www.ons.gov.uk/economy/inflationandpriceindices/bulletins/consumerpriceinflation/september2026 | E9: CPI 3.5%; does not establish an easing forecast.
A10: S | B10: September MPC | C10: 2026-09-17 | D10: https://www.bankofengland.co.uk/monetary-policy-summary-and-minutes/2026/september-2026 | E10: Bank Rate 3.75%; 6-3 hold; three preferred a hike.
A11: S | B11: Dealer option surface | C11: Unavailable | E11: No executable OTC 3m2y SONIA strike vols obtained. Do not substitute futures-option or realised vol.
