Workbook

Sheet Cover
C2: EQT / Range Resources | H2: Case selected | I2: =Inputs!D46 -> Base
C3: Announcement: 26 Oct 2026. Earnings: LTM Jun 2026. USDm / million shares.
C5: Announcement analysis | D5: Result
C6: Call | D6: =IF(Value!D14<0,"REJECT AS PRICED","ACCEPT ON MODEL ASSUMPTIONS") -> REJECT AS PRICED
C8: Year 1 EPS effect including costs | D8: =Merger!D30 -> -0.073568308
C9: Year 3 recurring EPS effect | D9: =Merger!F27 -> 0.012504761
C10: Company-adjusted year 3, before PPA | D10: =Merger!F32 -> 0.043555647
C11: EPS break-even annual synergies | D11: =Merger!D17 -> 265.55595
C12: Value break-even annual synergies | D12: =Value!D15 -> 343.89893
C13: Value surplus, perpetuity (USDm) | D13: =Value!D14 -> -135.29918
C14: Value surplus, 15 years (USDm) | D14: =Value!D18 -> -718.8173
C15: Value break-even exchange ratio | D15: =Value!D16 -> 0.97670354
G18: LTM earnings held constant over three full post-close years. These are earnings lenses, not calendar forecasts or consensus estimates.
G20: Closing share counts, primary price verification, final purchase accounting and integration plan are review items. Completion subject to approvals, expected Q1 2027.
G22: Change the case on Inputs. Down stresses Range earnings by 20% and captures half the synergy target. EQT earnings stay constant; no implied Henry Hub forecast.

Sheet Inputs
C2: Inputs
C3: Announcement: 26 Oct 2026. Earnings: LTM Jun 2026. USDm / million shares.
C5: Input | D5: Value | E5: Units | F5: Tag | G5: Source / reasoning
C6: Exchange ratio | D6: 0.987 | E6: EQT/RRC | F6: S | G6: DEAL: fixed stock exchange, not a cash offer
C7: Annual base synergy target | D7: 325 | E7: USDm | F7: S | G7: DEAL: within two years; >600 long-term pathway excluded
C8: EQT Q2 diluted weighted shares | D8: 629.049 | E8: m shares | F8: S | G8: E26: 629,049 thousand; A: closing share-count proxy
C9: Range Q2 diluted weighted shares | D9: 236.21 | E9: m shares | F9: S | G9: R26 p9: 236,210 thousand; A: shares exchanged proxy, includes dilutive awards
C10: EQT reference price proxy | D10: 55.63 | E10: USD/share | F10: A | G10: PRICE: 54.91 / 0.987 rounded; manual proxy, not independently verified exchange close
C11: Range unaffected price proxy | D11: 45.53 | E11: USD/share | F11: A | G11: PRICE: 54.91 / 1.206 rounded; manual proxy, value conclusion provisional pending primary prices
C12: EQT adjusted NI FY2025 | D12: 1879.156 | E12: USDm | F12: S | G12: E25: attributable to EQT; excludes noncontrolling interests
C13: EQT adjusted NI H1 2026 | D13: 1708.344 | E13: USDm | F13: S | G13: E26: attributable to EQT
C14: EQT adjusted NI H1 2025 | D14: 986.283 | E14: USDm | F14: S | G14: E26: comparable prior six months
C15: EQT GAAP NI FY2025 | D15: 2039.247 | E15: USDm | F15: S | G15: E25: attributable to EQT
C16: EQT GAAP NI H1 2026 | D16: 1698.654 | E16: USDm | F16: S | G16: E26: attributable to EQT
C17: EQT GAAP NI H1 2025 | D17: 1026.286 | E17: USDm | F17: S | G17: E26: attributable to EQT
... C41: Up: synergy target realised | D41: 1 | E41: % | F41: A | G41: No speculative long-term synergy uplift
C44: Active Range earnings multiplier | D44: =CHOOSE(Inputs!$D$35,Inputs!$D$36,Inputs!$D$37,Inputs!$D$38) -> 1
C45: Active synergy target realised | D45: =CHOOSE(Inputs!$D$35,Inputs!$D$39,Inputs!$D$40,Inputs!$D$41) -> 1
C46: Case selected | D46: =CHOOSE(Inputs!$D$35,"Down","Base","Up") -> Base

Sheet Merger
C2: Merger | H2: Case selected | I2: =Inputs!D46 -> Base
C3: Announcement: 26 Oct 2026. Earnings: LTM Jun 2026. USDm / million shares.
C5: Transaction / earnings bridge | D5: Value
C6: EQT standalone normalised earnings | D6: =History!G6 -> 2601.217 | G6: Normalised lens retains Range stock compensation at an assumed 25% tax rate. Other company non-GAAP adjustments are retained.
C7: Range adjusted earnings | D7: =History!G8 -> 875.606
C8: Range SBC retained, after tax | D8: =History!G10*(1-Inputs!$D$27) -> 35.70525
C9: Range normalised earnings, active case | D9: =(D7-D8)*Inputs!D44 -> 839.90075
C10: EQT diluted shares, closing proxy | D10: =Inputs!$D$8 -> 629.049
C11: New EQT shares, exchange proxy | D11: =Inputs!$D$9*Inputs!$D$6 -> 233.13927 | G11: Actual closing shares and award conversion remain unverified. Shares issued are not the disclosed final number.
C12: Combined diluted shares | D12: =SUM(D10:D11) -> 862.18827
C13: Range ownership | D13: =D11/D12 -> 0.27040413
C14: EQT standalone normalised EPS | D14: =D6/D10 -> 4.135158
C15: Annual incremental DD&A | D15: =Inputs!$D$28/Inputs!$D$29 -> 100 | G15: Illustrative purchase accounting: USD1,500m step-up / 15 years. Switch step-up to zero to isolate the impact.
C16: No-synergy recurring accretion | D16: =((D6+D9-D15*(1-Inputs!$D$27))/D12)/D14-1 -> -0.05586285
C17: EPS break-even annual pre-tax synergies | D17: =(D14*D11-D9)/(1-Inputs!$D$27)+D15 -> 265.55595
C20: Full post-close years | D20: Year 1 | E20: Year 2 | F20: Year 3
C21: Average synergy capture | D21: =Inputs!$D$33 -> 0.5 | E21: =1 -> 1 | F21: =1 -> 1
C22: Pre-tax synergies | D22: =Inputs!$D$7*Inputs!$D$45*D21 -> 162.5 | E22: =Inputs!$D$7*Inputs!$D$45*E21 -> 325 | F22: =Inputs!$D$7*Inputs!$D$45*F21 -> 325
C23: Integration costs, cash and P&L | D23: =Inputs!$D$30*Inputs!$D$34 -> 180 | E23: =Inputs!$D$30*(1-Inputs!$D$34) -> 120 | F23: =0 -> 0
C24: Transaction fees, P&L | D24: =Inputs!$D$31 -> 50 | E24: =0 -> 0 | F24: =0 -> 0
C25: Normalised recurring net income | D25: =$D$6+$D$9+(D22-$D$15)*(1-Inputs!$D$27) -> 3487.9927 | E25: =$D$6+$D$9+(E22-$D$15)*(1-Inputs!$D$27) -> 3609.8677 | F25: =$D$6+$D$9+(F22-$D$15)*(1-Inputs!$D$27) -> 3609.8677
C26: Normalised recurring EPS | D26: =D25/$D$12 -> 4.0455117 | E26: =E25/$D$12 -> 4.1868672 | F26: =F25/$D$12 -> 4.1868672
C27: Normalised recurring accretion | D27: =D26/$D$14-1 -> -0.021679044 | E27: =E26/$D$14-1 -> 0.012504761 | F27: =F26/$D$14-1 -> 0.012504761
C28: Net income including one-off costs | D28: =D25-D23*(1-Inputs!$D$27)-D24 -> 3302.9927 | E28: =E25-E23*(1-Inputs!$D$27)-E24 -> 3519.8677 | F28: =F25-F23*(1-Inputs!$D$27)-F24 -> 3609.8677 | G28: One-offs reduce earnings and cash. No acquisition cash payment or new financing interest: stock consideration only; existing debt interest remains in earnings.
C29: EPS including one-off costs | D29: =D28/$D$12 -> 3.8309414 | E29: =E28/$D$12 -> 4.0824816 | F29: =F28/$D$12 -> 4.1868672
C30: Accretion including one-off costs | D30: =D29/$D$14-1 -> -0.073568308 | E30: =E29/$D$14-1 -> -0.012738664 | F30: =F29/$D$14-1 -> 0.012504761
C31: Company-adjusted EPS, before PPA | D31: =($D$6+$D$7*Inputs!$D$44+D22*(1-Inputs!$D$27))/$D$12 -> 4.173912 | E31: =($D$6+$D$7*Inputs!$D$44+E22*(1-Inputs!$D$27))/$D$12 -> 4.3152675 | F31: =($D$6+$D$7*Inputs!$D$44+F22*(1-Inputs!$D$27))/$D$12 -> 4.3152675
C32: Company-adjusted accretion, before PPA | D32: =D31/$D$14-1 -> 0.0093718418 | E32: =E31/$D$14-1 -> 0.043555647 | F32: =F31/$D$14-1 -> 0.043555647
C33: GAAP earnings lens incl costs, EPS | D33: =(History!$G$7+History!$G$9*Inputs!$D$44+(D22-$D$15-D23)*(1-Inputs!$D$27 )-D24)/$D$12 -> 3.9826997 | E33: =(History!$G$7+History!$G$9*Inputs!$D$44+(E22-$D$15-E23)*(1-Inputs!$D$27 )-E24)/$D$12 -> 4.2342399 | F33: =(History!$G$7+History!$G$9*Inputs!$D$44+(F22-$D$15-F23)*(1-Inputs!$D$27 )-F24)/$D$12 -> 4.3386255 | G33: Uses historical GAAP NI plus illustrative adjustments. Not GAAP pro forma EPS: final PPA, deferred taxes, debt fair values and closing stub unavailable.
C34: GAAP earnings lens incl costs, accretion | D34: =D33/(History!$G$7/$D$10)-1 -> -0.076080753 | E34: =E33/(History!$G$7/$D$10)-1 -> -0.017727666 | F34: =F33/(History!$G$7/$D$10)-1 -> 0.0064880235

Sheet Sensitivity
C2: Sensitivity | H2: Case selected | I2: =Inputs!D46 -> Base
C3: Announcement: 26 Oct 2026. Earnings: LTM Jun 2026. USDm / million shares.
C4: Assumed ratios down / annual pre-tax synergies across (USDm)
C5: Year 3 recurring accretion | D5: 0 | E5: 162.5 | F5: 250 | G5: 325 | H5: 450 | I5: 600
C6: 0.8 | D6: =(Merger!$D$6+Merger!$D$9+(D$5-Merger!$D$15)*(1-Inputs!$D$27))/(Merger!$D$10+Inputs!$D$9*$C6)/Merger!$D$14-1 -> -0.0048813461 | E6: =(Merger!$D$6+Merger!$D$9+(E$5-Merger!$D$15)*(1-Inputs!$D$27))/(Merger!$D$10+Inputs!$D$9*$C6)/Merger!$D$14-1 -> 0.031148316 | F6: =(Merger!$D$6+Merger!$D$9+(F$5-Merger!$D$15)*(1-Inputs!$D$27))/(Merger!$D$10+Inputs!$D$9*$C6)/Merger!$D$14-1 -> 0.050548904 | G6: =(Merger!$D$6+Merger!$D$9+(G$5-Merger!$D$15)*(1-Inputs!$D$27))/(Merger!$D$10+Inputs!$D$9*$C6)/Merger!$D$14-1 -> 0.067177979 | H6: =(Merger!$D$6+Merger!$D$9+(H$5-Merger!$D$15)*(1-Inputs!$D$27))/(Merger!$D$10+Inputs!$D$9*$C6)/Merger!$D$14-1 -> 0.094893103 | I6: =(Merger!$D$6+Merger!$D$9+(I$5-Merger!$D$15)*(1-Inputs!$D$27))/(Merger!$D$10+Inputs!$D$9*$C6)/Merger!$D$14-1 -> 0.12815125
C7: 0.9 | D7: =(Merger!$D$6+Merger!$D$9+(D$5-Merger!$D$15)*(1-Inputs!$D$27))/(Merger!$D$10+Inputs!$D$9*$C7)/Merger!$D$14-1 -> -0.032809859 | E7: =(Merger!$D$6+Merger!$D$9+(E$5-Merger!$D$15)*(1-Inputs!$D$27))/(Merger!$D$10+Inputs!$D$9*$C7)/Merger!$D$14-1 -> 0.0022086125 | F7: =(Merger!$D$6+Merger!$D$9+(F$5-Merger!$D$15)*(1-Inputs!$D$27))/(Merger!$D$10+Inputs!$D$9*$C7)/Merger!$D$14-1 -> 0.021064713 | G7: =(Merger!$D$6+Merger!$D$9+(G$5-Merger!$D$15)*(1-Inputs!$D$27))/(Merger!$D$10+Inputs!$D$9*$C7)/Merger!$D$14-1 -> 0.037227084 | H7: =(Merger!$D$6+Merger!$D$9+(H$5-Merger!$D$15)*(1-Inputs!$D$27))/(Merger!$D$10+Inputs!$D$9*$C7)/Merger!$D$14-1 -> 0.06416437 | I7: =(Merger!$D$6+Merger!$D$9+(I$5-Merger!$D$15)*(1-Inputs!$D$27))/(Merger!$D$10+Inputs!$D$9*$C7)/Merger!$D$14-1 -> 0.096489113
C8: 0.987 | D8: =(Merger!$D$6+Merger!$D$9+(D$5-Merger!$D$15)*(1-Inputs!$D$27))/(Merger!$D$10+Inputs!$D$9*$C8)/Merger!$D$14-1 -> -0.05586285 | E8: =(Merger!$D$6+Merger!$D$9+(E$5-Merger!$D$15)*(1-Inputs!$D$27))/(Merger!$D$10+Inputs!$D$9*$C8)/Merger!$D$14-1 -> -0.021679044 | F8: =(Merger!$D$6+Merger!$D$9+(F$5-Merger!$D$15)*(1-Inputs!$D$27))/(Merger!$D$10+Inputs!$D$9*$C8)/Merger!$D$14-1 -> -0.0032723798 | G8: =(Merger!$D$6+Merger!$D$9+(G$5-Merger!$D$15)*(1-Inputs!$D$27))/(Merger!$D$10+Inputs!$D$9*$C8)/Merger!$D$14-1 -> 0.012504761 | H8: =(Merger!$D$6+Merger!$D$9+(H$5-Merger!$D$15)*(1-Inputs!$D$27))/(Merger!$D$10+Inputs!$D$9*$C8)/Merger!$D$14-1 -> 0.038799996 | I8: =(Merger!$D$6+Merger!$D$9+(I$5-Merger!$D$15)*(1-Inputs!$D$27))/(Merger!$D$10+Inputs!$D$9*$C8)/Merger!$D$14-1 -> 0.070354279
C9: 1.05 | D9: =(Merger!$D$6+Merger!$D$9+(D$5-Merger!$D$15)*(1-Inputs!$D$27))/(Merger!$D$10+Inputs!$D$9*$C9)/Merger!$D$14-1 -> -0.071882016 | E9: =(Merger!$D$6+Merger!$D$9+(E$5-Merger!$D$15)*(1-Inputs!$D$27))/(Merger!$D$10+Inputs!$D$9*$C9)/Merger!$D$14-1 -> -0.038278207 | F9: =(Merger!$D$6+Merger!$D$9+(F$5-Merger!$D$15)*(1-Inputs!$D$27))/(Merger!$D$10+Inputs!$D$9*$C9)/Merger!$D$14-1 -> -0.020183848 | G9: =(Merger!$D$6+Merger!$D$9+(G$5-Merger!$D$15)*(1-Inputs!$D$27))/(Merger!$D$10+Inputs!$D$9*$C9)/Merger!$D$14-1 -> -0.0046743975 | H9: =(Merger!$D$6+Merger!$D$9+(H$5-Merger!$D$15)*(1-Inputs!$D$27))/(Merger!$D$10+Inputs!$D$9*$C9)/Merger!$D$14-1 -> 0.021174687 | I9: =(Merger!$D$6+Merger!$D$9+(I$5-Merger!$D$15)*(1-Inputs!$D$27))/(Merger!$D$10+Inputs!$D$9*$C9)/Merger!$D$14-1 -> 0.052193588
C10: 1.1 | D10: =(Merger!$D$6+Merger!$D$9+(D$5-Merger!$D$15)*(1-Inputs!$D$27))/(Merger!$D$10+Inputs!$D$9*$C10)/Merger!$D$14-1 -> -0.084213869 | E10: =(Merger!$D$6+Merger!$D$9+(E$5-Merger!$D$15)*(1-Inputs!$D$27))/(Merger!$D$10+Inputs!$D$9*$C10)/Merger!$D$14-1 -> -0.051056552 | F10: =(Merger!$D$6+Merger!$D$9+(F$5-Merger!$D$15)*(1-Inputs!$D$27))/(Merger!$D$10+Inputs!$D$9*$C10)/Merger!$D$14-1 -> -0.033202612 | G10: =(Merger!$D$6+Merger!$D$9+(G$5-Merger!$D$15)*(1-Inputs!$D$27))/(Merger!$D$10+Inputs!$D$9*$C10)/Merger!$D$14-1 -> -0.017899234 | H10: =(Merger!$D$6+Merger!$D$9+(H$5-Merger!$D$15)*(1-Inputs!$D$27))/(Merger!$D$10+Inputs!$D$9*$C10)/Merger!$D$14-1 -> 0.0076063944 | I10: =(Merger!$D$6+Merger!$D$9+(I$5-Merger!$D$15)*(1-Inputs!$D$27))/(Merger!$D$10+Inputs!$D$9*$C10)/Merger!$D$14-1 -> 0.038213149
G13: Live simple formula: current case earnings and DD&A, absolute synergy amounts. 600m is sensitivity only. Grid omits one-off costs.

Sheet Value
C2: Value | H2: Case selected | I2: =Inputs!D46 -> Base
C3: Announcement: 26 Oct 2026. Earnings: LTM Jun 2026. USDm / million shares.
C5: Value versus equity premium | D5: Value
C6: Implied offer per Range share | D6: =Inputs!$D$6*Inputs!$D$10 -> 54.90681 | G6: Reference prices are secondary cross-checks. EQT is a rounded implied proxy. This is an announcement-date price test, not a live quote.
C7: Equity consideration, share proxy | D7: =D6*Inputs!$D$9 -> 12969.538
C8: Premium to unaffected reference | D8: =D6/Inputs!$D$11-1 -> 0.20594795
C9: Equity premium paid | D9: =(D6-Inputs!$D$11)*Inputs!$D$9 -> 2214.8963
C10: After-tax synergy PV per USD1 run rate | D10: =(1-Inputs!$D$27)*(Inputs!$D$33/(1+Inputs!$D$32)+1/(Inputs!$D$32*(1+Inputs!$D$32))) -> 7.1590909
C11: Gross synergy PV, perpetuity | D11: =Inputs!$D$7*Inputs!D45*D10 -> 2326.7045 | G11: Optimistic perpetuity: no growth, no incremental capex or working capital; 50% year 1, 100% from year 2. No speculative >600m pathway.
C12: PV of integration and fees | D12: =Inputs!$D$30*(1-Inputs!$D$27)*(Inputs!$D$34/(1+Inputs!$D$32)+(1-Inputs!$D$34)/(1+Inputs!$D$32)^2)+Inputs!$D$31 -> 247.10744
C13: Net synergy PV | D13: =D11-D12 -> 2079.5971
C14: Value surplus after premium | D14: =D13-D9 -> -135.29918 | G14: Premium paid in shares is an economic cost. EPS accretion alone does not establish value creation. Unaffected share price is a standalone value proxy.
C15: Value break-even pre-tax annual synergy | D15: =(D9+D12)/D10 -> 343.89893
C16: Maximum exchange ratio at value break-even | D16: =(Inputs!$D$11+D13/Inputs!$D$9)/Inputs!$D$10 -> 0.97670354
C17: Finite 15-year synergy PV | D17: =Inputs!$D$7*Inputs!D45*(1-Inputs!$D$27)*((1-(1+Inputs!$D$32)^-15)/Inputs!$D$32-(1-Inputs!$D$33)/(1+Inputs!$D$32)) -> 1743.1864
C18: Finite 15-year value surplus | D18: =D17-D12-D9 -> -718.8173
C20: Stock consideration funding | D20: =Merger!D11*Inputs!$D$10 -> 12969.538
C21: Stock consideration funding less purchase price | D21: =D20-D7 -> 0
C22: Cash used for integration and fees | D22: =Inputs!$D$30+Inputs!$D$31 -> 350 | G22: Gross cash cost reserve, before tax benefit. No opening liquidity or refinancing capacity assertion. This module is not a full three-statement model.
C23: Cash bridge allocation check | D23: =SUM(Merger!D23:F23)+Merger!D24-D22 -> 0

Sheet History
C2: History | H2: Case selected | I2: =Inputs!D46 -> Base
C3: Announcement: 26 Oct 2026. Earnings: LTM Jun 2026. USDm / million shares.
C5: Earnings measure | D5: FY2025 | E5: H1 2025 | F5: H1 2026 | G5: LTM Jun 2026
C6: EQT adjusted attributable NI | D6: =Inputs!$D$12 -> 1879.156 | E6: =Inputs!$D$14 -> 986.283 | F6: =Inputs!$D$13 -> 1708.344 | G6: =D6-E6+F6 -> 2601.217
C7: EQT GAAP attributable NI | D7: =Inputs!$D$15 -> 2039.247 | E7: =Inputs!$D$17 -> 1026.286 | F7: =Inputs!$D$16 -> 1698.654 | G7: =D7-E7+F7 -> 2711.615
C8: Range adjusted NI | D8: =Inputs!$D$18 -> 719.745 | E8: =Inputs!$D$20 -> 389.871 | F8: =Inputs!$D$19 -> 545.732 | G8: =D8-E8+F8 -> 875.606
C9: Range GAAP NI | D9: =Inputs!$D$21 -> 658.024 | E9: =Inputs!$D$23 -> 334.63 | F9: =Inputs!$D$22 -> 536.953 | G9: =D9-E9+F9 -> 860.347
C10: Range SBC addback, before tax | D10: =Inputs!$D$24 -> 45.959 | E10: =Inputs!$D$26 -> 22.833 | F10: =Inputs!$D$25 -> 24.481 | G10: =D10-E10+F10 -> 47.607
G12: LTM = FY2025 minus H1 2025 plus H1 2026. Q2 diluted shares are closing proxies, not historical LTM EPS denominators.
G14: Range SBC uses the net income reconciliation, including amortisation. EQT adjusted reconciliation has no SBC addback. Other adjustment policies still differ.

Sheet Sources
C2: Sources
C3: Announcement: 26 Oct 2026. Earnings: LTM Jun 2026. USDm / million shares.
C5: ID | D5: Source and locator | E5: URL
C6: DEAL | D6: EQT, 26 Oct 2026, Transaction Details and Synergy Value | E6: https://ir.eqt.com/newsroom/news-releases/news-release-details/2026/EQT-Announces-Strategic-Acquisition-of-Range-Resources-Creating-Americas-Undisputed-Natural-Gas-Champion/default.aspx
C7: E25 | D7: EQT FY2025 release, adjusted net income reconciliation; annual column, USD000 | E7: https://ir.eqt.com/newsroom/news-releases/news-release-details/2026/EQT-Reports-Fourth-Quarter-and-Full-Year-2025-Results-and-Provides-2026-Guidance/default.aspx
C8: E26 | D8: EQT Q2 2026 release, adjusted net income reconciliation; six-month columns and Q2 shares, USD000 | E8: https://ir.eqt.com/investor-relations/news/news-release-details/2026/EQT-Reports-Second-Quarter-2026-Results/default.aspx
C9: R25 | D9: Range FY2025 release, pp11-12 net income reconciliation; annual column, USD000 | E9: https://ir.rangeresources.com/node/29286/pdf
C10: R26 | D10: Range Q2 2026 release, pp7,9,11-12; six-month net income and stock compensation, Q2 diluted shares, USD000 | E10: https://ir.rangeresources.com/static-files/efd9ff3a-a355-40d0-9193-b491b2e7de52
C11: PRICE | D11: SECONDARY cross-check: Reuters via Investing.com, 26 Oct 2026, USD54.91 offer and 20.6% premium; EQT proxy 54.91 / 0.987, Range proxy 54.91 / 1.206 | E11: https://www.investing.com/news/stock-market-news/eqt-range-resources-tie-up-in-50-billionplus-deal-to-create-us-gas-giant-4972044
