Workbook

Sheet Cover
C2: Meta AI financing | H2: Case selected | I2: =Inputs!D50 -> Base
C3: 27 Oct 2026 priced terms. USDm / million securities. Offerings not yet closed.
C5: ECM / DCM Financing Case | D5: Result
C6: Call | D6: ACCEPT FOR STAGED FUNDING
C8: Gross priced package (USDm) | D8: =Funding!D10 -> 37500
C9: Expected initial net cash (USDm) | D9: =Funding!D16 -> 12475
C10: Deferred net proceeds (USDm) | D10: =Funding!D14 -> 24906.8
C11: Annual preferred dividends (USDm) | D11: =Funding!D19 -> 812.5
C12: Bridge after-tax cost to deadline (USDm) | D12: =Funding!D22 -> 1242.8459
C13: Debt alternative annual after-tax coupon (USDm) | D13: =Alternatives!F10 -> 1632.4012
C14: Conditional ATM excluded (USDm) | D14: =Funding!D18 -> 60000
C17: Accept the equity-led package for staged investment. If the full amount is required at close, arrange funding for the deferred proceeds. Do not count the planned ATM as cash. This is an issuer financing recommendation, not a Meta stock recommendation.
C19: Conversion analysis illustrates initial Class A terms. Pending Class C recapitalisation must be modelled before quoting actual 2029 dilution. Final prospectus and forward agreements remain review items.

Sheet Inputs
C2: Inputs
C3: 27 Oct 2026 priced terms. USDm / million securities. Offerings not yet closed.
C5: Input | D5: Value | E5: Units | F5: Tag | G5: Source / reasoning
C6: Depositary shares offered | D6: 250 | E6: m | F6: S | G6: PRICING: base offering, excludes option
C7: Depositary share public price | D7: 50 | E7: USD | F7: S | G7: PRICING
C8: Depositary interests per preferred share | D8: 20 | E8: x | F8: S | G8: PRICING: each represents 1/20th
C9: Liquidation preference per preferred share | D9: 1000 | E9: USD | F9: S | G9: PRICING
C10: Preferred annual dividend | D10: 0.065 | E10: % | F10: S | G10: PRICING: when declared, cash or shares permitted
C11: Minimum initial Class A conversion rate | D11: 1.362 | E11: shares/pref | F11: S | G11: PRICING: subject to adjustments and Class C transition
C12: Maximum initial Class A conversion rate | D12: 1.6 | E12: shares/pref | F12: S | G12: PRICING: subject to adjustments and Class C transition
C13: Forward common shares | D13: 40 | E13: m | F13: S | G13: PRICING: base offer, physical settlement assumption below
C14: Common public offering price | D14: 625 | E14: USD | F14: S | G14: PRICING: priced, not a live market quote
C15: Initial net forward price | D15: 622.92 | E15: USD | F15: S | G15: PRICING: approximate, subject to contractual adjustments
C16: Planned future Class C ATM | D16: 60000 | E16: USDm | F16: S | G16: LAUNCH: no signed programme; excluded from funded proceeds
C17: Reported cash and cash equivalents | D17: 11222 | E17: USDm | F17: S | G17: Q3: 30 Sep 2026, excludes restricted cash
... C42: Up: final averaging price proxy | D42: 850 | E42: USD | F42: A | G42: Not a target price or forecast
C45: Expected offer close | D45: 46324
C46: Forward settlement deadline, assumed use | D46: 46710
C47: Mandatory preferred conversion | D47: 47345
C49: Active initial Class A reference price | D49: =CHOOSE(Inputs!$D$39,Inputs!$D$40,Inputs!$D$41,Inputs!$D$42) -> 625
C50: Case selected | D50: =CHOOSE(Inputs!$D$39,"Down","Base","Up") -> Base

Sheet Funding
C2: Funding | H2: Case selected | I2: =Inputs!D50 -> Base
C3: 27 Oct 2026 priced terms. USDm / million securities. Offerings not yet closed.
C5: Priced package and cash timing | D5: USDm
C6: Preferred gross proceeds | D6: =Inputs!$D$6*Inputs!$D$7 -> 12500
C7: Preferred issuance cost proxy | D7: =D6*Inputs!$D$27 -> 25
C8: Expected preferred net cash at close | D8: =D6-D7 -> 12475
C9: Common forward gross public offering | D9: =Inputs!$D$13*Inputs!$D$14 -> 25000
C10: Gross priced package | D10: =D6+D9 -> 37500
C11: Initial common net forward proceeds | D11: =Inputs!$D$13*Inputs!$D$15 -> 24916.8
C12: Forward price adjustment stress | D12: =D11*Inputs!$D$29 -> 0
C13: Forward extra expense proxy | D13: =Inputs!$D$28 -> 10
C14: Deferred net proceeds | D14: =D11+D12-D13 -> 24906.8
C15: Total eventual net proceeds | D15: =D8+D14 -> 37381.8
C16: Cash available at expected offering close | D16: =D8 -> 12475
C17: Share of net proceeds deferred | D17: =D14/D15 -> 0.66628145
C18: Excluded conditional ATM capacity | D18: =Inputs!$D$16 -> 60000
C19: Annual preferred dividends | D19: =Conversion!D6*Inputs!$D$9*Inputs!$D$10 -> 812.5
C20: Bridge interest to latest settlement | D20: =D14*Inputs!$D$36*(Inputs!$D$46-Inputs!$D$45)/365 -> 1448.6887
C21: Bridge fee overlay | D21: =D14*Inputs!$D$37 -> 124.534
C22: Bridge total after assumed tax shield | D22: =SUM(D20:D21)*(1-Inputs!$D$35) -> 1242.8459
C24: Historical nine-month free cash flow | D24: =Inputs!$D$22-Inputs!$D$23-Inputs!$D$24 -> 11049
C25: Reported liquid resources, 30 Sep | D25: =Inputs!$D$17+Inputs!$D$18 -> 82449
C26: Q4 spend implied by capex guidance, low | D26: =Inputs!$D$25-Inputs!$D$23-Inputs!$D$24 -> 49176
C27: Q4 spend implied by capex guidance, high | D27: =Inputs!$D$26-Inputs!$D$23-Inputs!$D$24 -> 59176
C30: Preferred net proceeds use unverified issuance costs. Common proceeds assume physical settlement at the deadline and a zero base price adjustment; contractual carry, dividends, stock borrow and alternative settlement may change the result.
C32: Bridge overlay assumes all eventual proceeds are needed at close. It is not a verified loan or Meta funding requirement. Interest and fees are additional cash uses. No ATM cash, options, operating cash flow or prior cash is added to issuance proceeds.
C34: Historical liquidity includes securities. Free cash flow is nine-month operating cash less capex and finance-lease principal. Q4 capex range is implied spend, not a funding shortfall or forecast cash burn.

Sheet Alternatives
C2: Alternatives | H2: Case selected | I2: =Inputs!D50 -> Base
C3: 27 Oct 2026 priced terms. USDm / million securities. Offerings not yet closed.
C5: Same eventual net funding | D5: Priced package | E5: Immediate common | F5: Straight debt
C6: Net cash at close | D6: =Funding!D8 -> 12475 | E6: =Funding!D15 -> 37381.8 | F6: =Funding!D15 -> 37381.8
C7: Deferred net cash | D7: =Funding!D14 -> 24906.8 | E7: =0 -> 0 | F7: =0 -> 0
C8: Total net proceeds | D8: =SUM(D6:D7) -> 37381.8 | E8: =SUM(E6:E7) -> 37381.8 | F8: =SUM(F6:F7) -> 37381.8
C9: Gap if all proceeds needed at close | D9: =D8-D6 -> 24906.8 | E9: =E8-E6 -> 0 | F9: =F8-F6 -> 0
C10: Annual after-tax financing cash charge | D10: =Funding!D19 -> 812.5 | E10: =0 -> 0 | F10: =Bond!D7*(1-Inputs!$D$35) -> 1632.4012
C11: New common at initial forward settlement | D11: =Inputs!$D$13 -> 40 | E11: =E6/(1-Inputs!$D$30 )/Inputs!$D$14 -> 60.010595 | F11: =0 -> 0
C12: New common at preferred conversion (initial terms) | D12: =Conversion!D10 -> 20 | E12: =0 -> 0 | F12: =0 -> 0
C13: Bond face amount | D13: =0 -> 0 | E13: =0 -> 0 | F13: =Bond!D6 -> 37569.648
C14: Bond bullet maturity principal | D14: =0 -> 0 | E14: =0 -> 0 | F14: =Bond!D6 -> 37569.648
C15: Issue-only balance-sheet check | D15: =Position!D11 -> 0 | E15: =Position!F11 -> 0 | F15: =Position!G11 -> 0
C18: Annual charge compares preferred cash dividends (no tax deduction) with bond coupons after an assumed 21% tax shield. It excludes common dividends and equity opportunity cost, and does not establish the cheapest source of capital.
C20: Mixed package shares are an initial Class A reference illustration, not actual 2029 dilution after Class C. All alternatives exclude over-allotments. Straight debt has a five-year bullet and new interest costs; cash charges are not GAAP EPS.

Sheet Conversion
C2: Conversion | H2: Case selected | I2: =Inputs!D50 -> Base
C3: 27 Oct 2026 priced terms. USDm / million securities. Offerings not yet closed.
C5: Initial Class A mechanics only | D5: Value
C6: Preferred shares, not depositary shares | D6: =Inputs!$D$6/Inputs!$D$8 -> 12.5
C7: Lower conversion price | D7: =Inputs!$D$9/Inputs!$D$12 -> 625
C8: Upper conversion price | D8: =Inputs!$D$9/Inputs!$D$11 -> 734.21439
C9: Active conversion rate | D9: =ROUND(MAX(Inputs!$D$11,MIN(Inputs!$D$12,Inputs!$D$9/Inputs!D49)),4) -> 1.6
C10: Shares delivered, initial terms | D10: =D6*D9 -> 20
C11: Converted market value | D11: =D10*Inputs!D49 -> 12500
C12: Illustrative total cash dividends | D12: =SUM(E20:E30) -> 2270.4861
C13: Investor total nominal return | D13: =(D11+D12)/Funding!D6-1 -> 0.18163889
C15: Class C transition and anti-dilution adjustments may change conversion securities, prices and rates. This schedule deliberately illustrates initial terms only. It is not a forecast of actual economic or voting dilution.
C19: Illustrative dividend date | D19: 30/360 years | E19: Dividend USDm | F19: Dividend PV
C20: 46433 | D20: =(360*(YEAR(C20)-YEAR(Inputs!$D$45))+30*(MONTH(C20)-MONTH(Inputs!$D$45))+MIN(DAY(C20),30)-MIN(DAY(Inputs!$D$45),30))/360 -> 0.29444444 | E20: =$D$6*Inputs!$D$9*Inputs!$D$10*D20 -> 239.23611 | F20: =E20/(1+Inputs!$D$38)^((C20-Inputs!$D$45)/365) -> 233.80048
C21: 46522 | D21: =(360*(YEAR(C21)-YEAR(C20))+30*(MONTH(C21)-MONTH(C20))+MIN(DAY(C21),30)-MIN(DAY(C20),30))/360 -> 0.25 | E21: =$D$6*Inputs!$D$9*Inputs!$D$10*D21 -> 203.125 | F21: =E21/(1+Inputs!$D$38)^((C21-Inputs!$D$45)/365) -> 194.81937
C22: 46614 | D22: =(360*(YEAR(C22)-YEAR(C21))+30*(MONTH(C22)-MONTH(C21))+MIN(DAY(C22),30)-MIN(DAY(C21),30))/360 -> 0.25 | E22: =$D$6*Inputs!$D$9*Inputs!$D$10*D22 -> 203.125 | F22: =E22/(1+Inputs!$D$38)^((C22-Inputs!$D$45)/365) -> 191.07661
C23: 46706 | D23: =(360*(YEAR(C23)-YEAR(C22))+30*(MONTH(C23)-MONTH(C22))+MIN(DAY(C23),30)-MIN(DAY(C22),30))/360 -> 0.25 | E23: =$D$6*Inputs!$D$9*Inputs!$D$10*D23 -> 203.125 | F23: =E23/(1+Inputs!$D$38)^((C23-Inputs!$D$45)/365) -> 187.40574
C24: 46798 | D24: =(360*(YEAR(C24)-YEAR(C23))+30*(MONTH(C24)-MONTH(C23))+MIN(DAY(C24),30)-MIN(DAY(C23),30))/360 -> 0.25 | E24: =$D$6*Inputs!$D$9*Inputs!$D$10*D24 -> 203.125 | F24: =E24/(1+Inputs!$D$38)^((C24-Inputs!$D$45)/365) -> 183.80541
C25: 46888 | D25: =(360*(YEAR(C25)-YEAR(C24))+30*(MONTH(C25)-MONTH(C24))+MIN(DAY(C25),30)-MIN(DAY(C24),30))/360 -> 0.25 | E25: =$D$6*Inputs!$D$9*Inputs!$D$10*D25 -> 203.125 | F25: =E25/(1+Inputs!$D$38)^((C25-Inputs!$D$45)/365) -> 180.35027
C26: 46980 | D26: =(360*(YEAR(C26)-YEAR(C25))+30*(MONTH(C26)-MONTH(C25))+MIN(DAY(C26),30)-MIN(DAY(C25),30))/360 -> 0.25 | E26: =$D$6*Inputs!$D$9*Inputs!$D$10*D26 -> 203.125 | F26: =E26/(1+Inputs!$D$38)^((C26-Inputs!$D$45)/365) -> 176.88548
C27: 47072 | D27: =(360*(YEAR(C27)-YEAR(C26))+30*(MONTH(C27)-MONTH(C26))+MIN(DAY(C27),30)-MIN(DAY(C26),30))/360 -> 0.25 | E27: =$D$6*Inputs!$D$9*Inputs!$D$10*D27 -> 203.125 | F27: =E27/(1+Inputs!$D$38)^((C27-Inputs!$D$45)/365) -> 173.48725
C28: 47164 | D28: =(360*(YEAR(C28)-YEAR(C27))+30*(MONTH(C28)-MONTH(C27))+MIN(DAY(C28),30)-MIN(DAY(C27),30))/360 -> 0.25 | E28: =$D$6*Inputs!$D$9*Inputs!$D$10*D28 -> 203.125 | F28: =E28/(1+Inputs!$D$38)^((C28-Inputs!$D$45)/365) -> 170.15431
C29: 47253 | D29: =(360*(YEAR(C29)-YEAR(C28))+30*(MONTH(C29)-MONTH(C28))+MIN(DAY(C29),30)-MIN(DAY(C28),30))/360 -> 0.25 | E29: =$D$6*Inputs!$D$9*Inputs!$D$10*D29 -> 203.125 | F29: =E29/(1+Inputs!$D$38)^((C29-Inputs!$D$45)/365) -> 166.991
C30: 47345 | D30: =(360*(YEAR(C30)-YEAR(C29))+30*(MONTH(C30)-MONTH(C29))+MIN(DAY(C30),30)-MIN(DAY(C29),30))/360 -> 0.25 | E30: =$D$6*Inputs!$D$9*Inputs!$D$10*D30 -> 203.125 | F30: =E30/(1+Inputs!$D$38)^((C30-Inputs!$D$45)/365) -> 163.78285
C32: All dividends assumed declared and paid in cash. Analyst 30/360 approximation includes first stub; verify final prospectus day count. No share-paid dividends, arrears or early/fundamental-change conversion.
C35: Price reference | D35: Conversion rate | E35: New shares | F35: Capital value | G35: Return incl dividends
C36: 300 | D36: =ROUND(MAX(Inputs!$D$11,MIN(Inputs!$D$12,Inputs!$D$9/C36)),4) -> 1.6 | E36: =$D$6*D36 -> 20 | F36: =E36*C36 -> 6000 | G36: =(F36+$D$12)/Funding!$D$6-1 -> -0.33836111
C37: 400 | D37: =ROUND(MAX(Inputs!$D$11,MIN(Inputs!$D$12,Inputs!$D$9/C37)),4) -> 1.6 | E37: =$D$6*D37 -> 20 | F37: =E37*C37 -> 8000 | G37: =(F37+$D$12)/Funding!$D$6-1 -> -0.17836111
C38: 500 | D38: =ROUND(MAX(Inputs!$D$11,MIN(Inputs!$D$12,Inputs!$D$9/C38)),4) -> 1.6 | E38: =$D$6*D38 -> 20 | F38: =E38*C38 -> 10000 | G38: =(F38+$D$12)/Funding!$D$6-1 -> -0.018361111
C39: 625 | D39: =ROUND(MAX(Inputs!$D$11,MIN(Inputs!$D$12,Inputs!$D$9/C39)),4) -> 1.6 | E39: =$D$6*D39 -> 20 | F39: =E39*C39 -> 12500 | G39: =(F39+$D$12)/Funding!$D$6-1 -> 0.18163889
C40: 700 | D40: =ROUND(MAX(Inputs!$D$11,MIN(Inputs!$D$12,Inputs!$D$9/C40)),4) -> 1.4286 | E40: =$D$6*D40 -> 17.8575 | F40: =E40*C40 -> 12500.25 | G40: =(F40+$D$12)/Funding!$D$6-1 -> 0.18165889
C41: 800 | D41: =ROUND(MAX(Inputs!$D$11,MIN(Inputs!$D$12,Inputs!$D$9/C41)),4) -> 1.362 | E41: =$D$6*D41 -> 17.025 | F41: =E41*C41 -> 13620 | G41: =(F41+$D$12)/Funding!$D$6-1 -> 0.27123889
C42: 900 | D42: =ROUND(MAX(Inputs!$D$11,MIN(Inputs!$D$12,Inputs!$D$9/C42)),4) -> 1.362 | E42: =$D$6*D42 -> 17.025 | F42: =E42*C42 -> 15322.5 | G42: =(F42+$D$12)/Funding!$D$6-1 -> 0.40743889
C45: PV of assumed cash dividends | D45: =SUM(F20:F30) -> 2022.5588
C46: Required terminal value at investor hurdle | D46: =(Funding!D6-D45)*(1+Inputs!$D$38)^((Inputs!$D$47-Inputs!$D$45)/365) -> 12994.219
C47: Initial Class A price meeting investor hurdle | D47: =D46/($D$6*IF(D46>$D$6*Inputs!$D$9,Inputs!$D$11,Inputs!$D$12)) -> 763.2434
C49: Deterministic price at the selected return hurdle; not an option valuation, market forecast or actual Class C price. Cash dividends assumed certain for this illustration. Conversion-rate rounding creates small boundary differences.

Sheet Bond
C2: Bond | H2: Case selected | I2: =Inputs!D50 -> Base
C3: 27 Oct 2026 priced terms. USDm / million securities. Offerings not yet closed.
C5: Hypothetical five-year debt | D5: Value
C6: Face needed for matched net proceeds | D6: =Funding!D15/(1-Inputs!$D$31) -> 37569.648
C7: Annual coupon cash | D7: =D6*Inputs!$D$32 -> 2066.3307
C8: Effective yield including issuance costs | D8: =RATE(Inputs!$D$34,-D7,Funding!D15,-D6) -> 0.056174656
C9: Price per 100 at selected yield | D9: =-PV(Inputs!$D$33,Inputs!$D$34,Inputs!$D$32*100,100) -> 100
C10: Benchmark total cash coupon, five years | D10: =D7*Inputs!$D$34 -> 10331.653
C12: Hypothetical debt, not an announced bond or market quote. Fixed coupon and selected valuation yield are separate. Own May 2026 notes provide a historical coupon range only, not comparable live yields.
C15: Year | D15: Opening carrying | E15: Cash coupon | F15: Effective interest | G15: Fee amortisation | H15: Principal | I15: Closing carrying
C16: 1 | D16: =Funding!D15 -> 37381.8 | E16: =$D$7 -> 2066.3307 | F16: =D16*$D$8 -> 2099.9098 | G16: =F16-E16 -> 33.579115 | H16: =IF(C16=Inputs!$D$34,$D$6,0) -> 0 | I16: =D16+G16-H16 -> 37415.379
C17: 2 | D17: =I16 -> 37415.379 | E17: =$D$7 -> 2066.3307 | F17: =D17*$D$8 -> 2101.7961 | G17: =F17-E17 -> 35.46541 | H17: =IF(C17=Inputs!$D$34,$D$6,0) -> 0 | I17: =D17+G17-H17 -> 37450.845
C18: 3 | D18: =I17 -> 37450.845 | E18: =$D$7 -> 2066.3307 | F18: =D18*$D$8 -> 2103.7883 | G18: =F18-E18 -> 37.457667 | H18: =IF(C18=Inputs!$D$34,$D$6,0) -> 0 | I18: =D18+G18-H18 -> 37488.302
C19: 4 | D19: =I18 -> 37488.302 | E19: =$D$7 -> 2066.3307 | F19: =D19*$D$8 -> 2105.8925 | G19: =F19-E19 -> 39.561839 | H19: =IF(C19=Inputs!$D$34,$D$6,0) -> 0 | I19: =D19+G19-H19 -> 37527.864
C20: 5 | D20: =I19 -> 37527.864 | E20: =$D$7 -> 2066.3307 | F20: =D20*$D$8 -> 2108.1149 | G20: =F20-E20 -> 41.784211 | H20: =IF(C20=Inputs!$D$34,$D$6,0) -> 37569.648 | I20: =ROUND(D20+G20-H20,6) -> 0
C23: Assumed yield | D23: Price per 100
C24: 0.035 | D24: =-PV(C24,Inputs!$D$34,Inputs!$D$32*100,100) -> 109.0301
C25: 0.045 | D25: =-PV(C25,Inputs!$D$34,Inputs!$D$32*100,100) -> 104.38998
C26: 0.055 | D26: =-PV(C26,Inputs!$D$34,Inputs!$D$32*100,100) -> 100
C27: 0.065 | D27: =-PV(C27,Inputs!$D$34,Inputs!$D$32*100,100) -> 95.844321
C28: 0.075 | D28: =-PV(C28,Inputs!$D$34,Inputs!$D$32*100,100) -> 91.90823
C30: Five-year annual schedule is fixed. Change coupon, yield or fee for sensitivities; changing maturity requires rebuilding the schedule. Principal is a cash outflow at maturity, not a financing expense.

Sheet Position
C2: Position | H2: Case selected | I2: =Inputs!D50 -> Base
C3: 27 Oct 2026 priced terms. USDm / million securities. Offerings not yet closed.
C5: Issue-only snapshot | D5: Package close | E5: Package settled | F5: Immediate common | G5: Straight debt
C6: Reported opening cash | D6: =Inputs!$D$17 -> 11222 | E6: =Inputs!$D$17 -> 11222 | F6: =Inputs!$D$17 -> 11222 | G6: =Inputs!$D$17 -> 11222
C7: Net issuance cash | D7: =Funding!D8 -> 12475 | E7: =Funding!D15 -> 37381.8 | F7: =Funding!D15 -> 37381.8 | G7: =Funding!D15 -> 37381.8
C8: Pro forma cash before deployment | D8: =SUM(D6:D7) -> 23697 | E8: =SUM(E6:E7) -> 48603.8 | F8: =SUM(F6:F7) -> 48603.8 | G8: =SUM(G6:G7) -> 48603.8
C9: Total assets | D9: =Inputs!$D$19+D7 -> 491311 | E9: =Inputs!$D$19+E7 -> 516217.8 | F9: =Inputs!$D$19+F7 -> 516217.8 | G9: =Inputs!$D$19+G7 -> 516217.8
C10: Liabilities plus equity capital | D10: =SUM(D13:D14) -> 491311 | E10: =SUM(E13:E14) -> 516217.8 | F10: =SUM(F13:F14) -> 516217.8 | G10: =SUM(G13:G14) -> 516217.8
C11: Balance difference | D11: =D9-D10 -> 0 | E11: =E9-E10 -> 0 | F11: =F9-F10 -> 0 | G11: =G9-G10 -> 0
C13: Liabilities | D13: =Inputs!$D$20 -> 206450 | E13: =Inputs!$D$20 -> 206450 | F13: =Inputs!$D$20 -> 206450 | G13: =Inputs!$D$20+G7 -> 243831.8
C14: Equity capital | D14: =Inputs!$D$21+D7 -> 284861 | E14: =Inputs!$D$21+E7 -> 309767.8 | F14: =Inputs!$D$21+F7 -> 309767.8 | G14: =Inputs!$D$21 -> 272386
C17: Static issuance bridge on 30 Sep balances, not a forecast balance sheet at future dates. Proceeds retained as cash; no capex, operating flows, bridge overlay, dividends or other balance changes. Securities remain separate from cash.
C19: Preferred treated as equity capital and issuance costs deducted from equity. New bond costs reduce carrying debt. Final classification, existing instruments and forward derivative accounting unverified. Package settled excludes any intervening dividends.

Sheet Sources
C2: Sources
C3: 27 Oct 2026 priced terms. USDm / million securities. Offerings not yet closed.
C5: ID | D5: Document / locator | E5: URL
C6: PRICING | D6: Meta, 27 Oct 2026 pricing release: offer sizes, prices, conversion limits, dividends and forward cash timing | E6: https://investor.atmeta.com/investor-news/press-release-details/2026/Meta-Announces-Pricing-of-Offering-of-Depositary-Shares-Representing-Series-A-Mandatory-Convertible-Preferred-Stock-and-Offering-of-Class-A-Common-Stock-in-Connection-with-Forward-Sale-Agreements/default.aspx
C7: LAUNCH | D7: Meta, 26 Oct 2026 launch: financing plan, conditional ATM and AI investment | E7: https://investor.atmeta.com/investor-news/press-release-details/2026/Meta-Announces-Launch-of-Offering-of-Depositary-Shares-Representing-Series-A-Mandatory-Convertible-Preferred-Stock-and-Offering-of-Class-A-Common-Stock-in-Connection-with-Forward-Sale-Agreements/default.aspx
C8: Q3 | D8: Meta Q3 2026 release, 21 Oct: September balance sheet, nine-month cash flow, FY capex guidance, Class C discussion | E8: https://investor.atmeta.com/investor-news/press-release-details/2026/Meta-Reports-Third-Quarter-2026-Results/default.aspx
C9: Q2SEC | D9: Meta June 2026 10-Q, Note 8: May notes coupon range 4.55%-6.45%; historical terms, not current yields | E9: https://www.sec.gov/Archives/edgar/data/1326801/000162828026050705/meta-20260630.htm
