Workbook

Sheet Cover
A1: Vitamin Well / Vital Bidco credit review
A2: 27 October 2026. Public-information model of the 2026 refinancing; no verified contractual covenant test.
A3: Case selected | B3: =Inputs!C5 -> Base
A5: Metric | B5: Value
A6: Term loan, EURm equivalent | B6: =Inputs!$C$9 -> 1900
A7: Term loan translated, SEKm | B7: =Capacity!B5 -> 20900
A8: Capacity under assumed policy, SEKm | B8: =Capacity!B13 -> 21422.5
A9: Requested less capacity, SEKm | B9: =Capacity!B14 -> -522.5
A10: 2026 gross leverage / cash EBITDA | B10: =Forecast!B32 -> 5.3398945
A11: 2026 cash interest cover | B11: =Forecast!B33 -> 2.6424695
A12: 2026 FCF, SEKm | B12: =Forecast!B20 -> -98.889231
A13: Peak revolver, SEKm | B13: =MAX(Forecast!B27:F27) -> 107.88923
A14: Minimum cash plus undrawn RCF, SEKm | B14: =MIN(Forecast!B31:F31) -> 2392.1108
A15: Peak unfunded cash gap, SEKm | B15: =MAX(Forecast!B36:F36) -> 0
A16: 2030 gross leverage / cash EBITDA | B16: =Forecast!F32 -> 2.2572575
A17: Default first-lien recovery | B17: =Recovery!B13 -> 0.58750866
A18: Actual contractual covenant compliance | B18: Not established: loan agreement missing
A19: Selected-case policy screen | B19: =IF(OR(Capacity!B14>0,MAX(Forecast!B36:F36)>0,MIN(Forecast!B34:F34)<0,MIN(Forecast!B35:F35)<0),"REJECT at assumed policy limits","PASS policy screen; evidence still required") -> PASS policy screen; evidence still required
A20: Recorded credit-memo verdict | B20: Reject pending downside protection and evidence
A22: No purchase-price or sources-and-uses bridge: transaction consideration is undisclosed.
A23: No audited full balance sheet: cash and debt rollforwards reconcile separately.
A24: 2026 is a full-year pro forma proxy, not remaining cash flow after the review date.

Sheet Inputs
A1: Vitamin Well: underwriting inputs
A2: SEKm unless labelled. S: source/agency forecast. A: assumption. D: derived. No audited borrower accounts.
A4: Case number: 1 Downside, 2 Base, 3 Bull | C4: 2
A5: Selected case | C5: =CHOOSE(C4,"Downside","Base","Bull") -> Base
A8: Input | B8: Unit | C8: Value | D8: Tag | E8: Source / reason
A9: New term loan, EURm equivalent | B9: EURm | C9: 1900 | D9: S | E9: SP26: agency reports issuance; final agreement unverified
A10: Revolver commitment, EURm equivalent | B10: EURm | C10: 200 | D10: S | E10: SP26: reported undrawn commitment
A11: Term loan maturity year | B11: year | C11: 2033 | D11: S | E11: SP26; exact date unverified
A12: SEK per EUR, constant translation proxy | B12: SEK/EUR | C12: 11 | D12: A | E12: Round common currency proxy; not an observed spot or FX hedge
A13: 2026 agency EBITDA forecast low | B13: SEKm | C13: 4000 | D13: S | E13: SP26: adjusted pro forma forecast
A14: 2026 agency EBITDA forecast high | B14: SEKm | C14: 4200 | D14: S | E14: SP26: adjusted pro forma forecast
A15: Starting EBITDA margin proxy | B15: % | C15: 0.26 | D15: A | E15: Middle of agency's 25-27% outlook; not reported margin
A16: Adjusted EBITDA to cash EBITDA haircut | B16: % | C16: 0.05 | D16: A | E16: 5% reserve for noncash/addback leakage; requires reconciliation
A17: Opening cash proxy | B17: SEKm | C17: 500 | D17: A | E17: Unverified opening liquidity; sensitise before any approval
A18: Minimum operating cash | B18: SEKm | C18: 300 | D18: A | E18: Analyst buffer, not a covenant
A19: Reference rate proxy | B19: % | C19: 0.03 | D19: A | E19: Constant illustrative blended funding rate; not current EURIBOR/SOFR
A20: New term-loan spread proxy | B20: % | C20: 0.04 | D20: A | E20: Illustrative 400bp; not carried from the legacy loan or verified pricing
... A38: Revolver drawn at default | B38: % | C38: 1 | D38: A | E38: Full draw; assume pari passu with term loan
A43: Revenue growth | D43: 2026 | E43: 2027 | F43: 2028 | G43: 2029 | H43: 2030
A44: Active revenue growth | D44: =CHOOSE($C$4,D45,D46,D47) -> 0 | E44: =CHOOSE($C$4,E45,E46,E47) -> 0.15 | F44: =CHOOSE($C$4,F45,F46,F47) -> 0.12 | G44: =CHOOSE($C$4,G45,G46,G47) -> 0.1 | H44: =CHOOSE($C$4,H45,H46,H47) -> 0.08
A45: Downside | B45: A | D45: 0 | E45: -0.1 | F45: 0.02 | G45: 0.04 | H45: 0.05
A46: Base | B46: A | D46: 0 | E46: 0.15 | F46: 0.12 | G46: 0.1 | H46: 0.08
A47: Bull | B47: A | D47: 0 | E47: 0.2 | F47: 0.15 | G47: 0.12 | H47: 0.1
A50: EBITDA margin | D50: 2026 | E50: 2027 | F50: 2028 | G50: 2029 | H50: 2030
A51: Active ebitda margin | D51: =CHOOSE($C$4,D52,D53,D54) -> 0.26 | E51: =CHOOSE($C$4,E52,E53,E54) -> 0.27 | F51: =CHOOSE($C$4,F52,F53,F54) -> 0.27 | G51: =CHOOSE($C$4,G52,G53,G54) -> 0.27 | H51: =CHOOSE($C$4,H52,H53,H54) -> 0.27
A52: Downside | B52: A | D52: 0.24 | E52: 0.21 | F52: 0.22 | G52: 0.23 | H52: 0.24
A53: Base | B53: A | D53: 0.26 | E53: 0.27 | F53: 0.27 | G53: 0.27 | H53: 0.27
A54: Bull | B54: A | D54: 0.27 | E54: 0.28 | F54: 0.285 | G54: 0.285 | H54: 0.285
A57: Rate shock | D57: 2026 | E57: 2027 | F57: 2028 | G57: 2029 | H57: 2030
A58: Active rate shock | D58: =CHOOSE($C$4,D59,D60,D61) -> 0 | E58: =CHOOSE($C$4,E59,E60,E61) -> 0 | F58: =CHOOSE($C$4,F59,F60,F61) -> 0 | G58: =CHOOSE($C$4,G59,G60,G61) -> 0 | H58: =CHOOSE($C$4,H59,H60,H61) -> 0
A59: Downside | B59: A | D59: 0.02 | E59: 0.02 | F59: 0.02 | G59: 0.02 | H59: 0.02
A60: Base | B60: A | D60: 0 | E60: 0 | F60: 0 | G60: 0 | H60: 0
A61: Bull | B61: A | D61: -0.005 | E61: -0.005 | F61: -0.005 | G61: -0.005 | H61: -0.005
A64: Capex multiplier | D64: 2026 | E64: 2027 | F64: 2028 | G64: 2029 | H64: 2030
A65: Active capex multiplier | D65: =CHOOSE($C$4,D66,D67,D68) -> 1 | E65: =CHOOSE($C$4,E66,E67,E68) -> 1 | F65: =CHOOSE($C$4,F66,F67,F68) -> 1 | G65: =CHOOSE($C$4,G66,G67,G68) -> 1 | H65: =CHOOSE($C$4,H66,H67,H68) -> 1
A66: Downside | B66: A | D66: 1.25 | E66: 1.25 | F66: 1.25 | G66: 1.25 | H66: 1.25
A67: Base | B67: A | D67: 1 | E67: 1 | F67: 1 | G67: 1 | H67: 1
A68: Bull | B68: A | D68: 0.9 | E68: 0.9 | F68: 0.9 | G68: 0.9 | H68: 0.9

Sheet Forecast
A1: Cash flow and debt forecast
A2: Full-year pro forma proxies; opening-balance interest; no acquisition completion claim.
A3: Case selected | B3: =Inputs!C5 -> Base
A4: Metric | B4: 2026 | C4: 2027 | D4: 2028 | E4: 2029 | F4: 2030
A5: Revenue growth | B5: =Inputs!$D$44 -> 0 | C5: =Inputs!$E$44 -> 0.15 | D5: =Inputs!$F$44 -> 0.12 | E5: =Inputs!$G$44 -> 0.1 | F5: =Inputs!$H$44 -> 0.08
A6: Adjusted EBITDA margin | B6: =Inputs!$D$51 -> 0.26 | C6: =Inputs!$E$51 -> 0.27 | D6: =Inputs!$F$51 -> 0.27 | E6: =Inputs!$G$51 -> 0.27 | F6: =Inputs!$H$51 -> 0.27
A7: Opening cash | B7: =Inputs!$C$17 -> 500 | C7: =B28 -> 300 | D7: =C28 -> 938.66254 | E7: =D28 -> 1537.8106 | F7: =E28 -> 2060.9837
A8: Opening term loan | B8: =Capacity!B5 -> 20900 | C8: =B26 -> 20691 | D8: =C26 -> 19843.337 | E8: =D26 -> 18396.527 | F8: =E26 -> 16426.543
A9: Opening revolver | B9: =0 -> 0 | C9: =B27 -> 107.88923 | D9: =C27 -> 0 | E9: =D27 -> 0 | F9: =E27 -> 0
A10: Revenue | B10: =Capacity!B8*(1+B5) -> 15769.231 | C10: =B10*(1+C5) -> 18134.615 | D10: =C10*(1+D5) -> 20310.769 | E10: =D10*(1+E5) -> 22341.846 | F10: =E10*(1+F5) -> 24129.194
A11: Adjusted EBITDA | B11: =B10*B6 -> 4100 | C11: =C10*C6 -> 4896.3462 | D11: =D10*D6 -> 5483.9077 | E11: =E10*E6 -> 6032.2985 | F11: =F10*F6 -> 6514.8823
A12: Cash EBITDA | B12: =B11*(1-Inputs!$C$16) -> 3895 | C12: =C11*(1-Inputs!$C$16) -> 4651.5288 | D12: =D11*(1-Inputs!$C$16) -> 5209.7123 | E12: =E11*(1-Inputs!$C$16) -> 5730.6835 | F12: =F11*(1-Inputs!$C$16) -> 6189.1382
A13: Interest on opening balances | B13: =B8*(Inputs!$C$19+Inputs!$C$20+Inputs!$D$58)+B9*(Inputs!$C$19+Inputs!$C$21+Inputs!$D$58) -> 1463 | C13: =C8*(Inputs!$C$19+Inputs!$C$20+Inputs!$E$58)+C9*(Inputs!$C$19+Inputs!$C$21+Inputs!$E$58) -> 1456.4617 | D13: =D8*(Inputs!$C$19+Inputs!$C$20+Inputs!$F$58)+D9*(Inputs!$C$19+Inputs!$C$21+Inputs!$F$58) -> 1389.0336 | E13: =E8*(Inputs!$C$19+Inputs!$C$20+Inputs!$G$58)+E9*(Inputs!$C$19+Inputs!$C$21+Inputs!$G$58) -> 1287.7569 | F13: =F8*(Inputs!$C$19+Inputs!$C$20+Inputs!$H$58)+F9*(Inputs!$C$19+Inputs!$C$21+Inputs!$H$58) -> 1149.858
A14: Undrawn commitment fee | B14: =(Capacity!$B$6-B9)*Inputs!$C$22 -> 11 | C14: =(Capacity!$B$6-C9)*Inputs!$C$22 -> 10.460554 | D14: =(Capacity!$B$6-D9)*Inputs!$C$22 -> 11 | E14: =(Capacity!$B$6-E9)*Inputs!$C$22 -> 11 | F14: =(Capacity!$B$6-F9)*Inputs!$C$22 -> 11
A15: D&A proxy | B15: =B10*Inputs!$C$26 -> 394.23077 | C15: =C10*Inputs!$C$26 -> 453.36538 | D15: =D10*Inputs!$C$26 -> 507.76923 | E15: =E10*Inputs!$C$26 -> 558.54615 | F15: =F10*Inputs!$C$26 -> 603.22985
A16: Cash tax proxy | B16: =MAX(0,B12-B15-B13-B14)*Inputs!$C$25 -> 445.88923 | C16: =MAX(0,C12-C15-C13-C14)*Inputs!$C$25 -> 600.87307 | D16: =MAX(0,D12-D15-D13-D14)*Inputs!$C$25 -> 726.42008 | E16: =MAX(0,E12-E15-E13-E14)*Inputs!$C$25 -> 852.14371 | F16: =MAX(0,F12-F15-F13-F14)*Inputs!$C$25 -> 973.51108
A17: Capex | B17: =AVERAGE(Inputs!$C$27,Inputs!$C$28)*Inputs!$D$65 -> 1250 | C17: =C10*Inputs!$C$29*Inputs!$E$65 -> 634.71154 | D17: =D10*Inputs!$C$29*Inputs!$F$65 -> 710.87692 | E17: =E10*Inputs!$C$29*Inputs!$G$65 -> 781.96462 | F17: =F10*Inputs!$C$29*Inputs!$H$65 -> 844.52178
A18: Working capital investment | B18: =(B10-Capacity!$B$8)*Inputs!$C$31 -> 0 | C18: =(C10-B10)*Inputs!$C$31 -> 354.80769 | D18: =(D10-C10)*Inputs!$C$31 -> 326.42308 | E18: =(E10-D10)*Inputs!$C$31 -> 304.66154 | F18: =(F10-E10)*Inputs!$C$31 -> 268.10215
A19: Transaction costs | B19: =Inputs!$C$30 -> 824 | C19: =0 -> 0 | D19: =0 -> 0 | E19: =0 -> 0 | F19: =0 -> 0
A20: FCF after interest and tax | B20: =B12-SUM(B13:B14)-B16-SUM(B17:B19) -> -98.889231 | C20: =C12-SUM(C13:C14)-C16-SUM(C17:C19) -> 1594.2143 | D20: =D12-SUM(D13:D14)-D16-SUM(D17:D19) -> 2045.9586 | E20: =E12-SUM(E13:E14)-E16-SUM(E17:E19) -> 2493.1568 | F20: =F12-SUM(F13:F14)-F16-SUM(F17:F19) -> 2942.1452
A21: Mandatory term-loan amortisation | B21: =MIN(B8,Capacity!$B$5*Inputs!$C$23) -> 209 | C21: =MIN(C8,Capacity!$B$5*Inputs!$C$23) -> 209 | D21: =MIN(D8,Capacity!$B$5*Inputs!$C$23) -> 209 | E21: =MIN(E8,Capacity!$B$5*Inputs!$C$23) -> 209 | F21: =MIN(F8,Capacity!$B$5*Inputs!$C$23) -> 209
A22: Cash before discretionary financing | B22: =B7+B20-B21 -> 192.11077 | C22: =C7+C20-C21 -> 1685.2143 | D22: =D7+D20-D21 -> 2775.6211 | E22: =E7+E20-E21 -> 3821.9674 | F22: =F7+F20-F21 -> 4794.1289
A23: Revolver draw | B23: =MIN(MAX(0,Inputs!$C$18-B22),Capacity!$B$6-B9) -> 107.88923 | C23: =MIN(MAX(0,Inputs!$C$18-C22),Capacity!$B$6-C9) -> 0 | D23: =MIN(MAX(0,Inputs!$C$18-D22),Capacity!$B$6-D9) -> 0 | E23: =MIN(MAX(0,Inputs!$C$18-E22),Capacity!$B$6-E9) -> 0 | F23: =MIN(MAX(0,Inputs!$C$18-F22),Capacity!$B$6-F9) -> 0
A24: Revolver repayment | B24: =MIN(MAX(0,B22-Inputs!$C$18),B9) -> 0 | C24: =MIN(MAX(0,C22-Inputs!$C$18),C9) -> 107.88923 | D24: =MIN(MAX(0,D22-Inputs!$C$18),D9) -> 0 | E24: =MIN(MAX(0,E22-Inputs!$C$18),E9) -> 0 | F24: =MIN(MAX(0,F22-Inputs!$C$18),F9) -> 0
A25: Term-loan cash sweep | B25: =MIN(MAX(0,B22-B24-Inputs!$C$18)*Inputs!$C$24,B8-B21) -> 0 | C25: =MIN(MAX(0,C22-C24-Inputs!$C$18)*Inputs!$C$24,C8-C21) -> 638.66254 | D25: =MIN(MAX(0,D22-D24-Inputs!$C$18)*Inputs!$C$24,D8-D21) -> 1237.8106 | E25: =MIN(MAX(0,E22-E24-Inputs!$C$18)*Inputs!$C$24,E8-E21) -> 1760.9837 | F25: =MIN(MAX(0,F22-F24-Inputs!$C$18)*Inputs!$C$24,F8-F21) -> 2247.0644
A26: Closing term loan | B26: =B8-B21-B25 -> 20691 | C26: =C8-C21-C25 -> 19843.337 | D26: =D8-D21-D25 -> 18396.527 | E26: =E8-E21-E25 -> 16426.543 | F26: =F8-F21-F25 -> 13970.479
A27: Closing revolver | B27: =B9+B23-B24 -> 107.88923 | C27: =C9+C23-C24 -> 0 | D27: =D9+D23-D24 -> 0 | E27: =E9+E23-E24 -> 0 | F27: =F9+F23-F24 -> 0
A28: Closing cash | B28: =B22+B23-B24-B25 -> 300 | C28: =C22+C23-C24-C25 -> 938.66254 | D28: =D22+D23-D24-D25 -> 1537.8106 | E28: =E22+E23-E24-E25 -> 2060.9837 | F28: =F22+F23-F24-F25 -> 2547.0644
A29: Gross funded debt | B29: =B26+B27 -> 20798.889 | C29: =C26+C27 -> 19843.337 | D29: =D26+D27 -> 18396.527 | E29: =E26+E27 -> 16426.543 | F29: =F26+F27 -> 13970.479
A30: Net funded debt | B30: =B29-B28 -> 20498.889 | C30: =C29-C28 -> 18904.675 | D30: =D29-D28 -> 16858.716 | E30: =E29-E28 -> 14365.56 | F30: =F29-F28 -> 11423.414
A31: Cash plus undrawn revolver | B31: =B28+Capacity!$B$6-B27 -> 2392.1108 | C31: =C28+Capacity!$B$6-C27 -> 3138.6625 | D31: =D28+Capacity!$B$6-D27 -> 3737.8106 | E31: =E28+Capacity!$B$6-E27 -> 4260.9837 | F31: =F28+Capacity!$B$6-F27 -> 4747.0644
A32: Gross leverage / cash EBITDA | B32: =B29/B12 -> 5.3398945 | C32: =C29/C12 -> 4.2659818 | D32: =D29/D12 -> 3.5311982 | E32: =E29/E12 -> 2.8664195 | F32: =F29/F12 -> 2.2572575
A33: Cash interest cover | B33: =B12/SUM(B13:B14) -> 2.6424695 | C33: =C12/SUM(C13:C14) -> 3.1709444 | D33: =D12/SUM(D13:D14) -> 3.7211337 | E33: =E12/SUM(E13:E14) -> 4.4124375 | F33: =F12/SUM(F13:F14) -> 5.3315204
A34: Headroom to assumed leverage ceiling | B34: =Inputs!$C$32-B32 -> 0.16010546 | C34: =Inputs!$C$32-C32 -> 1.2340182 | D34: =Inputs!$C$32-D32 -> 1.9688018 | E34: =Inputs!$C$32-E32 -> 2.6335805 | F34: =Inputs!$C$32-F32 -> 3.2427425
A35: Headroom above assumed cover floor | B35: =B33-Inputs!$C$33 -> 0.64246947 | C35: =C33-Inputs!$C$33 -> 1.1709444 | D35: =D33-Inputs!$C$33 -> 1.7211337 | E35: =E33-Inputs!$C$33 -> 2.4124375 | F35: =F33-Inputs!$C$33 -> 3.3315204
A36: Unfunded cash-minimum gap | B36: =MAX(0,Inputs!$C$18-B28) -> 0 | C36: =MAX(0,Inputs!$C$18-C28) -> 0 | D36: =MAX(0,Inputs!$C$18-D28) -> 0 | E36: =MAX(0,Inputs!$C$18-E28) -> 0 | F36: =MAX(0,Inputs!$C$18-F28) -> 0
A37: Cash rollforward check | B37: =B28-B7-B20+B21-B23+B24+B25 -> 0 | C37: =C28-C7-C20+C21-C23+C24+C25 -> 0 | D37: =D28-D7-D20+D21-D23+D24+D25 -> 0 | E37: =E28-E7-E20+E21-E23+E24+E25 -> 0 | F37: =F28-F7-F20+F21-F23+F24+F25 -> 0
A38: Debt rollforward check | B38: =B29-B8-B9+B21+B25-B23+B24 -> -1.1368684e-12 | C38: =C29-C8-C9+C21+C25-C23+C24 -> 1.2505552e-12 | D38: =D29-D8-D9+D21+D25-D23+D24 -> 0 | E38: =E29-E8-E9+E21+E25-E23+E24 -> 0 | F38: =F29-F8-F9+F21+F25-F23+F24 -> 0

Sheet Capacity
A1: Debt capacity under assumed credit policy
A2: Entry capacity only. These are underwriting limits, not contractual covenants.
A4: Metric | B4: Value
A5: Term loan translated to SEKm | B5: =Inputs!$C$9*Inputs!$C$12 -> 20900
A6: Revolver translated to SEKm | B6: =Inputs!$C$10*Inputs!$C$12 -> 2200
A7: 2026 adjusted EBITDA forecast midpoint | B7: =AVERAGE(Inputs!$C$13,Inputs!$C$14) -> 4100
A8: Inferred revenue proxy | B8: =B7/Inputs!$C$15 -> 15769.231
A9: Cash EBITDA after haircut | B9: =B7*(1-Inputs!$C$16) -> 3895
A10: Assumed all-in term-loan rate | B10: =Inputs!$C$19+Inputs!$C$20 -> 0.07
A11: Debt capacity: leverage limit | B11: =B9*Inputs!$C$32 -> 21422.5
A12: Debt capacity: cover limit | B12: =(B9/Inputs!$C$33-B6*Inputs!$C$22)/B10 -> 27664.286
A13: Capacity: binding policy limit | B13: =MAX(0,MIN(B11:B12)) -> 21422.5
A14: Requested debt less capacity | B14: =B5-B13 -> -522.5
A15: Adjusted EBITDA needed at leverage limit | B15: =B5/Inputs!$C$32/(1-Inputs!$C$16) -> 4000
A16: EBITDA fall to entry leverage ceiling | B16: =1-B15/B7 -> 0.024390244

Sheet Recovery
A1: Default recovery waterfall
A2: Assumed pari passu first lien; no legal opinion. No unrestricted cash credited at default.
A4: Metric | B4: Value
A5: Default cash EBITDA | B5: =Capacity!B9*(1-Inputs!$C$34) -> 2531.75
A6: Default enterprise value | B6: =B5*Inputs!$C$35 -> 15190.5
A7: Enforcement cost reserve | B7: =B6*Inputs!$C$36 -> 1519.05
A8: Other priority claims | B8: =Inputs!$C$37 -> 100
A9: Available first-lien pool | B9: =MAX(0,B6-B7-B8) -> 13571.45
A10: Term-loan claim | B10: =Capacity!B5 -> 20900
A11: Revolver claim at default | B11: =Capacity!B6*Inputs!$C$38 -> 2200
A12: Total pari passu claims | B12: =SUM(B10:B11) -> 23100
A13: First-lien recovery | B13: =MIN(1,B9/B12) -> 0.58750866
A14: Term-loan proceeds | B14: =B10*B13 -> 12278.931
A15: Revolver proceeds | B15: =B11*B13 -> 1292.519
A16: Unrecovered first-lien claim | B16: =B12-SUM(B14:B15) -> 9528.55
A17: Residual equity | B17: =MAX(0,B9-B12) -> 0

Sheet Sensitivity
A1: Recovery and debt-capacity sensitivities
A2: Direct scalar calculations; fixed current policy and default assumptions. No duplicated cash-flow model.
A4: Recovery: EBITDA haircut / EV multiple | B4: 4 | C4: 5 | D4: 6 | E4: 7 | F4: 8
A5: 0.15 | B5: =MIN(1,MAX(0,Capacity!$B$9*(1-$A5)*B$4*(1-Inputs!$C$36)-Inputs!$C$37)/Recovery!$B$12) -> 0.51163203 | C5: =MIN(1,MAX(0,Capacity!$B$9*(1-$A5)*C$4*(1-Inputs!$C$36)-Inputs!$C$37)/Recovery!$B$12) -> 0.64062229 | D5: =MIN(1,MAX(0,Capacity!$B$9*(1-$A5)*D$4*(1-Inputs!$C$36)-Inputs!$C$37)/Recovery!$B$12) -> 0.76961255 | E5: =MIN(1,MAX(0,Capacity!$B$9*(1-$A5)*E$4*(1-Inputs!$C$36)-Inputs!$C$37)/Recovery!$B$12) -> 0.89860281 | F5: =MIN(1,MAX(0,Capacity!$B$9*(1-$A5)*F$4*(1-Inputs!$C$36)-Inputs!$C$37)/Recovery!$B$12) -> 1
A6: 0.25 | B6: =MIN(1,MAX(0,Capacity!$B$9*(1-$A6)*B$4*(1-Inputs!$C$36)-Inputs!$C$37)/Recovery!$B$12) -> 0.45093074 | C6: =MIN(1,MAX(0,Capacity!$B$9*(1-$A6)*C$4*(1-Inputs!$C$36)-Inputs!$C$37)/Recovery!$B$12) -> 0.56474567 | D6: =MIN(1,MAX(0,Capacity!$B$9*(1-$A6)*D$4*(1-Inputs!$C$36)-Inputs!$C$37)/Recovery!$B$12) -> 0.67856061 | E6: =MIN(1,MAX(0,Capacity!$B$9*(1-$A6)*E$4*(1-Inputs!$C$36)-Inputs!$C$37)/Recovery!$B$12) -> 0.79237554 | F6: =MIN(1,MAX(0,Capacity!$B$9*(1-$A6)*F$4*(1-Inputs!$C$36)-Inputs!$C$37)/Recovery!$B$12) -> 0.90619048
A7: 0.35 | B7: =MIN(1,MAX(0,Capacity!$B$9*(1-$A7)*B$4*(1-Inputs!$C$36)-Inputs!$C$37)/Recovery!$B$12) -> 0.39022944 | C7: =MIN(1,MAX(0,Capacity!$B$9*(1-$A7)*C$4*(1-Inputs!$C$36)-Inputs!$C$37)/Recovery!$B$12) -> 0.48886905 | D7: =MIN(1,MAX(0,Capacity!$B$9*(1-$A7)*D$4*(1-Inputs!$C$36)-Inputs!$C$37)/Recovery!$B$12) -> 0.58750866 | E7: =MIN(1,MAX(0,Capacity!$B$9*(1-$A7)*E$4*(1-Inputs!$C$36)-Inputs!$C$37)/Recovery!$B$12) -> 0.68614827 | F7: =MIN(1,MAX(0,Capacity!$B$9*(1-$A7)*F$4*(1-Inputs!$C$36)-Inputs!$C$37)/Recovery!$B$12) -> 0.78478788
A8: 0.45 | B8: =MIN(1,MAX(0,Capacity!$B$9*(1-$A8)*B$4*(1-Inputs!$C$36)-Inputs!$C$37)/Recovery!$B$12) -> 0.32952814 | C8: =MIN(1,MAX(0,Capacity!$B$9*(1-$A8)*C$4*(1-Inputs!$C$36)-Inputs!$C$37)/Recovery!$B$12) -> 0.41299242 | D8: =MIN(1,MAX(0,Capacity!$B$9*(1-$A8)*D$4*(1-Inputs!$C$36)-Inputs!$C$37)/Recovery!$B$12) -> 0.49645671 | E8: =MIN(1,MAX(0,Capacity!$B$9*(1-$A8)*E$4*(1-Inputs!$C$36)-Inputs!$C$37)/Recovery!$B$12) -> 0.579921 | F8: =MIN(1,MAX(0,Capacity!$B$9*(1-$A8)*F$4*(1-Inputs!$C$36)-Inputs!$C$37)/Recovery!$B$12) -> 0.66338528
A9: 0.55 | B9: =MIN(1,MAX(0,Capacity!$B$9*(1-$A9)*B$4*(1-Inputs!$C$36)-Inputs!$C$37)/Recovery!$B$12) -> 0.26882684 | C9: =MIN(1,MAX(0,Capacity!$B$9*(1-$A9)*C$4*(1-Inputs!$C$36)-Inputs!$C$37)/Recovery!$B$12) -> 0.3371158 | D9: =MIN(1,MAX(0,Capacity!$B$9*(1-$A9)*D$4*(1-Inputs!$C$36)-Inputs!$C$37)/Recovery!$B$12) -> 0.40540476 | E9: =MIN(1,MAX(0,Capacity!$B$9*(1-$A9)*E$4*(1-Inputs!$C$36)-Inputs!$C$37)/Recovery!$B$12) -> 0.47369372 | F9: =MIN(1,MAX(0,Capacity!$B$9*(1-$A9)*F$4*(1-Inputs!$C$36)-Inputs!$C$37)/Recovery!$B$12) -> 0.54198268
A13: Debt capacity: EBITDA / all-in rate | B13: 0.05 | C13: 0.07 | D13: 0.09 | E13: 0.11 | F13: 0.13
A14: =Capacity!$B$7*0.7 -> 2870 | B14: =MAX(0,MIN($A14*(1-Inputs!$C$16)*Inputs!$C$32,($A14*(1-Inputs!$C$16)/Inputs!$C$33-Capacity!$B$6*Inputs!$C$22)/B$13)) -> 14995.75 | C14: =MAX(0,MIN($A14*(1-Inputs!$C$16)*Inputs!$C$32,($A14*(1-Inputs!$C$16)/Inputs!$C$33-Capacity!$B$6*Inputs!$C$22)/C$13)) -> 14995.75 | D14: =MAX(0,MIN($A14*(1-Inputs!$C$16)*Inputs!$C$32,($A14*(1-Inputs!$C$16)/Inputs!$C$33-Capacity!$B$6*Inputs!$C$22)/D$13)) -> 14995.75 | E14: =MAX(0,MIN($A14*(1-Inputs!$C$16)*Inputs!$C$32,($A14*(1-Inputs!$C$16)/Inputs!$C$33-Capacity!$B$6*Inputs!$C$22)/E$13)) -> 12293.182 | F14: =MAX(0,MIN($A14*(1-Inputs!$C$16)*Inputs!$C$32,($A14*(1-Inputs!$C$16)/Inputs!$C$33-Capacity!$B$6*Inputs!$C$22)/F$13)) -> 10401.923
A15: =Capacity!$B$7*0.85 -> 3485 | B15: =MAX(0,MIN($A15*(1-Inputs!$C$16)*Inputs!$C$32,($A15*(1-Inputs!$C$16)/Inputs!$C$33-Capacity!$B$6*Inputs!$C$22)/B$13)) -> 18209.125 | C15: =MAX(0,MIN($A15*(1-Inputs!$C$16)*Inputs!$C$32,($A15*(1-Inputs!$C$16)/Inputs!$C$33-Capacity!$B$6*Inputs!$C$22)/C$13)) -> 18209.125 | D15: =MAX(0,MIN($A15*(1-Inputs!$C$16)*Inputs!$C$32,($A15*(1-Inputs!$C$16)/Inputs!$C$33-Capacity!$B$6*Inputs!$C$22)/D$13)) -> 18209.125 | E15: =MAX(0,MIN($A15*(1-Inputs!$C$16)*Inputs!$C$32,($A15*(1-Inputs!$C$16)/Inputs!$C$33-Capacity!$B$6*Inputs!$C$22)/E$13)) -> 14948.864 | F15: =MAX(0,MIN($A15*(1-Inputs!$C$16)*Inputs!$C$32,($A15*(1-Inputs!$C$16)/Inputs!$C$33-Capacity!$B$6*Inputs!$C$22)/F$13)) -> 12649.038
A16: =Capacity!$B$7*1 -> 4100 | B16: =MAX(0,MIN($A16*(1-Inputs!$C$16)*Inputs!$C$32,($A16*(1-Inputs!$C$16)/Inputs!$C$33-Capacity!$B$6*Inputs!$C$22)/B$13)) -> 21422.5 | C16: =MAX(0,MIN($A16*(1-Inputs!$C$16)*Inputs!$C$32,($A16*(1-Inputs!$C$16)/Inputs!$C$33-Capacity!$B$6*Inputs!$C$22)/C$13)) -> 21422.5 | D16: =MAX(0,MIN($A16*(1-Inputs!$C$16)*Inputs!$C$32,($A16*(1-Inputs!$C$16)/Inputs!$C$33-Capacity!$B$6*Inputs!$C$22)/D$13)) -> 21422.5 | E16: =MAX(0,MIN($A16*(1-Inputs!$C$16)*Inputs!$C$32,($A16*(1-Inputs!$C$16)/Inputs!$C$33-Capacity!$B$6*Inputs!$C$22)/E$13)) -> 17604.545 | F16: =MAX(0,MIN($A16*(1-Inputs!$C$16)*Inputs!$C$32,($A16*(1-Inputs!$C$16)/Inputs!$C$33-Capacity!$B$6*Inputs!$C$22)/F$13)) -> 14896.154
A17: =Capacity!$B$7*1.15 -> 4715 | B17: =MAX(0,MIN($A17*(1-Inputs!$C$16)*Inputs!$C$32,($A17*(1-Inputs!$C$16)/Inputs!$C$33-Capacity!$B$6*Inputs!$C$22)/B$13)) -> 24635.875 | C17: =MAX(0,MIN($A17*(1-Inputs!$C$16)*Inputs!$C$32,($A17*(1-Inputs!$C$16)/Inputs!$C$33-Capacity!$B$6*Inputs!$C$22)/C$13)) -> 24635.875 | D17: =MAX(0,MIN($A17*(1-Inputs!$C$16)*Inputs!$C$32,($A17*(1-Inputs!$C$16)/Inputs!$C$33-Capacity!$B$6*Inputs!$C$22)/D$13)) -> 24635.875 | E17: =MAX(0,MIN($A17*(1-Inputs!$C$16)*Inputs!$C$32,($A17*(1-Inputs!$C$16)/Inputs!$C$33-Capacity!$B$6*Inputs!$C$22)/E$13)) -> 20260.227 | F17: =MAX(0,MIN($A17*(1-Inputs!$C$16)*Inputs!$C$32,($A17*(1-Inputs!$C$16)/Inputs!$C$33-Capacity!$B$6*Inputs!$C$22)/F$13)) -> 17143.269
A18: =Capacity!$B$7*1.3 -> 5330 | B18: =MAX(0,MIN($A18*(1-Inputs!$C$16)*Inputs!$C$32,($A18*(1-Inputs!$C$16)/Inputs!$C$33-Capacity!$B$6*Inputs!$C$22)/B$13)) -> 27849.25 | C18: =MAX(0,MIN($A18*(1-Inputs!$C$16)*Inputs!$C$32,($A18*(1-Inputs!$C$16)/Inputs!$C$33-Capacity!$B$6*Inputs!$C$22)/C$13)) -> 27849.25 | D18: =MAX(0,MIN($A18*(1-Inputs!$C$16)*Inputs!$C$32,($A18*(1-Inputs!$C$16)/Inputs!$C$33-Capacity!$B$6*Inputs!$C$22)/D$13)) -> 27849.25 | E18: =MAX(0,MIN($A18*(1-Inputs!$C$16)*Inputs!$C$32,($A18*(1-Inputs!$C$16)/Inputs!$C$33-Capacity!$B$6*Inputs!$C$22)/E$13)) -> 22915.909 | F18: =MAX(0,MIN($A18*(1-Inputs!$C$16)*Inputs!$C$32,($A18*(1-Inputs!$C$16)/Inputs!$C$33-Capacity!$B$6*Inputs!$C$22)/F$13)) -> 19390.385

Sheet Sources
A1: Sources and evidence boundaries
A2: Agency forecasts are not audited borrower financials. Accessed 27 October 2026.
A4: Key | B4: Document / section | C4: URL
A5: SP26 | B5: S&P rating action, 7 Sep 2026, Vital Holdco assigned B+; opening bullets and financial outlook. Agency forecasts, not audited actuals. | C5: https://www.spglobal.com/ratings/en/regulatory/article/-/view/type/HTML/id/3623391
A6: CIN26 | B6: Cinven, 2 Jul 2026, Vitamin Well Group to combine with EMPWR. Financial terms undisclosed; subject to approvals. | C6: https://www.cinven.com/news-insights/vitamin-well-group-empwr/
A7: CIN24 | B7: Cinven, 6 Aug 2024, agreement to become lead investor; Bridgepoint retains minority; financial terms undisclosed. | C7: https://www.cinven.com/news-insights/cinven-to-become-lead-investor-in-vitamin-well/
A8: OBDC25 | B8: Blue Owl 10-Q, 30 Sep 2025, Vital Bidco investment rows: legacy first lien S+450bp, Oct 2031. Lender holding, not total borrower debt. | C8: https://www.sec.gov/Archives/edgar/data/1655888/000165588825000024/obdc-20250930.htm
A11: Missing: final agreement, audited group accounts, closing cash/debt bridge, security and ranking, pricing, covenants.
