Workbook

Sheet Cover
C2: Thames Water restructuring | I2: Funding case | J2: =Inputs!D30 -> Upsize assumed
C3: 27 Oct 2026. GBPm. Funding and plan terms are conditional; current cash and claims unverified.
C5: Restructuring & Liability Management | D5: Result
C6: Call | D6: REJECT UNCONDITIONAL NEW MONEY
C8: Minimum cash, selected approvals (GBPm) | D8: =Liquidity!D22 -> 342.54688
C9: Peak buffer funding gap (GBPm) | D9: =Liquidity!D23 -> 0
C10: Illustrative Class A waterfall recovery | D10: =Recovery!F12 -> 0.6375
C11: Class A par break-even EV (GBPm) | D11: =Recovery!D18 -> 24105.263
C12: Class B proposed legacy recovery value (GBPm) | D12: ='Class B'!D7 -> 59
C13: Class B legacy ownership at equity proxy | D13: ='Class B'!D8 -> 0.0098333333
C14: New equity investment is a cash outflow (GBPm) | D14: ='Class B'!D9 -> 150
C17: Liquidity extension is not a completed recapitalisation. Verify accessible cash, consent conditions, tranche commitments, March maturities, creditor ranking and Ofwat approval before an unconditional commitment. Base funding case assumes approvals; it is not current liquidity.
C20: Do not quote the illustrative waterfall as an actual creditor recovery, or 5.9% as ownership. The model separates proposed consideration for old debt from the cost and risk of participating in new money.

Sheet Inputs
C2: Inputs
C3: 27 Oct 2026. GBPm. Funding and plan terms are conditional; current cash and claims unverified.
C5: Input | D5: Value | E5: Units | F5: Tag | G5: Source / reason
C6: Super senior drawn, 15 Oct | D6: 2650 | E6: GBPm | F6: S | G6: CONSENT: issuer-to-TWUL chain, not additional separate loans
C7: Existing super senior facility capacity | D7: 3000 | E7: GBPm | F7: S | G7: CONSENT: conditional capacity; undrawn is not free cash
C8: Proposed incremental capacity | D8: 2400 | E8: GBPm | F8: S | G8: CONSENT: commitments to be sought in tranches, not fully committed
C9: Existing super senior historical coupon | D9: 0.0975 | E9: % | F9: S | G9: AR26 pp139-140; A: also applied to illustrative new draws
C10: Approximate Class B debt | D10: 1000 | E10: GBPm | F10: S | G10: CLASSB: cGBP1bn, not an exact reconciled legal claim
C11: Proposed Class B legacy recovery | D11: 0.059 | E11: % | F11: S | G11: CLASSB: recovery rate, NOT 5.9% ownership of the whole equity
C12: Class B right to invest new equity | D12: 150 | E12: GBPm | F12: S | G12: CLASSB: additional investment right, not a free GBP150m recovery
C13: Historical Class A trading reference | D13: 0.69 | E13: price/par | F13: S | G13: AR26 p124: c69% at March 2026, not current or executable
C14: FY26 cash outflow before other financing | D14: 1130.2 | E14: GBPm/year | F14: S | G14: AR26 p39: excludes subsequent borrowings, leases and derivative settlements
C15: Opening accessible cash proxy, 31 Oct | D15: 200 | E15: GBPm | F15: A | G15: Current accessible balance unavailable; not rolled forward from March cash
C16: Monthly cash use before new-draw interest | D16: 200 | E16: GBPm/month | F16: A | G16: Illustrative stress above FY26 GBP94.2m monthly outflow; includes all opening-debt interest and capex, no automatic financing plug
C17: Minimum cash buffer | D17: 100 | E17: GBPm | F17: A | G17: Analyst liquidity buffer, not a covenant or regulatory requirement
... C27: Class A claim proxy | D27: 16000 | E27: GBPm | F27: A | G27: Unverified round claim amount, not a reconciliation of statutory or covenant net debt
C30: Funding case selected | D30: =CHOOSE(Inputs!$D$19+1,"Blocked","Existing only","Upsize assumed") -> Upsize assumed

Sheet Liquidity
C2: Liquidity | I2: Funding case | J2: =Inputs!D30 -> Upsize assumed
C3: 27 Oct 2026. GBPm. Funding and plan terms are conditional; current cash and claims unverified.
C5: Monthly cash use / funding | D5: 46327 | E5: 46357 | F5: 46388 | G5: 46419 | H5: 46447 | I5: 46478 | J5: 46508 | K5: 46539 | L5: 46569 | M5: 46600 | N5: 46631 | O5: 46661
C7: Opening unfunded cash position | D7: =Inputs!$D$15 -> 200 | E7: =D13 -> 738.95312 | F7: =E13 -> 532.85938 | G7: =F13 -> 717.14062 | H7: =G13 -> 507.79688 | I7: =H13 -> 688.82812 | J7: =I13 -> 476.23438 | K7: =J13 -> 654.01562 | L7: =K13 -> 438.17188 | ... O7: =N13 -> 564.89062
C8: Existing capacity draw, conditional | D8: =IF(Inputs!$D$19>=1,Inputs!$D$7-Inputs!$D$6,0) -> 350 | E8: =0 -> 0 | F8: =0 -> 0 | G8: =0 -> 0 | H8: =0 -> 0 | I8: =0 -> 0 | J8: =0 -> 0 | K8: =0 -> 0 | L8: =0 -> 0 | ... O8: =0 -> 0
C9: New upsize draw, conditional | D9: =IF(Inputs!$D$19=2,Inputs!$D$8/6,0) -> 400 | E9: =0 -> 0 | F9: =IF(Inputs!$D$19=2,Inputs!$D$8/6,0) -> 400 | G9: =0 -> 0 | H9: =IF(Inputs!$D$19=2,Inputs!$D$8/6,0) -> 400 | I9: =0 -> 0 | J9: =IF(Inputs!$D$19=2,Inputs!$D$8/6,0) -> 400 | K9: =0 -> 0 | L9: =IF(Inputs!$D$19=2,Inputs!$D$8/6,0) -> 400 | M9: =0 -> 0 | N9: =IF(Inputs!$D$19=2,Inputs!$D$8/6,0) -> 400 | O9: =0 -> 0
C10: Upsize draw fee | D10: =D9*Inputs!$D$18 -> 8 | E10: =E9*Inputs!$D$18 -> 0 | F10: =F9*Inputs!$D$18 -> 8 | G10: =G9*Inputs!$D$18 -> 0 | H10: =H9*Inputs!$D$18 -> 8 | I10: =I9*Inputs!$D$18 -> 0 | J10: =J9*Inputs!$D$18 -> 8 | K10: =K9*Inputs!$D$18 -> 0 | ... O10: =O9*Inputs!$D$18 -> 0
C11: Interest on incremental draws | D11: =(D15+SUM(D8:D9)/2)*Inputs!$D$9/12 -> 3.046875 | E11: =(E15+SUM(E8:E9)/2)*Inputs!$D$9/12 -> 6.09375 | F11: =(F15+SUM(F8:F9)/2)*Inputs!$D$9/12 -> 7.71875 | G11: =(G15+SUM(G8:G9)/2)*Inputs!$D$9/12 -> 9.34375 | H11: =(H15+SUM(H8:H9)/2)*Inputs!$D$9/12 -> 10.96875 | I11: =(I15+SUM(I8:I9)/2)*Inputs!$D$9/12 -> 12.59375 | J11: =(J15+SUM(J8:J9)/2)*Inputs!$D$9/12 -> 14.21875 | K11: =(K15+SUM(K8:K9)/2)*Inputs!$D$9/12 -> 15.84375 | ... O11: =(O15+SUM(O8:O9)/2)*Inputs!$D$9/12 -> 22.34375
C12: Class A maturity cash requirement | D12: =0 -> 0 | E12: =0 -> 0 | F12: =0 -> 0 | G12: =0 -> 0 | H12: =IF(Inputs!$D$20=0,Inputs!$D$21,0) -> 0 | I12: =0 -> 0 | J12: =0 -> 0 | K12: =0 -> 0 | L12: =0 -> 0 | M12: =0 -> 0 | N12: =0 -> 0 | O12: =0 -> 0
C13: Closing unfunded cash position | D13: =D7+SUM(D8:D9)-Inputs!$D$16-SUM(D10:D12) -> 738.95312 | E13: =E7+SUM(E8:E9)-Inputs!$D$16-SUM(E10:E12) -> 532.85938 | F13: =F7+SUM(F8:F9)-Inputs!$D$16-SUM(F10:F12) -> 717.14062 | G13: =G7+SUM(G8:G9)-Inputs!$D$16-SUM(G10:G12) -> 507.79688 | H13: =H7+SUM(H8:H9)-Inputs!$D$16-SUM(H10:H12) -> 688.82812 | I13: =I7+SUM(I8:I9)-Inputs!$D$16-SUM(I10:I12) -> 476.23438 | J13: =J7+SUM(J8:J9)-Inputs!$D$16-SUM(J10:J12) -> 654.01562 | K13: =K7+SUM(K8:K9)-Inputs!$D$16-SUM(K10:K12) -> 438.17188 | ... O13: =O7+SUM(O8:O9)-Inputs!$D$16-SUM(O10:O12) -> 342.54688
C14: Gap to minimum cash buffer | D14: =MAX(0,Inputs!$D$17-D13) -> 0 | E14: =MAX(0,Inputs!$D$17-E13) -> 0 | F14: =MAX(0,Inputs!$D$17-F13) -> 0 | G14: =MAX(0,Inputs!$D$17-G13) -> 0 | H14: =MAX(0,Inputs!$D$17-H13) -> 0 | I14: =MAX(0,Inputs!$D$17-I13) -> 0 | J14: =MAX(0,Inputs!$D$17-J13) -> 0 | K14: =MAX(0,Inputs!$D$17-K13) -> 0 | ... O14: =MAX(0,Inputs!$D$17-O13) -> 0
C15: Incremental debt opening | D15: =0 -> 0 | E15: =D18 -> 750 | F15: =E18 -> 750 | G15: =F18 -> 1150 | H15: =G18 -> 1150 | I15: =H18 -> 1550 | J15: =I18 -> 1550 | K15: =J18 -> 1950 | L15: =K18 -> 1950 | ... O15: =N18 -> 2750
C16: Super senior closing claim | D16: =Inputs!$D$6+D18 -> 3400 | E16: =Inputs!$D$6+E18 -> 3400 | F16: =Inputs!$D$6+F18 -> 3800 | G16: =Inputs!$D$6+G18 -> 3800 | H16: =Inputs!$D$6+H18 -> 4200 | I16: =Inputs!$D$6+I18 -> 4200 | J16: =Inputs!$D$6+J18 -> 4600 | K16: =Inputs!$D$6+K18 -> 4600 | ... O16: =Inputs!$D$6+O18 -> 5400
C18: Cumulative incremental draws | D18: =D15+SUM(D8:D9) -> 750 | E18: =E15+SUM(E8:E9) -> 750 | F18: =F15+SUM(F8:F9) -> 1150 | G18: =G15+SUM(G8:G9) -> 1150 | H18: =H15+SUM(H8:H9) -> 1550 | I18: =I15+SUM(I8:I9) -> 1550 | J18: =J15+SUM(J8:J9) -> 1950 | K18: =K15+SUM(K8:K9) -> 1950 | ... O18: =O15+SUM(O8:O9) -> 2750
C19: Cash bridge check | D19: =D13-(D7+SUM(D8:D9)-Inputs!$D$16-SUM(D10:D12)) -> 0 | E19: =E13-(E7+SUM(E8:E9)-Inputs!$D$16-SUM(E10:E12)) -> 0 | F19: =F13-(F7+SUM(F8:F9)-Inputs!$D$16-SUM(F10:F12)) -> 0 | G19: =G13-(G7+SUM(G8:G9)-Inputs!$D$16-SUM(G10:G12)) -> 0 | H19: =H13-(H7+SUM(H8:H9)-Inputs!$D$16-SUM(H10:H12)) -> 0 | I19: =I13-(I7+SUM(I8:I9)-Inputs!$D$16-SUM(I10:I12)) -> 0 | J19: =J13-(J7+SUM(J8:J9)-Inputs!$D$16-SUM(J10:J12)) -> 0 | K19: =K13-(K7+SUM(K8:K9)-Inputs!$D$16-SUM(K10:K12)) -> 0 | ... O19: =O13-(O7+SUM(O8:O9)-Inputs!$D$16-SUM(O10:O12)) -> 0
C22: Minimum unfunded cash position | D22: =MIN(D13:O13) -> 342.54688
C23: Peak gap to minimum buffer | D23: =MAX(D14:O14) -> 0
C24: Incremental interest paid | D24: =SUM(D11:O11) -> 159.45312
C25: Upsize fees paid | D25: =SUM(D10:O10) -> 48
C28: Negative cash positions show unfinanced need, not actual bank overdrafts. There is no automatic borrowing plug. Existing debt interest is included in monthly cash use. Only incremental draw interest is added, using half-month draw convention.
C30: Six GBP400m upsize tranches are assumptions. The GBP350m remaining existing capacity is counted once, not separately at issuer and TWUL. All draws require approvals and conditions. March maturity stress is separate from funding consent.
C32: No current opening cash verified. Monthly use is an analyst stress. FY26 historical monthly outflow is not a current burn forecast. No full balance sheet is constructed from incomplete debt and asset information.

Sheet Recovery
C2: Recovery | I2: Funding case | J2: =Inputs!D30 -> Upsize assumed
C3: 27 Oct 2026. GBPm. Funding and plan terms are conditional; current cash and claims unverified.
C5: Illustrative priority waterfall | D5: Claim / value | E5: Paid | F5: Recovery
C6: Enterprise value | D6: =Inputs!$D$24 -> 18000
C7: Costs / value leakage | D7: =D6*Inputs!$D$25 -> 900
C8: Distributable value | D8: =D6-D7 -> 17100
C10: Priority hedge / other reserve | D10: =Inputs!$D$26 -> 1500 | E10: =MIN(D10,$D$8) -> 1500 | F10: =E10/D10 -> 1
C11: Super senior, including assumed new funding | D11: =Liquidity!O16 -> 5400 | E11: =MIN(D11,MAX(0,$D$8-E10)) -> 5400 | F11: =E11/D11 -> 1
C12: Class A claim proxy | D12: =Inputs!$D$27 -> 16000 | E12: =MIN(D12,MAX(0,$D$8-SUM(E10:E11))) -> 10200 | F12: =E12/D12 -> 0.6375
C13: Class B | D13: =Inputs!$D$10 -> 1000 | E13: =MIN(D13,MAX(0,$D$8-SUM(E10:E12))) -> 0 | F13: =E13/D13 -> 0
C14: Residual equity | D14: =MAX(0,D8-SUM(E10:E13)) -> 0
C16: Value allocation check | D16: =D8-SUM(E10:E13)-D14 -> 0
C18: Class A par break-even EV / Class B attachment | D18: =SUM(D10:D12)/(1-Inputs!$D$25) -> 24105.263
C19: EV at historical c69% A reference | D19: =(D10+D11+D12*Inputs!$D$13)/(1-Inputs!$D$25) -> 18884.211
C22: Illustrative waterfall, not a legal recovery forecast. Claims, value, costs and ranking are unverified. No cash recovery is added. EV is not RCV. A maturity cash requirement does not remove a claim without funded redemption; the Class A proxy is unchanged.
C24: The c69% Class A reference is reported for March 2026. Applying it to scenario claims is a reverse sensitivity, not an executable price or a March/current market enterprise valuation. No return or buy/sell trade is inferred.

Sheet Class B
C2: Class B | I2: Funding case | J2: =Inputs!D30 -> Upsize assumed
C3: 27 Oct 2026. GBPm. Funding and plan terms are conditional; current cash and claims unverified.
C5: Conditional Class B treatment | D5: Value
C6: Approximate debt written off | D6: =Inputs!$D$10 -> 1000
C7: Implied legacy equity recovery value | D7: =D6*Inputs!$D$11 -> 59
C8: Legacy fraction of assumed post-money equity | D8: =D7/Inputs!$D$22 -> 0.0098333333
C9: New equity investment paid | D9: =Inputs!$D$12 -> 150
C10: New investment ownership fraction | D10: =D9/Inputs!$D$22 -> 0.025
C11: Realised post-money equity value | D11: =Inputs!$D$22*Inputs!$D$23 -> 6000
C12: Marked value of legacy recovery | D12: =D8*D11 -> 59
C13: Marked value of new investment | D13: =D10*D11 -> 150
C14: Net package value after NEW cash paid | D14: =SUM(D12:D13)-D9 -> 59
C15: Legacy recovery rate | D15: =D12/D6 -> 0.059
C17: Equity value for legacy holding to equal old par | D17: =D6/D8 -> 101694.92
C20: 5.9% is a recovery rate on approximately GBP1bn debt, not a stated ownership percentage. Legacy ownership is derived from an assumed GBP6bn post-money value. Actual equity allocation has not been disclosed here.
C22: The GBP150m right requires fresh investment. It is assumed exercised at fair value. Net package value subtracts that cash; it can be negative when new money loses value. The right itself is not valued. Other 5.9% participation rights and fees are excluded, not treated as free assets.
C25: Equity value multiplier | D25: Legacy value | E25: New value | F25: Net after cash | G25: Legacy recovery
C26: 0.5 | D26: =$D$7*C26 -> 29.5 | E26: =$D$9*C26 -> 75 | F26: =SUM(D26:E26)-$D$9 -> -45.5 | G26: =D26/$D$6 -> 0.0295
C27: 1 | D27: =$D$7*C27 -> 59 | E27: =$D$9*C27 -> 150 | F27: =SUM(D27:E27)-$D$9 -> 59 | G27: =D27/$D$6 -> 0.059
C28: 1.5 | D28: =$D$7*C28 -> 88.5 | E28: =$D$9*C28 -> 225 | F28: =SUM(D28:E28)-$D$9 -> 163.5 | G28: =D28/$D$6 -> 0.0885
C31: Negotiated Class B equity consideration and a hypothetical enforcement waterfall are separate analyses. They are not cash distributions from the same scenario. No agreed RP2 total equity value, new-money size or complete allocation model is claimed.

Sheet Sensitivity
C2: Sensitivity | I2: Funding case | J2: =Inputs!D30 -> Upsize assumed
C3: 27 Oct 2026. GBPm. Funding and plan terms are conditional; current cash and claims unverified.
C5: Class A recovery: EV / costs | D5: 0 | E5: 0.05 | F5: 0.1
C6: 12000 | D6: =MAX(0,MIN(1,($C6*(1-D$5)-Recovery!$D$10-Recovery!$D$11)/Recovery!$D$12)) -> 0.31875 | E6: =MAX(0,MIN(1,($C6*(1-E$5)-Recovery!$D$10-Recovery!$D$11)/Recovery!$D$12)) -> 0.28125 | F6: =MAX(0,MIN(1,($C6*(1-F$5)-Recovery!$D$10-Recovery!$D$11)/Recovery!$D$12)) -> 0.24375
C7: 15000 | D7: =MAX(0,MIN(1,($C7*(1-D$5)-Recovery!$D$10-Recovery!$D$11)/Recovery!$D$12)) -> 0.50625 | E7: =MAX(0,MIN(1,($C7*(1-E$5)-Recovery!$D$10-Recovery!$D$11)/Recovery!$D$12)) -> 0.459375 | F7: =MAX(0,MIN(1,($C7*(1-F$5)-Recovery!$D$10-Recovery!$D$11)/Recovery!$D$12)) -> 0.4125
C8: 18000 | D8: =MAX(0,MIN(1,($C8*(1-D$5)-Recovery!$D$10-Recovery!$D$11)/Recovery!$D$12)) -> 0.69375 | E8: =MAX(0,MIN(1,($C8*(1-E$5)-Recovery!$D$10-Recovery!$D$11)/Recovery!$D$12)) -> 0.6375 | F8: =MAX(0,MIN(1,($C8*(1-F$5)-Recovery!$D$10-Recovery!$D$11)/Recovery!$D$12)) -> 0.58125
C9: 21000 | D9: =MAX(0,MIN(1,($C9*(1-D$5)-Recovery!$D$10-Recovery!$D$11)/Recovery!$D$12)) -> 0.88125 | E9: =MAX(0,MIN(1,($C9*(1-E$5)-Recovery!$D$10-Recovery!$D$11)/Recovery!$D$12)) -> 0.815625 | F9: =MAX(0,MIN(1,($C9*(1-F$5)-Recovery!$D$10-Recovery!$D$11)/Recovery!$D$12)) -> 0.75
C10: 24000 | D10: =MAX(0,MIN(1,($C10*(1-D$5)-Recovery!$D$10-Recovery!$D$11)/Recovery!$D$12)) -> 1 | E10: =MAX(0,MIN(1,($C10*(1-E$5)-Recovery!$D$10-Recovery!$D$11)/Recovery!$D$12)) -> 0.99375 | F10: =MAX(0,MIN(1,($C10*(1-F$5)-Recovery!$D$10-Recovery!$D$11)/Recovery!$D$12)) -> 0.91875
C11: 27000 | D11: =MAX(0,MIN(1,($C11*(1-D$5)-Recovery!$D$10-Recovery!$D$11)/Recovery!$D$12)) -> 1 | E11: =MAX(0,MIN(1,($C11*(1-E$5)-Recovery!$D$10-Recovery!$D$11)/Recovery!$D$12)) -> 1 | F11: =MAX(0,MIN(1,($C11*(1-F$5)-Recovery!$D$10-Recovery!$D$11)/Recovery!$D$12)) -> 1
C14: Simple live recovery formula with scenario super senior and Class A claims. This tests value and costs, not changes in legal ranking or regulatory outcomes.

Sheet Sources
C2: Sources
C3: 27 Oct 2026. GBPm. Funding and plan terms are conditional; current cash and claims unverified.
C5: ID | D5: Document / locator | E5: URL
C6: CONSENT | D6: TWUL, 15 Oct 2026, Sixteenth Consent Requests: facility draw, conditional upsize, pari passu proposal, vote 29 Oct | E6: https://www.thameswater.co.uk/news/2026/oct/twul-sixteenth-consent-requests-results
C7: CLASSB | D7: TWUL, 16 Oct 2026, Class B TSA: proposed full debt write-off, c5.9% recovery, rights to invest; not completed | E7: https://www.thameswater.co.uk/news/2026/oct/class-b-creditors-update
C8: AR26 | D8: TWUL Group annual report 2025/26: p39 cash flow; pp139-140 loans/bonds; p124 hedging priority and historical c69% Class A trading level; pp108-109 March 2027 maturity extension | E8: https://www.thameswater.co.uk/media-library/2tad3w44/annual-report-2025-26.pdf
