Workbook

Sheet Cover
A1: US 12–1 momentum | B1: 28 October 2026 / data through September
A2: Verdict | B2: Reject standalone strategy under base costs
A3: Design net Sharpe | B3: =Performance!C2 -> 0.83808784
A4: Evaluation net Sharpe | B4: =Performance!C3 -> 0.050320175
A5: Annual execution + borrow | B5: =Performance!G4+Performance!H4 -> 0.022
A6: Full-history monthly drawdown | B6: =Performance!J4 -> -0.57599944
A7: Gross return correlation to Mom | B7: =Performance!I4 -> 0.89892291
A8: Data scope | B8: Published monthly historical-universe deciles; no independent stock-level signals
A9: Turnover | B9: 50% per leg assumed, not observed
A10: Test scope | B10: Historical split and expanding annual review; not a prospective preregistered test

Sheet Inputs
A1: Driver | B1: Value | C1: S/A/D / interpretation
A2: Absolute weight per leg | B2: 0.5 | C2: A: 50% long winners, 50% short losers
A3: Execution bp per traded notional | B3: 10 | C3: A: buys and sells charged
A4: One-way monthly turnover per leg | B4: 0.5 | C4: A: 50% replacement; not measured
A5: Annual borrow rate | B5: 0.02 | C5: A: charged on short weight
A6: Annualisation months | B6: 12 | C6: A
A7: Design end | B7: 1999-12 | C7: A: fixed split
A8: Evaluation start | B8: 2000-01 | C8: D: next month
A9: Source end | B9: 2026-09 | C9: S: 202609 CRSP release
A10: Gross / net exposure | B10: =2*B2 -> 1 | C10: =B2-B2 -> 0
A11: Traded notional per NAV | B11: =4*B2*B4 -> 1 | C11: D: buys plus sells, both legs

Sheet Backtest
A1: Month | B1: Winner | C1: Loser | D1: Gross excess | E1: Execution cost | F1: Borrow cost | G1: Net excess | H1: P&L index | I1: High water | J1: Drawdown | K1: Published Mom
A2: =Data!A2 -> 1963-01 | B2: =Data!K2 -> 0.0317 | C2: =Data!B2 -> 0.0488 | D2: =(B2-C2)*Inputs!B2 -> -0.00855 | E2: =4*Inputs!B2*Inputs!B4*Inputs!B3/10000 -> 0.001 | F2: =Inputs!B2*Inputs!B5/Inputs!B6 -> 0.00083333333 | G2: =D2-E2-F2 -> -0.010383333 | H2: =(1+G2) -> 0.98961667 | I2: =MAX(1,H$2:H2) -> 1 | J2: =H2/I2-1 -> -0.010383333 | K2: =Data!L2 -> -0.0214
A3: =Data!A3 -> 1963-02 | B3: =Data!K3 -> -0.0159 | C3: =Data!B3 -> -0.0377 | D3: =(B3-C3)*Inputs!B2 -> 0.0109 | E3: =4*Inputs!B2*Inputs!B4*Inputs!B3/10000 -> 0.001 | F3: =Inputs!B2*Inputs!B5/Inputs!B6 -> 0.00083333333 | G3: =D3-E3-F3 -> 0.0090666667 | H3: =(1+G3)*H2 -> 0.99858919 | I3: =MAX(1,H$2:H3) -> 1 | J3: =H3/I3-1 -> -0.0014108089 | K3: =Data!L3 -> 0.0252
A4: =Data!A4 -> 1963-03 | B4: =Data!K4 -> 0.0539 | C4: =Data!B4 -> 0.02 | D4: =(B4-C4)*Inputs!B2 -> 0.01695 | E4: =4*Inputs!B2*Inputs!B4*Inputs!B3/10000 -> 0.001 | F4: =Inputs!B2*Inputs!B5/Inputs!B6 -> 0.00083333333 | G4: =D4-E4-F4 -> 0.015116667 | H4: =(1+G4)*H3 -> 1.0136845 | I4: =MAX(1,H$2:H4) -> 1.0136845 | J4: =H4/I4-1 -> 0 | K4: =Data!L4 -> 0.0158
A5: =Data!A5 -> 1963-04 | B5: =Data!K5 -> 0.0505 | C5: =Data!B5 -> 0.0361 | D5: =(B5-C5)*Inputs!B2 -> 0.0072 | E5: =4*Inputs!B2*Inputs!B4*Inputs!B3/10000 -> 0.001 | F5: =Inputs!B2*Inputs!B5/Inputs!B6 -> 0.00083333333 | G5: =D5-E5-F5 -> 0.0053666667 | H5: =(1+G5)*H4 -> 1.0191246 | I5: =MAX(1,H$2:H5) -> 1.0191246 | J5: =H5/I5-1 -> 0 | K5: =Data!L5 -> -0.0006
A6: =Data!A6 -> 1963-05 | B6: =Data!K6 -> 0.0312 | C6: =Data!B6 -> 0.0297 | D6: =(B6-C6)*Inputs!B2 -> 0.00075 | E6: =4*Inputs!B2*Inputs!B4*Inputs!B3/10000 -> 0.001 | F6: =Inputs!B2*Inputs!B5/Inputs!B6 -> 0.00083333333 | G6: =D6-E6-F6 -> -0.0010833333 | H6: =(1+G6)*H5 -> 1.0180206 | I6: =MAX(1,H$2:H6) -> 1.0191246 | J6: =H6/I6-1 -> -0.0010833333 | K6: =Data!L6 -> 0.0029
A7: =Data!A7 -> 1963-06 | B7: =Data!K7 -> -0.0214 | C7: =Data!B7 -> -0.0174 | D7: =(B7-C7)*Inputs!B2 -> -0.002 | E7: =4*Inputs!B2*Inputs!B4*Inputs!B3/10000 -> 0.001 | F7: =Inputs!B2*Inputs!B5/Inputs!B6 -> 0.00083333333 | G7: =D7-E7-F7 -> -0.0038333333 | H7: =(1+G7)*H6 -> 1.0141182 | I7: =MAX(1,H$2:H7) -> 1.0191246 | J7: =H7/I7-1 -> -0.0049125139 | K7: =Data!L7 -> 0.0116
A8: =Data!A8 -> 1963-07 | B8: =Data!K8 -> 0.0041 | C8: =Data!B8 -> -0.0277 | D8: =(B8-C8)*Inputs!B2 -> 0.0159 | E8: =4*Inputs!B2*Inputs!B4*Inputs!B3/10000 -> 0.001 | F8: =Inputs!B2*Inputs!B5/Inputs!B6 -> 0.00083333333 | G8: =D8-E8-F8 -> 0.014066667 | H8: =(1+G8)*H7 -> 1.0283834 | I8: =MAX(1,H$2:H8) -> 1.0283834 | J8: =H8/I8-1 -> 0 | K8: =Data!L8 -> 0.0101
A9: =Data!A9 -> 1963-08 | B9: =Data!K9 -> 0.0922 | C9: =Data!B9 -> 0.0603 | D9: =(B9-C9)*Inputs!B2 -> 0.01595 | E9: =4*Inputs!B2*Inputs!B4*Inputs!B3/10000 -> 0.001 | F9: =Inputs!B2*Inputs!B5/Inputs!B6 -> 0.00083333333 | G9: =D9-E9-F9 -> 0.014116667 | H9: =(1+G9)*H8 -> 1.0429008 | I9: =MAX(1,H$2:H9) -> 1.0429008 | J9: =H9/I9-1 -> 0 | K9: =Data!L9 -> 0.01
A10: =Data!A10 -> 1963-09 | B10: =Data!K10 -> -0.0207 | C10: =Data!B10 -> -0.0308 | D10: =(B10-C10)*Inputs!B2 -> 0.00505 | E10: =4*Inputs!B2*Inputs!B4*Inputs!B3/10000 -> 0.001 | F10: =Inputs!B2*Inputs!B5/Inputs!B6 -> 0.00083333333 | G10: =D10-E10-F10 -> 0.0032166667 | H10: =(1+G10)*H9 -> 1.0462554 | I10: =MAX(1,H$2:H10) -> 1.0462554 | J10: =H10/I10-1 -> 0 | K10: =Data!L10 -> 0.0012
A11: =Data!A11 -> 1963-10 | B11: =Data!K11 -> 0.0549 | C11: =Data!B11 -> 0.019 | D11: =(B11-C11)*Inputs!B2 -> 0.01795 | E11: =4*Inputs!B2*Inputs!B4*Inputs!B3/10000 -> 0.001 | F11: =Inputs!B2*Inputs!B5/Inputs!B6 -> 0.00083333333 | G11: =D11-E11-F11 -> 0.016116667 | H11: =(1+G11)*H10 -> 1.0631176 | I11: =MAX(1,H$2:H11) -> 1.0631176 | J11: =H11/I11-1 -> 0 | K11: =Data!L11 -> 0.0313
A12: =Data!A12 -> 1963-11 | B12: =Data!K12 -> -0.0018 | C12: =Data!B12 -> 0.002 | D12: =(B12-C12)*Inputs!B2 -> -0.0019 | E12: =4*Inputs!B2*Inputs!B4*Inputs!B3/10000 -> 0.001 | F12: =Inputs!B2*Inputs!B5/Inputs!B6 -> 0.00083333333 | G12: =D12-E12-F12 -> -0.0037333333 | H12: =(1+G12)*H11 -> 1.0591486 | I12: =MAX(1,H$2:H12) -> 1.0631176 | J12: =H12/I12-1 -> -0.0037333333 | K12: =Data!L12 -> -0.0077
A13: =Data!A13 -> 1963-12 | B13: =Data!K13 -> 0.0077 | C13: =Data!B13 -> -0.0249 | D13: =(B13-C13)*Inputs!B2 -> 0.0163 | E13: =4*Inputs!B2*Inputs!B4*Inputs!B3/10000 -> 0.001 | F13: =Inputs!B2*Inputs!B5/Inputs!B6 -> 0.00083333333 | G13: =D13-E13-F13 -> 0.014466667 | H13: =(1+G13)*H12 -> 1.074471 | I13: =MAX(1,H$2:H13) -> 1.074471 | J13: =H13/I13-1 -> 0 | K13: =Data!L13 -> 0.0184
A14: =Data!A14 -> 1964-01 | B14: =Data!K14 -> 0.0191 | C14: =Data!B14 -> 0.0096 | D14: =(B14-C14)*Inputs!B2 -> 0.00475 | E14: =4*Inputs!B2*Inputs!B4*Inputs!B3/10000 -> 0.001 | F14: =Inputs!B2*Inputs!B5/Inputs!B6 -> 0.00083333333 | G14: =D14-E14-F14 -> 0.0029166667 | H14: =(1+G14)*H13 -> 1.0776048 | I14: =MAX(1,H$2:H14) -> 1.0776048 | J14: =H14/I14-1 -> 0 | K14: =Data!L14 -> 0.0081
A15: =Data!A15 -> 1964-02 | B15: =Data!K15 -> 0.0355 | C15: =Data!B15 -> 0.0176 | D15: =(B15-C15)*Inputs!B2 -> 0.00895 | E15: =4*Inputs!B2*Inputs!B4*Inputs!B3/10000 -> 0.001 | F15: =Inputs!B2*Inputs!B5/Inputs!B6 -> 0.00083333333 | G15: =D15-E15-F15 -> 0.0071166667 | H15: =(1+G15)*H14 -> 1.0852738 | I15: =MAX(1,H$2:H15) -> 1.0852738 | J15: =H15/I15-1 -> 0 | K15: =Data!L15 -> 0.0033
A16: =Data!A16 -> 1964-03 | B16: =Data!K16 -> 0.036 | C16: =Data!B16 -> 0.0051 | D16: =(B16-C16)*Inputs!B2 -> 0.01545 | E16: =4*Inputs!B2*Inputs!B4*Inputs!B3/10000 -> 0.001 | F16: =Inputs!B2*Inputs!B5/Inputs!B6 -> 0.00083333333 | G16: =D16-E16-F16 -> 0.013616667 | H16: =(1+G16)*H15 -> 1.1000516 | I16: =MAX(1,H$2:H16) -> 1.1000516 | J16: =H16/I16-1 -> 0 | K16: =Data!L16 -> 0.0073
A17: =Data!A17 -> 1964-04 | B17: =Data!K17 -> -0.0051 | C17: =Data!B17 -> -0.0065 | D17: =(B17-C17)*Inputs!B2 -> 0.0007 | E17: =4*Inputs!B2*Inputs!B4*Inputs!B3/10000 -> 0.001 | F17: =Inputs!B2*Inputs!B5/Inputs!B6 -> 0.00083333333 | G17: =D17-E17-F17 -> -0.0011333333 | H17: =(1+G17)*H16 -> 1.0988049 | I17: =MAX(1,H$2:H17) -> 1.1000516 | J17: =H17/I17-1 -> -0.0011333333 | K17: =Data!L17 -> -0.0064
A18: =Data!A18 -> 1964-05 | B18: =Data!K18 -> 0.0395 | C18: =Data!B18 -> 0.0024 | D18: =(B18-C18)*Inputs!B2 -> 0.01855 | E18: =4*Inputs!B2*Inputs!B4*Inputs!B3/10000 -> 0.001 | F18: =Inputs!B2*Inputs!B5/Inputs!B6 -> 0.00083333333 | G18: =D18-E18-F18 -> 0.016716667 | H18: =(1+G18)*H17 -> 1.1171732 | I18: =MAX(1,H$2:H18) -> 1.1171732 | J18: =H18/I18-1 -> 0 | K18: =Data!L18 -> 0.0253
A19: =Data!A19 -> 1964-06 | B19: =Data!K19 -> 0.0089 | C19: =Data!B19 -> 0.0102 | D19: =(B19-C19)*Inputs!B2 -> -0.00065 | E19: =4*Inputs!B2*Inputs!B4*Inputs!B3/10000 -> 0.001 | F19: =Inputs!B2*Inputs!B5/Inputs!B6 -> 0.00083333333 | G19: =D19-E19-F19 -> -0.0024833333 | H19: =(1+G19)*H18 -> 1.1143989 | I19: =MAX(1,H$2:H19) -> 1.1171732 | J19: =H19/I19-1 -> -0.0024833333 | K19: =Data!L19 -> 0.0047
A20: =Data!A20 -> 1964-07 | B20: =Data!K20 -> 0.0073 | C20: =Data!B20 -> 0.0189 | D20: =(B20-C20)*Inputs!B2 -> -0.0058 | E20: =4*Inputs!B2*Inputs!B4*Inputs!B3/10000 -> 0.001 | F20: =Inputs!B2*Inputs!B5/Inputs!B6 -> 0.00083333333 | G20: =D20-E20-F20 -> -0.0076333333 | H20: =(1+G20)*H19 -> 1.1058924 | I20: =MAX(1,H$2:H20) -> 1.1171732 | J20: =H20/I20-1 -> -0.010097711 | K20: =Data!L20 -> -0.0037
A21: =Data!A21 -> 1964-08 | B21: =Data!K21 -> -0.0088 | C21: =Data!B21 -> -0.0131 | D21: =(B21-C21)*Inputs!B2 -> 0.00215 | E21: =4*Inputs!B2*Inputs!B4*Inputs!B3/10000 -> 0.001 | F21: =Inputs!B2*Inputs!B5/Inputs!B6 -> 0.00083333333 | G21: =D21-E21-F21 -> 0.00031666667 | H21: =(1+G21)*H20 -> 1.1062426 | I21: =MAX(1,H$2:H21) -> 1.1171732 | J21: =H21/I21-1 -> -0.0097842415 | K21: =Data!L21 -> -0.0024
A22: =Data!A22 -> 1964-09 | B22: =Data!K22 -> 0.0639 | C22: =Data!B22 -> 0.0579 | D22: =(B22-C22)*Inputs!B2 -> 0.003 | E22: =4*Inputs!B2*Inputs!B4*Inputs!B3/10000 -> 0.001 | F22: =Inputs!B2*Inputs!B5/Inputs!B6 -> 0.00083333333 | G22: =D22-E22-F22 -> 0.0011666667 | H22: =(1+G22)*H21 -> 1.1075332 | I22: =MAX(1,H$2:H22) -> 1.1171732 | J22: =H22/I22-1 -> -0.0086289898 | K22: =Data!L22 -> -0.0039
A23: =Data!A23 -> 1964-10 | B23: =Data!K23 -> 0.0004 | C23: =Data!B23 -> 0.0154 | D23: =(B23-C23)*Inputs!B2 -> -0.0075 | E23: =4*Inputs!B2*Inputs!B4*Inputs!B3/10000 -> 0.001 | F23: =Inputs!B2*Inputs!B5/Inputs!B6 -> 0.00083333333 | G23: =D23-E23-F23 -> -0.0093333333 | H23: =(1+G23)*H22 -> 1.0971962 | I23: =MAX(1,H$2:H23) -> 1.1171732 | J23: =H23/I23-1 -> -0.017881786 | K23: =Data!L23 -> 0.0019
A24: =Data!A24 -> 1964-11 | B24: =Data!K24 -> 0.0001 | C24: =Data!B24 -> -0.0306 | D24: =(B24-C24)*Inputs!B2 -> 0.01535 | E24: =4*Inputs!B2*Inputs!B4*Inputs!B3/10000 -> 0.001 | F24: =Inputs!B2*Inputs!B5/Inputs!B6 -> 0.00083333333 | G24: =D24-E24-F24 -> 0.013516667 | H24: =(1+G24)*H23 -> 1.1120266 | I24: =MAX(1,H$2:H24) -> 1.1171732 | J24: =H24/I24-1 -> -0.0046068213 | K24: =Data!L24 -> 0.011
A25: =Data!A25 -> 1964-12 | B25: =Data!K25 -> -0.0079 | C25: =Data!B25 -> -0.0022 | D25: =(B25-C25)*Inputs!B2 -> -0.00285 | E25: =4*Inputs!B2*Inputs!B4*Inputs!B3/10000 -> 0.001 | F25: =Inputs!B2*Inputs!B5/Inputs!B6 -> 0.00083333333 | G25: =D25-E25-F25 -> -0.0046833333 | H25: =(1+G25)*H24 -> 1.1068186 | I25: =MAX(1,H$2:H25) -> 1.1171732 | J25: =H25/I25-1 -> -0.0092685794 | K25: =Data!L25 -> -0.007
A26: =Data!A26 -> 1965-01 | B26: =Data!K26 -> 0.0452 | C26: =Data!B26 -> 0.078 | D26: =(B26-C26)*Inputs!B2 -> -0.0164 | E26: =4*Inputs!B2*Inputs!B4*Inputs!B3/10000 -> 0.001 | F26: =Inputs!B2*Inputs!B5/Inputs!B6 -> 0.00083333333 | G26: =D26-E26-F26 -> -0.018233333 | H26: =(1+G26)*H25 -> 1.0866376 | I26: =MAX(1,H$2:H26) -> 1.1171732 | J26: =H26/I26-1 -> -0.027332916 | K26: =Data!L26 -> -0.0139
A27: =Data!A27 -> 1965-02 | B27: =Data!K27 -> 0.0281 | C27: =Data!B27 -> 0.0249 | D27: =(B27-C27)*Inputs!B2 -> 0.0016 | E27: =4*Inputs!B2*Inputs!B4*Inputs!B3/10000 -> 0.001 | F27: =Inputs!B2*Inputs!B5/Inputs!B6 -> 0.00083333333 | G27: =D27-E27-F27 -> -0.00023333333 | H27: =(1+G27)*H26 -> 1.0863841 | I27: =MAX(1,H$2:H27) -> 1.1171732 | J27: =H27/I27-1 -> -0.027559871 | K27: =Data!L27 -> 0.0024
A28: =Data!A28 -> 1965-03 | B28: =Data!K28 -> 0.0028 | C28: =Data!B28 -> -0.0111 | D28: =(B28-C28)*Inputs!B2 -> 0.00695 | E28: =4*Inputs!B2*Inputs!B4*Inputs!B3/10000 -> 0.001 | F28: =Inputs!B2*Inputs!B5/Inputs!B6 -> 0.00083333333 | G28: =D28-E28-F28 -> 0.0051166667 | H28: =(1+G28)*H27 -> 1.0919428 | I28: =MAX(1,H$2:H28) -> 1.1171732 | J28: =H28/I28-1 -> -0.022584219 | K28: =Data!L28 -> 0.0017
A29: =Data!A29 -> 1965-04 | B29: =Data!K29 -> 0.0507 | C29: =Data!B29 -> 0.0271 | D29: =(B29-C29)*Inputs!B2 -> 0.0118 | E29: =4*Inputs!B2*Inputs!B4*Inputs!B3/10000 -> 0.001 | F29: =Inputs!B2*Inputs!B5/Inputs!B6 -> 0.00083333333 | G29: =D29-E29-F29 -> 0.0099666667 | H29: =(1+G29)*H28 -> 1.1028258 | I29: =MAX(1,H$2:H29) -> 1.1171732 | J29: =H29/I29-1 -> -0.012842642 | K29: =Data!L29 -> 0.0253
A30: =Data!A30 -> 1965-05 | B30: =Data!K30 -> -0.0062 | C30: =Data!B30 -> -0.0123 | D30: =(B30-C30)*Inputs!B2 -> 0.00305 | E30: =4*Inputs!B2*Inputs!B4*Inputs!B3/10000 -> 0.001 | F30: =Inputs!B2*Inputs!B5/Inputs!B6 -> 0.00083333333 | G30: =D30-E30-F30 -> 0.0012166667 | H30: =(1+G30)*H29 -> 1.1041676 | I30: =MAX(1,H$2:H30) -> 1.1171732 | J30: =H30/I30-1 -> -0.011641601 | K30: =Data!L30 -> 0.0056
A31: =Data!A31 -> 1965-06 | B31: =Data!K31 -> -0.094 | C31: =Data!B31 -> -0.0346 | D31: =(B31-C31)*Inputs!B2 -> -0.0297 | E31: =4*Inputs!B2*Inputs!B4*Inputs!B3/10000 -> 0.001 | F31: =Inputs!B2*Inputs!B5/Inputs!B6 -> 0.00083333333 | G31: =D31-E31-F31 -> -0.031533333 | H31: =(1+G31)*H30 -> 1.0693495 | I31: =MAX(1,H$2:H31) -> 1.1171732 | J31: =H31/I31-1 -> -0.042807835 | K31: =Data!L31 -> -0.0318
A32: =Data!A32 -> 1965-07 | B32: =Data!K32 -> 0.0746 | C32: =Data!B32 -> 0.0095 | D32: =(B32-C32)*Inputs!B2 -> 0.03255 | E32: =4*Inputs!B2*Inputs!B4*Inputs!B3/10000 -> 0.001 | F32: =Inputs!B2*Inputs!B5/Inputs!B6 -> 0.00083333333 | G32: =D32-E32-F32 -> 0.030716667 | H32: =(1+G32)*H31 -> 1.1021963 | I32: =MAX(1,H$2:H32) -> 1.1171732 | J32: =H32/I32-1 -> -0.013406083 | K32: =Data!L32 -> 0.0409
A33: =Data!A33 -> 1965-08 | B33: =Data!K33 -> 0.0766 | C33: =Data!B33 -> 0.0465 | D33: =(B33-C33)*Inputs!B2 -> 0.01505 | E33: =4*Inputs!B2*Inputs!B4*Inputs!B3/10000 -> 0.001 | F33: =Inputs!B2*Inputs!B5/Inputs!B6 -> 0.00083333333 | G33: =D33-E33-F33 -> 0.013216667 | H33: =(1+G33)*H32 -> 1.1167637 | I33: =MAX(1,H$2:H33) -> 1.1171732 | J33: =H33/I33-1 -> -0.00036659983 | K33: =Data!L33 -> 0.0257
A34: =Data!A34 -> 1965-09 | B34: =Data!K34 -> 0.0533 | C34: =Data!B34 -> 0.0191 | D34: =(B34-C34)*Inputs!B2 -> 0.0171 | E34: =4*Inputs!B2*Inputs!B4*Inputs!B3/10000 -> 0.001 | F34: =Inputs!B2*Inputs!B5/Inputs!B6 -> 0.00083333333 | G34: =D34-E34-F34 -> 0.015266667 | H34: =(1+G34)*H33 -> 1.1338129 | I34: =MAX(1,H$2:H34) -> 1.1338129 | J34: =H34/I34-1 -> 0 | K34: =Data!L34 -> 0.0328
A35: =Data!A35 -> 1965-10 | B35: =Data!K35 -> 0.0786 | C35: =Data!B35 -> 0.0392 | D35: =(B35-C35)*Inputs!B2 -> 0.0197 | E35: =4*Inputs!B2*Inputs!B4*Inputs!B3/10000 -> 0.001 | F35: =Inputs!B2*Inputs!B5/Inputs!B6 -> 0.00083333333 | G35: =D35-E35-F35 -> 0.017866667 | H35: =(1+G35)*H34 -> 1.1540704 | I35: =MAX(1,H$2:H35) -> 1.1540704 | J35: =H35/I35-1 -> 0 | K35: =Data!L35 -> 0.0344
A36: =Data!A36 -> 1965-11 | B36: =Data!K36 -> 0.085 | C36: =Data!B36 -> -0.0141 | D36: =(B36-C36)*Inputs!B2 -> 0.04955 | E36: =4*Inputs!B2*Inputs!B4*Inputs!B3/10000 -> 0.001 | F36: =Inputs!B2*Inputs!B5/Inputs!B6 -> 0.00083333333 | G36: =D36-E36-F36 -> 0.047716667 | H36: =(1+G36)*H35 -> 1.2091388 | I36: =MAX(1,H$2:H36) -> 1.2091388 | J36: =H36/I36-1 -> 0 | K36: =Data!L36 -> 0.0441
A37: =Data!A37 -> 1965-12 | B37: =Data!K37 -> 0.0405 | C37: =Data!B37 -> 0.0335 | D37: =(B37-C37)*Inputs!B2 -> 0.0035 | E37: =4*Inputs!B2*Inputs!B4*Inputs!B3/10000 -> 0.001 | F37: =Inputs!B2*Inputs!B5/Inputs!B6 -> 0.00083333333 | G37: =D37-E37-F37 -> 0.0016666667 | H37: =(1+G37)*H36 -> 1.211154 | I37: =MAX(1,H$2:H37) -> 1.211154 | J37: =H37/I37-1 -> 0 | K37: =Data!L37 -> -0.001
A38: =Data!A38 -> 1966-01 | B38: =Data!K38 -> 0.09 | C38: =Data!B38 -> -0.002 | D38: =(B38-C38)*Inputs!B2 -> 0.046 | E38: =4*Inputs!B2*Inputs!B4*Inputs!B3/10000 -> 0.001 | F38: =Inputs!B2*Inputs!B5/Inputs!B6 -> 0.00083333333 | G38: =D38-E38-F38 -> 0.044166667 | H38: =(1+G38)*H37 -> 1.2646467 | I38: =MAX(1,H$2:H38) -> 1.2646467 | J38: =H38/I38-1 -> 0 | K38: =Data!L38 -> 0.0525
A39: =Data!A39 -> 1966-02 | B39: =Data!K39 -> 0.0827 | C39: =Data!B39 -> -0.0259 | D39: =(B39-C39)*Inputs!B2 -> 0.0543 | E39: =4*Inputs!B2*Inputs!B4*Inputs!B3/10000 -> 0.001 | F39: =Inputs!B2*Inputs!B5/Inputs!B6 -> 0.00083333333 | G39: =D39-E39-F39 -> 0.052466667 | H39: =(1+G39)*H38 -> 1.3309985 | I39: =MAX(1,H$2:H39) -> 1.3309985 | J39: =H39/I39-1 -> 0 | K39: =Data!L39 -> 0.0459
A40: =Data!A40 -> 1966-03 | B40: =Data!K40 -> 0.0112 | C40: =Data!B40 -> -0.0382 | D40: =(B40-C40)*Inputs!B2 -> 0.0247 | E40: =4*Inputs!B2*Inputs!B4*Inputs!B3/10000 -> 0.001 | F40: =Inputs!B2*Inputs!B5/Inputs!B6 -> 0.00083333333 | G40: =D40-E40-F40 -> 0.022866667 | H40: =(1+G40)*H39 -> 1.361434 | I40: =MAX(1,H$2:H40) -> 1.361434 | J40: =H40/I40-1 -> 0 | K40: =Data!L40 -> 0.0146
A41: =Data!A41 -> 1966-04 | B41: =Data!K41 -> 0.0508 | C41: =Data!B41 -> 0.0189 | D41: =(B41-C41)*Inputs!B2 -> 0.01595 | E41: =4*Inputs!B2*Inputs!B4*Inputs!B3/10000 -> 0.001 | F41: =Inputs!B2*Inputs!B5/Inputs!B6 -> 0.00083333333 | G41: =D41-E41-F41 -> 0.014116667 | H41: =(1+G41)*H40 -> 1.3806529 | I41: =MAX(1,H$2:H41) -> 1.3806529 | J41: =H41/I41-1 -> 0 | K41: =Data!L41 -> 0.0593
A42: =Data!A42 -> 1966-05 | B42: =Data!K42 -> -0.1098 | C42: =Data!B42 -> -0.0336 | D42: =(B42-C42)*Inputs!B2 -> -0.0381 | E42: =4*Inputs!B2*Inputs!B4*Inputs!B3/10000 -> 0.001 | F42: =Inputs!B2*Inputs!B5/Inputs!B6 -> 0.00083333333 | G42: =D42-E42-F42 -> -0.039933333 | H42: =(1+G42)*H41 -> 1.3255188 | I42: =MAX(1,H$2:H42) -> 1.3806529 | J42: =H42/I42-1 -> -0.039933333 | K42: =Data!L42 -> -0.0473
A43: =Data!A43 -> 1966-06 | B43: =Data!K43 -> 0.0361 | C43: =Data!B43 -> -0.0152 | D43: =(B43-C43)*Inputs!B2 -> 0.02565 | E43: =4*Inputs!B2*Inputs!B4*Inputs!B3/10000 -> 0.001 | F43: =Inputs!B2*Inputs!B5/Inputs!B6 -> 0.00083333333 | G43: =D43-E43-F43 -> 0.023816667 | H43: =(1+G43)*H42 -> 1.3570882 | I43: =MAX(1,H$2:H43) -> 1.3806529 | J43: =H43/I43-1 -> -0.017067746 | K43: =Data!L43 -> 0.0324
A44: =Data!A44 -> 1966-07 | B44: =Data!K44 -> -0.0216 | C44: =Data!B44 -> -0.0177 | D44: =(B44-C44)*Inputs!B2 -> -0.00195 | E44: =4*Inputs!B2*Inputs!B4*Inputs!B3/10000 -> 0.001 | F44: =Inputs!B2*Inputs!B5/Inputs!B6 -> 0.00083333333 | G44: =D44-E44-F44 -> -0.0037833333 | H44: =(1+G44)*H43 -> 1.3519539 | I44: =MAX(1,H$2:H44) -> 1.3806529 | J44: =H44/I44-1 -> -0.020786506 | K44: =Data!L44 -> -0.013
A45: =Data!A45 -> 1966-08 | B45: =Data!K45 -> -0.0918 | C45: =Data!B45 -> -0.0507 | D45: =(B45-C45)*Inputs!B2 -> -0.02055 | E45: =4*Inputs!B2*Inputs!B4*Inputs!B3/10000 -> 0.001 | F45: =Inputs!B2*Inputs!B5/Inputs!B6 -> 0.00083333333 | G45: =D45-E45-F45 -> -0.022383333 | H45: =(1+G45)*H44 -> 1.3216927 | I45: =MAX(1,H$2:H45) -> 1.3806529 | J45: =H45/I45-1 -> -0.042704568 | K45: =Data!L45 -> -0.0221
A46: =Data!A46 -> 1966-09 | B46: =Data!K46 -> -0.0487 | C46: =Data!B46 -> -0.0387 | D46: =(B46-C46)*Inputs!B2 -> -0.005 | E46: =4*Inputs!B2*Inputs!B4*Inputs!B3/10000 -> 0.001 | F46: =Inputs!B2*Inputs!B5/Inputs!B6 -> 0.00083333333 | G46: =D46-E46-F46 -> -0.0068333333 | H46: =(1+G46)*H45 -> 1.3126611 | I46: =MAX(1,H$2:H46) -> 1.3806529 | J46: =H46/I46-1 -> -0.049246087 | K46: =Data!L46 -> -0.0187
A47: =Data!A47 -> 1966-10 | B47: =Data!K47 -> -0.0576 | C47: =Data!B47 -> 0.0233 | D47: =(B47-C47)*Inputs!B2 -> -0.04045 | E47: =4*Inputs!B2*Inputs!B4*Inputs!B3/10000 -> 0.001 | F47: =Inputs!B2*Inputs!B5/Inputs!B6 -> 0.00083333333 | G47: =D47-E47-F47 -> -0.042283333 | H47: =(1+G47)*H46 -> 1.2571574 | I47: =MAX(1,H$2:H47) -> 1.3806529 | J47: =H47/I47-1 -> -0.089447131 | K47: =Data!L47 -> -0.052
A48: =Data!A48 -> 1966-11 | B48: =Data!K48 -> 0.121 | C48: =Data!B48 -> -0.0093 | D48: =(B48-C48)*Inputs!B2 -> 0.06515 | E48: =4*Inputs!B2*Inputs!B4*Inputs!B3/10000 -> 0.001 | F48: =Inputs!B2*Inputs!B5/Inputs!B6 -> 0.00083333333 | G48: =D48-E48-F48 -> 0.063316667 | H48: =(1+G48)*H47 -> 1.3367564 | I48: =MAX(1,H$2:H48) -> 1.3806529 | J48: =H48/I48-1 -> -0.031793959 | K48: =Data!L48 -> 0.0576
A49: =Data!A49 -> 1966-12 | B49: =Data!K49 -> 0.0138 | C49: =Data!B49 -> 0.0249 | D49: =(B49-C49)*Inputs!B2 -> -0.00555 | E49: =4*Inputs!B2*Inputs!B4*Inputs!B3/10000 -> 0.001 | F49: =Inputs!B2*Inputs!B5/Inputs!B6 -> 0.00083333333 | G49: =D49-E49-F49 -> -0.0073833333 | H49: =(1+G49)*H48 -> 1.3268867 | I49: =MAX(1,H$2:H49) -> 1.3806529 | J49: =H49/I49-1 -> -0.038942547 | K49: =Data!L49 -> 0.0099
A50: =Data!A50 -> 1967-01 | B50: =Data!K50 -> 0.0852 | C50: =Data!B50 -> 0.1446 | D50: =(B50-C50)*Inputs!B2 -> -0.0297 | E50: =4*Inputs!B2*Inputs!B4*Inputs!B3/10000 -> 0.001 | F50: =Inputs!B2*Inputs!B5/Inputs!B6 -> 0.00083333333 | G50: =D50-E50-F50 -> -0.031533333 | H50: =(1+G50)*H49 -> 1.2850456 | I50: =MAX(1,H$2:H50) -> 1.3806529 | J50: =H50/I50-1 -> -0.069247892 | K50: =Data!L50 -> -0.0694
A51: =Data!A51 -> 1967-02 | B51: =Data!K51 -> 0.0529 | C51: =Data!B51 -> 0.0031 | D51: =(B51-C51)*Inputs!B2 -> 0.0249 | E51: =4*Inputs!B2*Inputs!B4*Inputs!B3/10000 -> 0.001 | F51: =Inputs!B2*Inputs!B5/Inputs!B6 -> 0.00083333333 | G51: =D51-E51-F51 -> 0.023066667 | H51: =(1+G51)*H50 -> 1.3146873 | I51: =MAX(1,H$2:H51) -> 1.3806529 | J51: =H51/I51-1 -> -0.047778543 | K51: =Data!L51 -> 0.0351
A52: =Data!A52 -> 1967-03 | B52: =Data!K52 -> 0.0639 | C52: =Data!B52 -> 0.0248 | D52: =(B52-C52)*Inputs!B2 -> 0.01955 | E52: =4*Inputs!B2*Inputs!B4*Inputs!B3/10000 -> 0.001 | F52: =Inputs!B2*Inputs!B5/Inputs!B6 -> 0.00083333333 | G52: =D52-E52-F52 -> 0.017716667 | H52: =(1+G52)*H51 -> 1.3379792 | I52: =MAX(1,H$2:H52) -> 1.3806529 | J52: =H52/I52-1 -> -0.030908353 | K52: =Data!L52 -> 0.0139
A53: =Data!A53 -> 1967-04 | B53: =Data!K53 -> 0.0631 | C53: =Data!B53 -> 0.0682 | D53: =(B53-C53)*Inputs!B2 -> -0.00255 | E53: =4*Inputs!B2*Inputs!B4*Inputs!B3/10000 -> 0.001 | F53: =Inputs!B2*Inputs!B5/Inputs!B6 -> 0.00083333333 | G53: =D53-E53-F53 -> -0.0043833333 | H53: =(1+G53)*H52 -> 1.3321144 | I53: =MAX(1,H$2:H53) -> 1.3806529 | J53: =H53/I53-1 -> -0.035156205 | K53: =Data!L53 -> 0.0052
A54: =Data!A54 -> 1967-05 | B54: =Data!K54 -> -0.0336 | C54: =Data!B54 -> -0.0702 | D54: =(B54-C54)*Inputs!B2 -> 0.0183 | E54: =4*Inputs!B2*Inputs!B4*Inputs!B3/10000 -> 0.001 | F54: =Inputs!B2*Inputs!B5/Inputs!B6 -> 0.00083333333 | G54: =D54-E54-F54 -> 0.016466667 | H54: =(1+G54)*H53 -> 1.3540498 | I54: =MAX(1,H$2:H54) -> 1.3806529 | J54: =H54/I54-1 -> -0.019268444 | K54: =Data!L54 -> 0.0065
A55: =Data!A55 -> 1967-06 | B55: =Data!K55 -> 0.0846 | C55: =Data!B55 -> 0.0258 | D55: =(B55-C55)*Inputs!B2 -> 0.0294 | E55: =4*Inputs!B2*Inputs!B4*Inputs!B3/10000 -> 0.001 | F55: =Inputs!B2*Inputs!B5/Inputs!B6 -> 0.00083333333 | G55: =D55-E55-F55 -> 0.027566667 | H55: =(1+G55)*H54 -> 1.3913765 | I55: =MAX(1,H$2:H55) -> 1.3913765 | J55: =H55/I55-1 -> 0 | K55: =Data!L55 -> 0.0601
A56: =Data!A56 -> 1967-07 | B56: =Data!K56 -> 0.0725 | C56: =Data!B56 -> 0.1006 | D56: =(B56-C56)*Inputs!B2 -> -0.01405 | E56: =4*Inputs!B2*Inputs!B4*Inputs!B3/10000 -> 0.001 | F56: =Inputs!B2*Inputs!B5/Inputs!B6 -> 0.00083333333 | G56: =D56-E56-F56 -> -0.015883333 | H56: =(1+G56)*H55 -> 1.3692768 | I56: =MAX(1,H$2:H56) -> 1.3913765 | J56: =H56/I56-1 -> -0.015883333 | K56: =Data!L56 -> -0.0108
A57: =Data!A57 -> 1967-08 | B57: =Data!K57 -> -0.0174 | C57: =Data!B57 -> -0.0061 | D57: =(B57-C57)*Inputs!B2 -> -0.00565 | E57: =4*Inputs!B2*Inputs!B4*Inputs!B3/10000 -> 0.001 | F57: =Inputs!B2*Inputs!B5/Inputs!B6 -> 0.00083333333 | G57: =D57-E57-F57 -> -0.0074833333 | H57: =(1+G57)*H56 -> 1.35903 | I57: =MAX(1,H$2:H57) -> 1.3913765 | J57: =H57/I57-1 -> -0.023247806 | K57: =Data!L57 -> -0.0133
A58: =Data!A58 -> 1967-09 | B58: =Data!K58 -> 0.0448 | C58: =Data!B58 -> 0.0436 | D58: =(B58-C58)*Inputs!B2 -> 0.0006 | E58: =4*Inputs!B2*Inputs!B4*Inputs!B3/10000 -> 0.001 | F58: =Inputs!B2*Inputs!B5/Inputs!B6 -> 0.00083333333 | G58: =D58-E58-F58 -> -0.0012333333 | H58: =(1+G58)*H57 -> 1.3573539 | I58: =MAX(1,H$2:H58) -> 1.3913765 | J58: =H58/I58-1 -> -0.024452467 | K58: =Data!L58 -> 0.0239
A59: =Data!A59 -> 1967-10 | B59: =Data!K59 -> 0.0071 | C59: =Data!B59 -> -0.0401 | D59: =(B59-C59)*Inputs!B2 -> 0.0236 | E59: =4*Inputs!B2*Inputs!B4*Inputs!B3/10000 -> 0.001 | F59: =Inputs!B2*Inputs!B5/Inputs!B6 -> 0.00083333333 | G59: =D59-E59-F59 -> 0.021766667 | H59: =(1+G59)*H58 -> 1.386899 | I59: =MAX(1,H$2:H59) -> 1.3913765 | J59: =H59/I59-1 -> -0.0032180495 | K59: =Data!L59 -> 0.0364
A60: =Data!A60 -> 1967-11 | B60: =Data!K60 -> 0.0112 | C60: =Data!B60 -> 0.0137 | D60: =(B60-C60)*Inputs!B2 -> -0.00125 | E60: =4*Inputs!B2*Inputs!B4*Inputs!B3/10000 -> 0.001 | F60: =Inputs!B2*Inputs!B5/Inputs!B6 -> 0.00083333333 | G60: =D60-E60-F60 -> -0.0030833333 | H60: =(1+G60)*H59 -> 1.3826227 | I60: =MAX(1,H$2:H60) -> 1.3913765 | J60: =H60/I60-1 -> -0.0062914605 | K60: =Data!L60 -> 0.0122
A61: =Data!A61 -> 1967-12 | B61: =Data!K61 -> 0.0901 | C61: =Data!B61 -> 0.0237 | D61: =(B61-C61)*Inputs!B2 -> 0.0332 | E61: =4*Inputs!B2*Inputs!B4*Inputs!B3/10000 -> 0.001 | F61: =Inputs!B2*Inputs!B5/Inputs!B6 -> 0.00083333333 | G61: =D61-E61-F61 -> 0.031366667 | H61: =(1+G61)*H60 -> 1.425991 | I61: =MAX(1,H$2:H61) -> 1.425991 | J61: =H61/I61-1 -> 0 | K61: =Data!L61 -> 0.0321
A62: =Data!A62 -> 1968-01 | B62: =Data!K62 -> -0.0694 | C62: =Data!B62 -> 0.0018 | D62: =(B62-C62)*Inputs!B2 -> -0.0356 | E62: =4*Inputs!B2*Inputs!B4*Inputs!B3/10000 -> 0.001 | F62: =Inputs!B2*Inputs!B5/Inputs!B6 -> 0.00083333333 | G62: =D62-E62-F62 -> -0.037433333 | H62: =(1+G62)*H61 -> 1.3726114 | I62: =MAX(1,H$2:H62) -> 1.425991 | J62: =H62/I62-1 -> -0.037433333 | K62: =Data!L62 -> -0.0449
A63: =Data!A63 -> 1968-02 | B63: =Data!K63 -> -0.0895 | C63: =Data!B63 -> -0.036 | D63: =(B63-C63)*Inputs!B2 -> -0.02675 | E63: =4*Inputs!B2*Inputs!B4*Inputs!B3/10000 -> 0.001 | F63: =Inputs!B2*Inputs!B5/Inputs!B6 -> 0.00083333333 | G63: =D63-E63-F63 -> -0.028583333 | H63: =(1+G63)*H62 -> 1.3333775 | I63: =MAX(1,H$2:H63) -> 1.425991 | J63: =H63/I63-1 -> -0.064946697 | K63: =Data!L63 -> -0.0336
A64: =Data!A64 -> 1968-03 | B64: =Data!K64 -> 0.0256 | C64: =Data!B64 -> -0.0185 | D64: =(B64-C64)*Inputs!B2 -> 0.02205 | E64: =4*Inputs!B2*Inputs!B4*Inputs!B3/10000 -> 0.001 | F64: =Inputs!B2*Inputs!B5/Inputs!B6 -> 0.00083333333 | G64: =D64-E64-F64 -> 0.020216667 | H64: =(1+G64)*H63 -> 1.360334 | I64: =MAX(1,H$2:H64) -> 1.425991 | J64: =H64/I64-1 -> -0.046043036 | K64: =Data!L64 -> 0.0319
A65: =Data!A65 -> 1968-04 | B65: =Data!K65 -> 0.1922 | C65: =Data!B65 -> 0.1094 | D65: =(B65-C65)*Inputs!B2 -> 0.0414 | E65: =4*Inputs!B2*Inputs!B4*Inputs!B3/10000 -> 0.001 | F65: =Inputs!B2*Inputs!B5/Inputs!B6 -> 0.00083333333 | G65: =D65-E65-F65 -> 0.039566667 | H65: =(1+G65)*H64 -> 1.4141579 | I65: =MAX(1,H$2:H65) -> 1.425991 | J65: =H65/I65-1 -> -0.0082981391 | K65: =Data!L65 -> 0.0513
A66: =Data!A66 -> 1968-05 | B66: =Data!K66 -> 0.1024 | C66: =Data!B66 -> 0.0157 | D66: =(B66-C66)*Inputs!B2 -> 0.04335 | E66: =4*Inputs!B2*Inputs!B4*Inputs!B3/10000 -> 0.001 | F66: =Inputs!B2*Inputs!B5/Inputs!B6 -> 0.00083333333 | G66: =D66-E66-F66 -> 0.041516667 | H66: =(1+G66)*H65 -> 1.472869 | I66: =MAX(1,H$2:H66) -> 1.472869 | J66: =H66/I66-1 -> 0 | K66: =Data!L66 -> 0.0377
A67: =Data!A67 -> 1968-06 | B67: =Data!K67 -> 0.0073 | C67: =Data!B67 -> 0.018 | D67: =(B67-C67)*Inputs!B2 -> -0.00535 | E67: =4*Inputs!B2*Inputs!B4*Inputs!B3/10000 -> 0.001 | F67: =Inputs!B2*Inputs!B5/Inputs!B6 -> 0.00083333333 | G67: =D67-E67-F67 -> -0.0071833333 | H67: =(1+G67)*H66 -> 1.4622889 | I67: =MAX(1,H$2:H67) -> 1.472869 | J67: =H67/I67-1 -> -0.0071833333 | K67: =Data!L67 -> -0.021
A68: =Data!A68 -> 1968-07 | B68: =Data!K68 -> -0.0445 | C68: =Data!B68 -> -0.0239 | D68: =(B68-C68)*Inputs!B2 -> -0.0103 | E68: =4*Inputs!B2*Inputs!B4*Inputs!B3/10000 -> 0.001 | F68: =Inputs!B2*Inputs!B5/Inputs!B6 -> 0.00083333333 | G68: =D68-E68-F68 -> -0.012133333 | H68: =(1+G68)*H67 -> 1.4445465 | I68: =MAX(1,H$2:H68) -> 1.472869 | J68: =H68/I68-1 -> -0.019229509 | K68: =Data!L68 -> -0.0088
A69: =Data!A69 -> 1968-08 | B69: =Data!K69 -> 0.0491 | C69: =Data!B69 -> 0.0086 | D69: =(B69-C69)*Inputs!B2 -> 0.02025 | E69: =4*Inputs!B2*Inputs!B4*Inputs!B3/10000 -> 0.001 | F69: =Inputs!B2*Inputs!B5/Inputs!B6 -> 0.00083333333 | G69: =D69-E69-F69 -> 0.018416667 | H69: =(1+G69)*H68 -> 1.4711502 | I69: =MAX(1,H$2:H69) -> 1.472869 | J69: =H69/I69-1 -> -0.0011669857 | K69: =Data!L69 -> 0.0193
A70: =Data!A70 -> 1968-09 | B70: =Data!K70 -> 0.0983 | C70: =Data!B70 -> 0.0685 | D70: =(B70-C70)*Inputs!B2 -> 0.0149 | E70: =4*Inputs!B2*Inputs!B4*Inputs!B3/10000 -> 0.001 | F70: =Inputs!B2*Inputs!B5/Inputs!B6 -> 0.00083333333 | G70: =D70-E70-F70 -> 0.013066667 | H70: =(1+G70)*H69 -> 1.4903732 | I70: =MAX(1,H$2:H70) -> 1.4903732 | J70: =H70/I70-1 -> 0 | K70: =Data!L70 -> -0.0068
A71: =Data!A71 -> 1968-10 | B71: =Data!K71 -> -0.0157 | C71: =Data!B71 -> 0.019 | D71: =(B71-C71)*Inputs!B2 -> -0.01735 | E71: =4*Inputs!B2*Inputs!B4*Inputs!B3/10000 -> 0.001 | F71: =Inputs!B2*Inputs!B5/Inputs!B6 -> 0.00083333333 | G71: =D71-E71-F71 -> -0.019183333 | H71: =(1+G71)*H70 -> 1.4617829 | I71: =MAX(1,H$2:H71) -> 1.4903732 | J71: =H71/I71-1 -> -0.019183333 | K71: =Data!L71 -> -0.0144
A72: =Data!A72 -> 1968-11 | B72: =Data!K72 -> 0.1004 | C72: =Data!B72 -> 0.0855 | D72: =(B72-C72)*Inputs!B2 -> 0.00745 | E72: =4*Inputs!B2*Inputs!B4*Inputs!B3/10000 -> 0.001 | F72: =Inputs!B2*Inputs!B5/Inputs!B6 -> 0.00083333333 | G72: =D72-E72-F72 -> 0.0056166667 | H72: =(1+G72)*H71 -> 1.4699932 | I72: =MAX(1,H$2:H72) -> 1.4903732 | J72: =H72/I72-1 -> -0.013674413 | K72: =Data!L72 -> 0.0179
A73: =Data!A73 -> 1968-12 | B73: =Data!K73 -> -0.0287 | C73: =Data!B73 -> -0.0495 | D73: =(B73-C73)*Inputs!B2 -> 0.0104 | E73: =4*Inputs!B2*Inputs!B4*Inputs!B3/10000 -> 0.001 | F73: =Inputs!B2*Inputs!B5/Inputs!B6 -> 0.00083333333 | G73: =D73-E73-F73 -> 0.0085666667 | H73: =(1+G73)*H72 -> 1.4825862 | I73: =MAX(1,H$2:H73) -> 1.4903732 | J73: =H73/I73-1 -> -0.0052248905 | K73: =Data!L73 -> 0.0032
A74: =Data!A74 -> 1969-01 | B74: =Data!K74 -> -0.0187 | C74: =Data!B74 -> -0.0282 | D74: =(B74-C74)*Inputs!B2 -> 0.00475 | E74: =4*Inputs!B2*Inputs!B4*Inputs!B3/10000 -> 0.001 | F74: =Inputs!B2*Inputs!B5/Inputs!B6 -> 0.00083333333 | G74: =D74-E74-F74 -> 0.0029166667 | H74: =(1+G74)*H73 -> 1.4869104 | I74: =MAX(1,H$2:H74) -> 1.4903732 | J74: =H74/I74-1 -> -0.0023234631 | K74: =Data!L74 -> -0.0013
A75: =Data!A75 -> 1969-02 | B75: =Data!K75 -> -0.1046 | C75: =Data!B75 -> -0.0788 | D75: =(B75-C75)*Inputs!B2 -> -0.0129 | E75: =4*Inputs!B2*Inputs!B4*Inputs!B3/10000 -> 0.001 | F75: =Inputs!B2*Inputs!B5/Inputs!B6 -> 0.00083333333 | G75: =D75-E75-F75 -> -0.014733333 | H75: =(1+G75)*H74 -> 1.4650032 | I75: =MAX(1,H$2:H75) -> 1.4903732 | J75: =H75/I75-1 -> -0.017022564 | K75: =Data!L75 -> -0.025
A76: =Data!A76 -> 1969-03 | B76: =Data!K76 -> 0.0569 | C76: =Data!B76 -> -0.0109 | D76: =(B76-C76)*Inputs!B2 -> 0.0339 | E76: =4*Inputs!B2*Inputs!B4*Inputs!B3/10000 -> 0.001 | F76: =Inputs!B2*Inputs!B5/Inputs!B6 -> 0.00083333333 | G76: =D76-E76-F76 -> 0.032066667 | H76: =(1+G76)*H75 -> 1.511981 | I76: =MAX(1,H$2:H76) -> 1.511981 | J76: =H76/I76-1 -> 0 | K76: =Data!L76 -> 0.0406
A77: =Data!A77 -> 1969-04 | B77: =Data!K77 -> 0.0336 | C77: =Data!B77 -> 0.0038 | D77: =(B77-C77)*Inputs!B2 -> 0.0149 | E77: =4*Inputs!B2*Inputs!B4*Inputs!B3/10000 -> 0.001 | F77: =Inputs!B2*Inputs!B5/Inputs!B6 -> 0.00083333333 | G77: =D77-E77-F77 -> 0.013066667 | H77: =(1+G77)*H76 -> 1.5317376 | I77: =MAX(1,H$2:H77) -> 1.5317376 | J77: =H77/I77-1 -> 0 | K77: =Data!L77 -> 0.011
A78: =Data!A78 -> 1969-05 | B78: =Data!K78 -> 0.0299 | C78: =Data!B78 -> -0.0274 | D78: =(B78-C78)*Inputs!B2 -> 0.02865 | E78: =4*Inputs!B2*Inputs!B4*Inputs!B3/10000 -> 0.001 | F78: =Inputs!B2*Inputs!B5/Inputs!B6 -> 0.00083333333 | G78: =D78-E78-F78 -> 0.026816667 | H78: =(1+G78)*H77 -> 1.5728137 | I78: =MAX(1,H$2:H78) -> 1.5728137 | J78: =H78/I78-1 -> 0 | K78: =Data!L78 -> 0.0177
A79: =Data!A79 -> 1969-06 | B79: =Data!K79 -> -0.1147 | C79: =Data!B79 -> -0.1188 | D79: =(B79-C79)*Inputs!B2 -> 0.00205 | E79: =4*Inputs!B2*Inputs!B4*Inputs!B3/10000 -> 0.001 | F79: =Inputs!B2*Inputs!B5/Inputs!B6 -> 0.00083333333 | G79: =D79-E79-F79 -> 0.00021666667 | H79: =(1+G79)*H78 -> 1.5731544 | I79: =MAX(1,H$2:H79) -> 1.5731544 | J79: =H79/I79-1 -> 0 | K79: =Data!L79 -> -0.023
A80: =Data!A80 -> 1969-07 | B80: =Data!K80 -> -0.069 | C80: =Data!B80 -> -0.1233 | D80: =(B80-C80)*Inputs!B2 -> 0.02715 | E80: =4*Inputs!B2*Inputs!B4*Inputs!B3/10000 -> 0.001 | F80: =Inputs!B2*Inputs!B5/Inputs!B6 -> 0.00083333333 | G80: =D80-E80-F80 -> 0.025316667 | H80: =(1+G80)*H79 -> 1.6129815 | I80: =MAX(1,H$2:H80) -> 1.6129815 | J80: =H80/I80-1 -> 0 | K80: =Data!L80 -> 0.0181
A81: =Data!A81 -> 1969-08 | B81: =Data!K81 -> 0.1045 | C81: =Data!B81 -> 0.0641 | D81: =(B81-C81)*Inputs!B2 -> 0.0202 | E81: =4*Inputs!B2*Inputs!B4*Inputs!B3/10000 -> 0.001 | F81: =Inputs!B2*Inputs!B5/Inputs!B6 -> 0.00083333333 | G81: =D81-E81-F81 -> 0.018366667 | H81: =(1+G81)*H80 -> 1.6426066 | I81: =MAX(1,H$2:H81) -> 1.6426066 | J81: =H81/I81-1 -> 0 | K81: =Data!L81 -> 0.021
A82: =Data!A82 -> 1969-09 | B82: =Data!K82 -> -0.0266 | C82: =Data!B82 -> -0.0441 | D82: =(B82-C82)*Inputs!B2 -> 0.00875 | E82: =4*Inputs!B2*Inputs!B4*Inputs!B3/10000 -> 0.001 | F82: =Inputs!B2*Inputs!B5/Inputs!B6 -> 0.00083333333 | G82: =D82-E82-F82 -> 0.0069166667 | H82: =(1+G82)*H81 -> 1.6539679 | I82: =MAX(1,H$2:H82) -> 1.6539679 | J82: =H82/I82-1 -> 0 | K82: =Data!L82 -> 0.0241
A83: =Data!A83 -> 1969-10 | B83: =Data!K83 -> 0.0665 | C83: =Data!B83 -> 0.1071 | D83: =(B83-C83)*Inputs!B2 -> -0.0203 | E83: =4*Inputs!B2*Inputs!B4*Inputs!B3/10000 -> 0.001 | F83: =Inputs!B2*Inputs!B5/Inputs!B6 -> 0.00083333333 | G83: =D83-E83-F83 -> -0.022133333 | H83: =(1+G83)*H82 -> 1.6173601 | I83: =MAX(1,H$2:H83) -> 1.6539679 | J83: =H83/I83-1 -> -0.022133333 | K83: =Data!L83 -> -0.0436
A84: =Data!A84 -> 1969-11 | B84: =Data!K84 -> -0.0053 | C84: =Data!B84 -> -0.069 | D84: =(B84-C84)*Inputs!B2 -> 0.03185 | E84: =4*Inputs!B2*Inputs!B4*Inputs!B3/10000 -> 0.001 | F84: =Inputs!B2*Inputs!B5/Inputs!B6 -> 0.00083333333 | G84: =D84-E84-F84 -> 0.030016667 | H84: =(1+G84)*H83 -> 1.6659079 | I84: =MAX(1,H$2:H84) -> 1.6659079 | J84: =H84/I84-1 -> 0 | K84: =Data!L84 -> 0.0368
A85: =Data!A85 -> 1969-12 | B85: =Data!K85 -> 0.0137 | C85: =Data!B85 -> -0.082 | D85: =(B85-C85)*Inputs!B2 -> 0.04785 | E85: =4*Inputs!B2*Inputs!B4*Inputs!B3/10000 -> 0.001 | F85: =Inputs!B2*Inputs!B5/Inputs!B6 -> 0.00083333333 | G85: =D85-E85-F85 -> 0.046016667 | H85: =(1+G85)*H84 -> 1.7425674 | I85: =MAX(1,H$2:H85) -> 1.7425674 | J85: =H85/I85-1 -> 0 | K85: =Data!L85 -> 0.0527
A86: =Data!A86 -> 1970-01 | B86: =Data!K86 -> -0.0705 | C86: =Data!B86 -> -0.0649 | D86: =(B86-C86)*Inputs!B2 -> -0.0028 | E86: =4*Inputs!B2*Inputs!B4*Inputs!B3/10000 -> 0.001 | F86: =Inputs!B2*Inputs!B5/Inputs!B6 -> 0.00083333333 | G86: =D86-E86-F86 -> -0.0046333333 | H86: =(1+G86)*H85 -> 1.7344935 | I86: =MAX(1,H$2:H86) -> 1.7425674 | J86: =H86/I86-1 -> -0.0046333333 | K86: =Data!L86 -> 0.0056
A87: =Data!A87 -> 1970-02 | B87: =Data!K87 -> 0.0318 | C87: =Data!B87 -> 0.0353 | D87: =(B87-C87)*Inputs!B2 -> -0.00175 | E87: =4*Inputs!B2*Inputs!B4*Inputs!B3/10000 -> 0.001 | F87: =Inputs!B2*Inputs!B5/Inputs!B6 -> 0.00083333333 | G87: =D87-E87-F87 -> -0.0035833333 | H87: =(1+G87)*H86 -> 1.7282782 | I87: =MAX(1,H$2:H87) -> 1.7425674 | J87: =H87/I87-1 -> -0.0082000639 | K87: =Data!L87 -> 0.0027
A88: =Data!A88 -> 1970-03 | B88: =Data!K88 -> -0.0296 | C88: =Data!B88 -> -0.0387 | D88: =(B88-C88)*Inputs!B2 -> 0.00455 | E88: =4*Inputs!B2*Inputs!B4*Inputs!B3/10000 -> 0.001 | F88: =Inputs!B2*Inputs!B5/Inputs!B6 -> 0.00083333333 | G88: =D88-E88-F88 -> 0.0027166667 | H88: =(1+G88)*H87 -> 1.7329734 | I88: =MAX(1,H$2:H88) -> 1.7425674 | J88: =H88/I88-1 -> -0.0055056741 | K88: =Data!L88 -> -0.0037
A89: =Data!A89 -> 1970-04 | B89: =Data!K89 -> -0.1146 | C89: =Data!B89 -> -0.1738 | D89: =(B89-C89)*Inputs!B2 -> 0.0296 | E89: =4*Inputs!B2*Inputs!B4*Inputs!B3/10000 -> 0.001 | F89: =Inputs!B2*Inputs!B5/Inputs!B6 -> 0.00083333333 | G89: =D89-E89-F89 -> 0.027766667 | H89: =(1+G89)*H88 -> 1.7810923 | I89: =MAX(1,H$2:H89) -> 1.7810923 | J89: =H89/I89-1 -> 0 | K89: =Data!L89 -> -0.0083
A90: =Data!A90 -> 1970-05 | B90: =Data!K90 -> -0.062 | C90: =Data!B90 -> -0.0964 | D90: =(B90-C90)*Inputs!B2 -> 0.0172 | E90: =4*Inputs!B2*Inputs!B4*Inputs!B3/10000 -> 0.001 | F90: =Inputs!B2*Inputs!B5/Inputs!B6 -> 0.00083333333 | G90: =D90-E90-F90 -> 0.015366667 | H90: =(1+G90)*H89 -> 1.8084617 | I90: =MAX(1,H$2:H90) -> 1.8084617 | J90: =H90/I90-1 -> 0 | K90: =Data!L90 -> -0.0266
A91: =Data!A91 -> 1970-06 | B91: =Data!K91 -> -0.0093 | C91: =Data!B91 -> -0.1146 | D91: =(B91-C91)*Inputs!B2 -> 0.05265 | E91: =4*Inputs!B2*Inputs!B4*Inputs!B3/10000 -> 0.001 | F91: =Inputs!B2*Inputs!B5/Inputs!B6 -> 0.00083333333 | G91: =D91-E91-F91 -> 0.050816667 | H91: =(1+G91)*H90 -> 1.9003617 | I91: =MAX(1,H$2:H91) -> 1.9003617 | J91: =H91/I91-1 -> 0 | K91: =Data!L91 -> 0.0563
A92: =Data!A92 -> 1970-07 | B92: =Data!K92 -> 0.0443 | C92: =Data!B92 -> 0.047 | D92: =(B92-C92)*Inputs!B2 -> -0.00135 | E92: =4*Inputs!B2*Inputs!B4*Inputs!B3/10000 -> 0.001 | F92: =Inputs!B2*Inputs!B5/Inputs!B6 -> 0.00083333333 | G92: =D92-E92-F92 -> -0.0031833333 | H92: =(1+G92)*H91 -> 1.8943122 | I92: =MAX(1,H$2:H92) -> 1.9003617 | J92: =H92/I92-1 -> -0.0031833333 | K92: =Data!L92 -> -0.0311
A93: =Data!A93 -> 1970-08 | B93: =Data!K93 -> 0.0201 | C93: =Data!B93 -> 0.1296 | D93: =(B93-C93)*Inputs!B2 -> -0.05475 | E93: =4*Inputs!B2*Inputs!B4*Inputs!B3/10000 -> 0.001 | F93: =Inputs!B2*Inputs!B5/Inputs!B6 -> 0.00083333333 | G93: =D93-E93-F93 -> -0.056583333 | H93: =(1+G93)*H92 -> 1.7871257 | I93: =MAX(1,H$2:H93) -> 1.9003617 | J93: =H93/I93-1 -> -0.059586543 | K93: =Data!L93 -> -0.0673
A94: =Data!A94 -> 1970-09 | B94: =Data!K94 -> 0.0414 | C94: =Data!B94 -> 0.2269 | D94: =(B94-C94)*Inputs!B2 -> -0.09275 | E94: =4*Inputs!B2*Inputs!B4*Inputs!B3/10000 -> 0.001 | F94: =Inputs!B2*Inputs!B5/Inputs!B6 -> 0.00083333333 | G94: =D94-E94-F94 -> -0.094583333 | H94: =(1+G94)*H93 -> 1.6180934 | I94: =MAX(1,H$2:H94) -> 1.9003617 | J94: =H94/I94-1 -> -0.14853398 | K94: =Data!L94 -> -0.0864
A95: =Data!A95 -> 1970-10 | B95: =Data!K95 -> -0.0128 | C95: =Data!B95 -> -0.1451 | D95: =(B95-C95)*Inputs!B2 -> 0.06615 | E95: =4*Inputs!B2*Inputs!B4*Inputs!B3/10000 -> 0.001 | F95: =Inputs!B2*Inputs!B5/Inputs!B6 -> 0.00083333333 | G95: =D95-E95-F95 -> 0.064316667 | H95: =(1+G95)*H94 -> 1.7221638 | I95: =MAX(1,H$2:H95) -> 1.9003617 | J95: =H95/I95-1 -> -0.093770527 | K95: =Data!L95 -> 0.0946
A96: =Data!A96 -> 1970-11 | B96: =Data!K96 -> 0.0566 | C96: =Data!B96 -> -0.0121 | D96: =(B96-C96)*Inputs!B2 -> 0.03435 | E96: =4*Inputs!B2*Inputs!B4*Inputs!B3/10000 -> 0.001 | F96: =Inputs!B2*Inputs!B5/Inputs!B6 -> 0.00083333333 | G96: =D96-E96-F96 -> 0.032516667 | H96: =(1+G96)*H95 -> 1.7781628 | I96: =MAX(1,H$2:H96) -> 1.9003617 | J96: =H96/I96-1 -> -0.064302965 | K96: =Data!L96 -> 0.026
A97: =Data!A97 -> 1970-12 | B97: =Data!K97 -> 0.0345 | C97: =Data!B97 -> 0.0589 | D97: =(B97-C97)*Inputs!B2 -> -0.0122 | E97: =4*Inputs!B2*Inputs!B4*Inputs!B3/10000 -> 0.001 | F97: =Inputs!B2*Inputs!B5/Inputs!B6 -> 0.00083333333 | G97: =D97-E97-F97 -> -0.014033333 | H97: =(1+G97)*H96 -> 1.7532093 | I97: =MAX(1,H$2:H97) -> 1.9003617 | J97: =H97/I97-1 -> -0.077433913 | K97: =Data!L97 -> -0.0229
A98: =Data!A98 -> 1971-01 | B98: =Data!K98 -> 0.0207 | C98: =Data!B98 -> 0.1369 | D98: =(B98-C98)*Inputs!B2 -> -0.0581 | E98: =4*Inputs!B2*Inputs!B4*Inputs!B3/10000 -> 0.001 | F98: =Inputs!B2*Inputs!B5/Inputs!B6 -> 0.00083333333 | G98: =D98-E98-F98 -> -0.059933333 | H98: =(1+G98)*H97 -> 1.6481336 | I98: =MAX(1,H$2:H98) -> 1.9003617 | J98: =H98/I98-1 -> -0.13272637 | K98: =Data!L98 -> -0.0685
A99: =Data!A99 -> 1971-02 | B99: =Data!K99 -> 0.04 | C99: =Data!B99 -> 0.0452 | D99: =(B99-C99)*Inputs!B2 -> -0.0026 | E99: =4*Inputs!B2*Inputs!B4*Inputs!B3/10000 -> 0.001 | F99: =Inputs!B2*Inputs!B5/Inputs!B6 -> 0.00083333333 | G99: =D99-E99-F99 -> -0.0044333333 | H99: =(1+G99)*H98 -> 1.6408269 | I99: =MAX(1,H$2:H99) -> 1.9003617 | J99: =H99/I99-1 -> -0.13657129 | K99: =Data!L99 -> 0.0083
A100: =Data!A100 -> 1971-03 | B100: =Data!K100 -> 0.0521 | C100: =Data!B100 -> 0.0797 | D100: =(B100-C100)*Inputs!B2 -> -0.0138 | E100: =4*Inputs!B2*Inputs!B4*Inputs!B3/10000 -> 0.001 | F100: =Inputs!B2*Inputs!B5/Inputs!B6 -> 0.00083333333 | G100: =D100-E100-F100 -> -0.015633333 | H100: =(1+G100)*H99 -> 1.6151753 | I100: =MAX(1,H$2:H100) -> 1.9003617 | J100: =H100/I100-1 -> -0.15006956 | K100: =Data!L100 -> -0.0136
...

Sheet Performance
A1: Sample | B1: N months | C1: Net Sharpe | D1: Annual net mean | E1: Annual net vol | F1: Net CAGR | G1: Execution drag | H1: Borrow drag | I1: Gross vs Mom corr | J1: Worst monthly DD
A2: Design | B2: 444 | C2: =AVERAGE(Backtest!G2:G445)/STDEV(Backtest!G2:G445)*SQRT(Inputs!B6) -> 0.83808784 | D2: =AVERAGE(Backtest!G2:G445)*Inputs!B6 -> 0.079252703 | E2: =STDEV(Backtest!G2:G445)*SQRT(Inputs!B6) -> 0.094563719 | F2: =(Backtest!H445/1)^(Inputs!B6/B2)-1 -> 0.077376177 | G2: =AVERAGE(Backtest!E2:E445)*Inputs!B6 -> 0.012 | H2: =AVERAGE(Backtest!F2:F445)*Inputs!B6 -> 0.01 | I2: =CORREL(Backtest!D2:D445,Backtest!K2:K445) -> 0.91626799 | J2: =MIN(Backtest!J2:J445) -> -0.16675288
A3: Evaluation | B3: 321 | C3: =AVERAGE(Backtest!G446:G766)/STDEV(Backtest!G446:G766)*SQRT(Inputs!B6) -> 0.050320175 | D3: =AVERAGE(Backtest!G446:G766)*Inputs!B6 -> 0.0081102804 | E3: =STDEV(Backtest!G446:G766)*SQRT(Inputs!B6) -> 0.16117353 | F3: =(Backtest!H766/Backtest!H445)^(Inputs!B6/B3)-1 -> -0.0053820776 | G3: =AVERAGE(Backtest!E446:E766)*Inputs!B6 -> 0.012 | H3: =AVERAGE(Backtest!F446:F766)*Inputs!B6 -> 0.01 | I3: =CORREL(Backtest!D446:D766,Backtest!K446:K766) -> 0.8908437 | J3: =MIN(Backtest!J446:J766) -> -0.57599944
A4: Full | B4: 765 | C4: =AVERAGE(Backtest!G2:G766)/STDEV(Backtest!G2:G766)*SQRT(Inputs!B6) -> 0.38850881 | D4: =AVERAGE(Backtest!G2:G766)*Inputs!B6 -> 0.049400784 | E4: =STDEV(Backtest!G2:G766)*SQRT(Inputs!B6) -> 0.12715486 | F4: =(Backtest!H766/1)^(Inputs!B6/B4)-1 -> 0.041843109 | G4: =AVERAGE(Backtest!E2:E766)*Inputs!B6 -> 0.012 | H4: =AVERAGE(Backtest!F2:F766)*Inputs!B6 -> 0.01 | I4: =CORREL(Backtest!D2:D766,Backtest!K2:K766) -> 0.89892291 | J4: =MIN(Backtest!J2:J766) -> -0.57599944

Sheet Walk forward
A1: Year | B1: Training end | C1: Train months | D1: Train Sharpe | E1: Train ann vol | F1: Test months | G1: Test return | H1: Test ann vol
A2: 2000 | B2: 1999-12 | C2: 444 | D2: =AVERAGE(Backtest!G2:G445)/STDEV(Backtest!G2:G445)*SQRT(Inputs!B6) -> 0.83808784 | E2: =STDEV(Backtest!G2:G445)*SQRT(Inputs!B6) -> 0.094563719 | F2: 12 | G2: =Backtest!H457/Backtest!H445-1 -> 0.19284813 | H2: =STDEV(Backtest!G446:G457)*SQRT(Inputs!B6) -> 0.19749854
A3: 2001 | B3: 2000-12 | C3: 456 | D3: =AVERAGE(Backtest!G2:G457)/STDEV(Backtest!G2:G457)*SQRT(Inputs!B6) -> 0.83654824 | E3: =STDEV(Backtest!G2:G457)*SQRT(Inputs!B6) -> 0.098377313 | F3: 12 | G3: =Backtest!H469/Backtest!H457-1 -> -0.085126174 | H3: =STDEV(Backtest!G458:G469)*SQRT(Inputs!B6) -> 0.29420649
A4: 2002 | B4: 2001-12 | C4: 468 | D4: =AVERAGE(Backtest!G2:G469)/STDEV(Backtest!G2:G469)*SQRT(Inputs!B6) -> 0.73677045 | E4: =STDEV(Backtest!G2:G469)*SQRT(Inputs!B6) -> 0.10724907 | F4: 12 | G4: =Backtest!H481/Backtest!H469-1 -> 0.096909494 | H4: =STDEV(Backtest!G470:G481)*SQRT(Inputs!B6) -> 0.20766334
A5: 2003 | B5: 2002-12 | C5: 480 | D5: =AVERAGE(Backtest!G2:G481)/STDEV(Backtest!G2:G481)*SQRT(Inputs!B6) -> 0.72287152 | E5: =STDEV(Backtest!G2:G481)*SQRT(Inputs!B6) -> 0.11048471 | F5: 12 | G5: =Backtest!H493/Backtest!H481-1 -> -0.15271849 | H5: =STDEV(Backtest!G482:G493)*SQRT(Inputs!B6) -> 0.12362887
A6: 2004 | B6: 2003-12 | C6: 492 | D6: =AVERAGE(Backtest!G2:G493)/STDEV(Backtest!G2:G493)*SQRT(Inputs!B6) -> 0.66626363 | E6: =STDEV(Backtest!G2:G493)*SQRT(Inputs!B6) -> 0.11118795 | F6: 12 | G6: =Backtest!H505/Backtest!H493-1 -> -0.081441606 | H6: =STDEV(Backtest!G494:G505)*SQRT(Inputs!B6) -> 0.079043456
A7: 2005 | B7: 2004-12 | C7: 504 | D7: =AVERAGE(Backtest!G2:G505)/STDEV(Backtest!G2:G505)*SQRT(Inputs!B6) -> 0.63575955 | E7: =STDEV(Backtest!G2:G505)*SQRT(Inputs!B6) -> 0.11068687 | F7: 12 | G7: =Backtest!H517/Backtest!H505-1 -> 0.070616114 | H7: =STDEV(Backtest!G506:G517)*SQRT(Inputs!B6) -> 0.047358409
A8: 2006 | B8: 2005-12 | C8: 516 | D8: =AVERAGE(Backtest!G2:G517)/STDEV(Backtest!G2:G517)*SQRT(Inputs!B6) -> 0.64181935 | E8: =STDEV(Backtest!G2:G517)*SQRT(Inputs!B6) -> 0.10960847 | F8: 12 | G8: =Backtest!H529/Backtest!H517-1 -> -0.093927998 | H8: =STDEV(Backtest!G518:G529)*SQRT(Inputs!B6) -> 0.063541416
A9: 2007 | B9: 2006-12 | C9: 528 | D9: =AVERAGE(Backtest!G2:G529)/STDEV(Backtest!G2:G529)*SQRT(Inputs!B6) -> 0.61076617 | E9: =STDEV(Backtest!G2:G529)*SQRT(Inputs!B6) -> 0.10897825 | F9: 12 | G9: =Backtest!H541/Backtest!H529-1 -> 0.20731266 | H9: =STDEV(Backtest!G530:G541)*SQRT(Inputs!B6) -> 0.071794251
A10: 2008 | B10: 2007-12 | C10: 540 | D10: =AVERAGE(Backtest!G2:G541)/STDEV(Backtest!G2:G541)*SQRT(Inputs!B6) -> 0.63991354 | E10: =STDEV(Backtest!G2:G541)*SQRT(Inputs!B6) -> 0.10837749 | F10: 12 | G10: =Backtest!H553/Backtest!H541-1 -> 0.27891802 | H10: =STDEV(Backtest!G542:G553)*SQRT(Inputs!B6) -> 0.18582529
A11: 2009 | B11: 2008-12 | C11: 552 | D11: =AVERAGE(Backtest!G2:G553)/STDEV(Backtest!G2:G553)*SQRT(Inputs!B6) -> 0.66500918 | E11: =STDEV(Backtest!G2:G553)*SQRT(Inputs!B6) -> 0.11066536 | F11: 12 | G11: =Backtest!H565/Backtest!H553-1 -> -0.44978664 | H11: =STDEV(Backtest!G554:G565)*SQRT(Inputs!B6) -> 0.35053769
A12: 2010 | B12: 2009-12 | C12: 564 | D12: =AVERAGE(Backtest!G2:G565)/STDEV(Backtest!G2:G565)*SQRT(Inputs!B6) -> 0.49754318 | E12: =STDEV(Backtest!G2:G565)*SQRT(Inputs!B6) -> 0.12248055 | F12: 12 | G12: =Backtest!H577/Backtest!H565-1 -> 0.0045878942 | H12: =STDEV(Backtest!G566:G577)*SQRT(Inputs!B6) -> 0.099366469
A13: 2011 | B13: 2010-12 | C13: 576 | D13: =AVERAGE(Backtest!G2:G577)/STDEV(Backtest!G2:G577)*SQRT(Inputs!B6) -> 0.49069434 | E13: =STDEV(Backtest!G2:G577)*SQRT(Inputs!B6) -> 0.12199125 | F13: 12 | G13: =Backtest!H589/Backtest!H577-1 -> 0.10237098 | H13: =STDEV(Backtest!G578:G589)*SQRT(Inputs!B6) -> 0.058950848
A14: 2012 | B14: 2011-12 | C14: 588 | D14: =AVERAGE(Backtest!G2:G589)/STDEV(Backtest!G2:G589)*SQRT(Inputs!B6) -> 0.50131656 | E14: =STDEV(Backtest!G2:G589)*SQRT(Inputs!B6) -> 0.12101808 | F14: 12 | G14: =Backtest!H601/Backtest!H589-1 -> -0.028089139 | H14: =STDEV(Backtest!G590:G601)*SQRT(Inputs!B6) -> 0.10763125
A15: 2013 | B15: 2012-12 | C15: 600 | D15: =AVERAGE(Backtest!G2:G601)/STDEV(Backtest!G2:G601)*SQRT(Inputs!B6) -> 0.48864506 | E15: =STDEV(Backtest!G2:G601)*SQRT(Inputs!B6) -> 0.1207318 | F15: 12 | G15: =Backtest!H613/Backtest!H601-1 -> -0.028861351 | H15: =STDEV(Backtest!G602:G613)*SQRT(Inputs!B6) -> 0.053278383
A16: 2014 | B16: 2013-12 | C16: 612 | D16: =AVERAGE(Backtest!G2:G613)/STDEV(Backtest!G2:G613)*SQRT(Inputs!B6) -> 0.47819722 | E16: =STDEV(Backtest!G2:G613)*SQRT(Inputs!B6) -> 0.11980454 | F16: 12 | G16: =Backtest!H625/Backtest!H613-1 -> 0.0089735944 | H16: =STDEV(Backtest!G614:G625)*SQRT(Inputs!B6) -> 0.065130631
A17: 2015 | B17: 2014-12 | C17: 624 | D17: =AVERAGE(Backtest!G2:G625)/STDEV(Backtest!G2:G625)*SQRT(Inputs!B6) -> 0.4740347 | E17: =STDEV(Backtest!G2:G625)*SQRT(Inputs!B6) -> 0.11897457 | F17: 12 | G17: =Backtest!H637/Backtest!H625-1 -> 0.20845712 | H17: =STDEV(Backtest!G626:G637)*SQRT(Inputs!B6) -> 0.15985247
A18: 2016 | B18: 2015-12 | C18: 636 | D18: =AVERAGE(Backtest!G2:G637)/STDEV(Backtest!G2:G637)*SQRT(Inputs!B6) -> 0.49357413 | E18: =STDEV(Backtest!G2:G637)*SQRT(Inputs!B6) -> 0.11984589 | F18: 12 | G18: =Backtest!H649/Backtest!H637-1 -> -0.1530841 | H18: =STDEV(Backtest!G638:G649)*SQRT(Inputs!B6) -> 0.12218434
A19: 2017 | B19: 2016-12 | C19: 648 | D19: =AVERAGE(Backtest!G2:G649)/STDEV(Backtest!G2:G649)*SQRT(Inputs!B6) -> 0.45909503 | E19: =STDEV(Backtest!G2:G649)*SQRT(Inputs!B6) -> 0.12009133 | F19: 12 | G19: =Backtest!H661/Backtest!H649-1 -> -0.0053397084 | H19: =STDEV(Backtest!G650:G661)*SQRT(Inputs!B6) -> 0.083076909
A20: 2018 | B20: 2017-12 | C20: 660 | D20: =AVERAGE(Backtest!G2:G661)/STDEV(Backtest!G2:G661)*SQRT(Inputs!B6) -> 0.45265683 | E20: =STDEV(Backtest!G2:G661)*SQRT(Inputs!B6) -> 0.1194965 | F20: 12 | G20: =Backtest!H673/Backtest!H661-1 -> 0.10271153 | H20: =STDEV(Backtest!G662:G673)*SQRT(Inputs!B6) -> 0.099072737
A21: 2019 | B21: 2018-12 | C21: 672 | D21: =AVERAGE(Backtest!G2:G673)/STDEV(Backtest!G2:G673)*SQRT(Inputs!B6) -> 0.46137863 | E21: =STDEV(Backtest!G2:G673)*SQRT(Inputs!B6) -> 0.11911506 | F21: 12 | G21: =Backtest!H685/Backtest!H673-1 -> -0.02946063 | H21: =STDEV(Backtest!G674:G685)*SQRT(Inputs!B6) -> 0.13059269
A22: 2020 | B22: 2019-12 | C22: 684 | D22: =AVERAGE(Backtest!G2:G685)/STDEV(Backtest!G2:G685)*SQRT(Inputs!B6) -> 0.44948466 | E22: =STDEV(Backtest!G2:G685)*SQRT(Inputs!B6) -> 0.11925743 | F22: 12 | G22: =Backtest!H697/Backtest!H685-1 -> -0.079757648 | H22: =STDEV(Backtest!G686:G697)*SQRT(Inputs!B6) -> 0.27411431
A23: 2021 | B23: 2020-12 | C23: 696 | D23: =AVERAGE(Backtest!G2:G697)/STDEV(Backtest!G2:G697)*SQRT(Inputs!B6) -> 0.42107152 | E23: =STDEV(Backtest!G2:G697)*SQRT(Inputs!B6) -> 0.12320783 | F23: 12 | G23: =Backtest!H709/Backtest!H697-1 -> -0.18847432 | H23: =STDEV(Backtest!G698:G709)*SQRT(Inputs!B6) -> 0.15119009
A24: 2022 | B24: 2021-12 | C24: 708 | D24: =AVERAGE(Backtest!G2:G709)/STDEV(Backtest!G2:G709)*SQRT(Inputs!B6) -> 0.38464761 | E24: =STDEV(Backtest!G2:G709)*SQRT(Inputs!B6) -> 0.12395012 | F24: 12 | G24: =Backtest!H721/Backtest!H709-1 -> 0.20357436 | H24: =STDEV(Backtest!G710:G721)*SQRT(Inputs!B6) -> 0.088568058
A25: 2023 | B25: 2022-12 | C25: 720 | D25: =AVERAGE(Backtest!G2:G721)/STDEV(Backtest!G2:G721)*SQRT(Inputs!B6) -> 0.40525976 | E25: =STDEV(Backtest!G2:G721)*SQRT(Inputs!B6) -> 0.12351132 | F25: 12 | G25: =Backtest!H733/Backtest!H721-1 -> -0.14062846 | H25: =STDEV(Backtest!G722:G733)*SQRT(Inputs!B6) -> 0.17563858
A26: 2024 | B26: 2023-12 | C26: 732 | D26: =AVERAGE(Backtest!G2:G733)/STDEV(Backtest!G2:G733)*SQRT(Inputs!B6) -> 0.37737224 | E26: =STDEV(Backtest!G2:G733)*SQRT(Inputs!B6) -> 0.12456067 | F26: 12 | G26: =Backtest!H745/Backtest!H733-1 -> 0.16319776 | H26: =STDEV(Backtest!G734:G745)*SQRT(Inputs!B6) -> 0.1382666
A27: 2025 | B27: 2024-12 | C27: 744 | D27: =AVERAGE(Backtest!G2:G745)/STDEV(Backtest!G2:G745)*SQRT(Inputs!B6) -> 0.3915196 | E27: =STDEV(Backtest!G2:G745)*SQRT(Inputs!B6) -> 0.12475996 | F27: 12 | G27: =Backtest!H757/Backtest!H745-1 -> -0.085222078 | H27: =STDEV(Backtest!G746:G757)*SQRT(Inputs!B6) -> 0.11239486
A28: 2026 | B28: 2025-12 | C28: 756 | D28: =AVERAGE(Backtest!G2:G757)/STDEV(Backtest!G2:G757)*SQRT(Inputs!B6) -> 0.3752423 | E28: =STDEV(Backtest!G2:G757)*SQRT(Inputs!B6) -> 0.12459674 | F28: 9 | G28: =Backtest!H766/Backtest!H757-1 -> 0.19374505 | H28: =STDEV(Backtest!G758:G766)*SQRT(Inputs!B6) -> 0.27254087

Sheet Sensitivity
A1: Turnover one-way A | B1: Execution bp A | C1: Monthly all-in drag | D1: OOS net Sharpe | E1: Annual all-in drag
A2: 0.25 | B2: 0 | C2: =4*Inputs!B2*A2*B2/10000+Inputs!B2*Inputs!B5/Inputs!B6 -> 0.00083333333 | D2: =(AVERAGE(Backtest!D446:D766)-C2)/STDEV(Backtest!D446:D766)*SQRT(Inputs!B6) -> 0.12477409 | E2: =C2*Inputs!B6 -> 0.01
A3: 0.25 | B3: 10 | C3: =4*Inputs!B2*A3*B3/10000+Inputs!B2*Inputs!B5/Inputs!B6 -> 0.0013333333 | D3: =(AVERAGE(Backtest!D446:D766)-C3)/STDEV(Backtest!D446:D766)*SQRT(Inputs!B6) -> 0.087547132 | E3: =C3*Inputs!B6 -> 0.016
A4: 0.25 | B4: 25 | C4: =4*Inputs!B2*A4*B4/10000+Inputs!B2*Inputs!B5/Inputs!B6 -> 0.0020833333 | D4: =(AVERAGE(Backtest!D446:D766)-C4)/STDEV(Backtest!D446:D766)*SQRT(Inputs!B6) -> 0.031706697 | E4: =C4*Inputs!B6 -> 0.025
A5: 0.25 | B5: 50 | C5: =4*Inputs!B2*A5*B5/10000+Inputs!B2*Inputs!B5/Inputs!B6 -> 0.0033333333 | D5: =(AVERAGE(Backtest!D446:D766)-C5)/STDEV(Backtest!D446:D766)*SQRT(Inputs!B6) -> -0.061360693 | E5: =C5*Inputs!B6 -> 0.04
A6: 0.5 | B6: 0 | C6: =4*Inputs!B2*A6*B6/10000+Inputs!B2*Inputs!B5/Inputs!B6 -> 0.00083333333 | D6: =(AVERAGE(Backtest!D446:D766)-C6)/STDEV(Backtest!D446:D766)*SQRT(Inputs!B6) -> 0.12477409 | E6: =C6*Inputs!B6 -> 0.01
A7: 0.5 | B7: 10 | C7: =4*Inputs!B2*A7*B7/10000+Inputs!B2*Inputs!B5/Inputs!B6 -> 0.0018333333 | D7: =(AVERAGE(Backtest!D446:D766)-C7)/STDEV(Backtest!D446:D766)*SQRT(Inputs!B6) -> 0.050320175 | E7: =C7*Inputs!B6 -> 0.022
A8: 0.5 | B8: 25 | C8: =4*Inputs!B2*A8*B8/10000+Inputs!B2*Inputs!B5/Inputs!B6 -> 0.0033333333 | D8: =(AVERAGE(Backtest!D446:D766)-C8)/STDEV(Backtest!D446:D766)*SQRT(Inputs!B6) -> -0.061360693 | E8: =C8*Inputs!B6 -> 0.04
A9: 0.5 | B9: 50 | C9: =4*Inputs!B2*A9*B9/10000+Inputs!B2*Inputs!B5/Inputs!B6 -> 0.0058333333 | D9: =(AVERAGE(Backtest!D446:D766)-C9)/STDEV(Backtest!D446:D766)*SQRT(Inputs!B6) -> -0.24749547 | E9: =C9*Inputs!B6 -> 0.07
A10: 1 | B10: 0 | C10: =4*Inputs!B2*A10*B10/10000+Inputs!B2*Inputs!B5/Inputs!B6 -> 0.00083333333 | D10: =(AVERAGE(Backtest!D446:D766)-C10)/STDEV(Backtest!D446:D766)*SQRT(Inputs!B6) -> 0.12477409 | E10: =C10*Inputs!B6 -> 0.01
A11: 1 | B11: 10 | C11: =4*Inputs!B2*A11*B11/10000+Inputs!B2*Inputs!B5/Inputs!B6 -> 0.0028333333 | D11: =(AVERAGE(Backtest!D446:D766)-C11)/STDEV(Backtest!D446:D766)*SQRT(Inputs!B6) -> -0.024133737 | E11: =C11*Inputs!B6 -> 0.034
A12: 1 | B12: 25 | C12: =4*Inputs!B2*A12*B12/10000+Inputs!B2*Inputs!B5/Inputs!B6 -> 0.0058333333 | D12: =(AVERAGE(Backtest!D446:D766)-C12)/STDEV(Backtest!D446:D766)*SQRT(Inputs!B6) -> -0.24749547 | E12: =C12*Inputs!B6 -> 0.07
A13: 1 | B13: 50 | C13: =4*Inputs!B2*A13*B13/10000+Inputs!B2*Inputs!B5/Inputs!B6 -> 0.010833333 | D13: =(AVERAGE(Backtest!D446:D766)-C13)/STDEV(Backtest!D446:D766)*SQRT(Inputs!B6) -> -0.61976504 | E13: =C13*Inputs!B6 -> 0.13
A14: Base-turnover execution break-even bp | B14: =(AVERAGE(Backtest!D446:D766)-Inputs!B2*Inputs!B5/12)/(4*Inputs!B2*Inputs!B4)*10000 -> 16.758567

Sheet Drawdowns
A1: Peak | B1: Trough | C1: Recovery | D1: Net drawdown D
A2: 2009-02 | B2: 2021-05 | C2: Not recovered by 2026-09 | D2: -0.57599944
A3: 2002-09 | B3: 2007-02 | C3: 2008-11 | D3: -0.34825357
A4: 2000-12 | B4: 2001-01 | C4: 2001-09 | D4: -0.21103333
A5: 1980-11 | B5: 1981-08 | C5: 1982-09 | D5: -0.16675288
A6: 1999-02 | B6: 1999-05 | C6: 1999-11 | D6: -0.16343672
A7: Worst calendar years | B7: Net return D | C7: Months
A8: 2009 | B8: -0.44978664 | C8: 12
A9: 2021 | B9: -0.18847432 | C9: 12
A10: 2016 | B10: -0.1530841 | C10: 12
A11: 2003 | B11: -0.15271849 | C11: 12
A12: 2023 | B12: -0.14062846 | C12: 12
A13: Episodes are fixed Python research output. Rerun engine if changing costs; live full-history minimum is Performance!J4.

Sheet Data
A1: Month | B1: Decile 1 | C1: Decile 2 | D1: Decile 3 | E1: Decile 4 | F1: Decile 5 | G1: Decile 6 | H1: Decile 7 | I1: Decile 8 | J1: Decile 9 | K1: Decile 10 | L1: Published Mom
A2: 1963-01 | B2: 0.0488 | C2: 0.0791 | D2: 0.0679 | E2: 0.0634 | F2: 0.0403 | G2: 0.0583 | H2: 0.0467 | I2: 0.0505 | J2: 0.0521 | K2: 0.0317 | L2: -0.0214
A3: 1963-02 | B3: -0.0377 | C3: -0.0222 | D3: -0.038 | E3: -0.0293 | F3: -0.0302 | G3: -0.0286 | H3: -0.0114 | I3: -0.0125 | J3: -0.0243 | K3: -0.0159 | L3: 0.0252
A4: 1963-03 | B4: 0.02 | C4: 0.0221 | D4: 0.0395 | E4: 0.0237 | F4: 0.0253 | G4: 0.0212 | H4: 0.0299 | I4: 0.031 | J4: 0.0441 | K4: 0.0539 | L4: 0.0158
A5: 1963-04 | B5: 0.0361 | C5: 0.0773 | D5: 0.0393 | E5: 0.0495 | F5: 0.0452 | G5: 0.0404 | H5: 0.0517 | I5: 0.0438 | J5: 0.0428 | K5: 0.0505 | L5: -0.0006
A6: 1963-05 | B6: 0.0297 | C6: 0.0231 | D6: 0.0279 | E6: 0.0149 | F6: 0.0255 | G6: 0.0044 | H6: 0.014 | I6: 0.0333 | J6: 0.0164 | K6: 0.0312 | L6: 0.0029
A7: 1963-06 | B7: -0.0174 | C7: -0.0286 | D7: -0.0292 | E7: -0.0138 | F7: -0.0192 | G7: -0.0366 | H7: -0.0237 | I7: -0.0032 | J7: -0.0067 | K7: -0.0214 | L7: 0.0116
A8: 1963-07 | B8: -0.0277 | C8: -0.0116 | D8: -0.0101 | E8: -0.0044 | F8: -0.0099 | G8: 0.0151 | H8: -0.0058 | I8: 0.0051 | J8: -0.0056 | K8: 0.0041 | L8: 0.0101
A9: 1963-08 | B9: 0.0603 | C9: 0.0463 | D9: 0.0572 | E9: 0.0461 | F9: 0.0584 | G9: 0.0503 | H9: 0.0526 | I9: 0.0397 | J9: 0.0648 | K9: 0.0922 | L9: 0.01
A10: 1963-09 | B10: -0.0308 | C10: -0.0304 | D10: -0.0125 | E10: 0.0155 | F10: -0.0173 | G10: -0.0139 | H10: -0.0068 | I10: -0.0283 | J10: -0.0266 | K10: -0.0207 | L10: 0.0012
A11: 1963-10 | B11: 0.019 | C11: 0.0161 | D11: -0.0009 | E11: 0.0179 | F11: 0.0275 | G11: 0.028 | H11: 0.01 | I11: 0.0089 | J11: 0.0815 | K11: 0.0549 | L11: 0.0313
A12: 1963-11 | B12: 0.002 | C12: -0.0136 | D12: -0.0055 | E12: 0.0195 | F12: -0.0111 | G12: -0.0102 | H12: 0.0046 | I12: -0.0417 | J12: -0.0095 | K12: -0.0018 | L12: -0.0077
A13: 1963-12 | B13: -0.0249 | C13: -0.0101 | D13: 0.0199 | E13: 0.0211 | F13: 0.0231 | G13: 0.0178 | H13: 0.0251 | I13: 0.0368 | J13: 0.0281 | K13: 0.0077 | L13: 0.0184
... A766: 2026-09 | B766: -0.0948 | C766: -0.0133 | D766: -0.0349 | E766: -0.035 | F766: -0.0599 | G766: 0.008 | H766: -0.0428 | I766: -0.0054 | J766: -0.0219 | K766: 0.0718 | L766: 0.067

Sheet Sources
A1: Source / method | B1: URL / limitation
A2: deciles | B2: https://mba.tuck.dartmouth.edu/pages/faculty/ken.french/Data_Library/det_10_port_form_pr_12_2.html
A3: library | B3: https://mba.tuck.dartmouth.edu/pages/faculty/ken.french/data_library.html
A4: factor | B4: https://mba.tuck.dartmouth.edu/pages/faculty/ken.french/Data_Library/det_mom_factor.html
A5: Frozen files | B5: momentum/data/*.zip and manifest.json retain hashes; first value-weight monthly table only
A6: Signal S | B6: Prior months -12 to -2, excluding latest month. NYSE deciles; NYSE/AMEX/NASDAQ eligible stocks.
A7: Universe limit | B7: Historical CRSP-based aggregates, not current-survivor ticker selection. Constituents and delisting handling not independently audited.
A8: Vintage limit | B8: 202609 revised history, not archival point-in-time releases. CIZ/FIZ methodology change from 2025.
A9: Costs A | B9: Execution 10bp on bought/sold notional, 50% turnover each leg; 2% annual borrow on 50% short.
A10: Return D | B10: Monthly +0.5 winner -0.5 loser minus costs; excess over cash. Dollar-neutral at monthly rebalance; beta may vary.
A11: Validation limit | B11: French Mom uses related underlying CRSP data and is not an independent validation set.
A12: Daily data limit | B12: No stock-level daily/delisted price files. Daily French momentum deciles are formed daily and are not substituted for monthly portfolios.
