Workbook

Sheet Cover
A1: Fund selection: retail family case
A2: Decision | B2: PASS institutional Class I despite lower published fee
A3: Anchor | B3: Hypothetical US-dollar family after a liquidity event
A4: Scope | B4: Two share classes of one fund, not two different managers
A5: As of | B5: 30 June 2026. Historical research snapshot, not current dealing advice
A6: Limitations | B6: No allocation made; eligibility, tax and distribution-channel access need prospectus/platform review

Sheet Selection
A1: Share-class comparison | B1: Class I | C1: Class R
A2: Net expense ratio | B2: =Inputs!B5 -> 0.0067 | C2: =Inputs!B6 -> 0.0092
A3: Gross expense ratio | B3: =Inputs!B7 -> 0.0079 | C3: =Inputs!B8 -> 0.0104
A4: Illustrative first-year fee | B4: =Inputs!B2*B2 -> 6700 | C4: =Inputs!B2*C2 -> 9200
A5: 10-year ending capital | B5: =Inputs!B2*(1+Inputs!B3-B2)^Inputs!B4 -> 1527889.9 | C5: =Inputs!B2*(1+Inputs!B3-C2)^Inputs!B4 -> 1491670.3
A6: Net fee gap, basis points | B6: =(C2-B2)*10000 -> 25
A7: Annual indicative cost difference | B7: =C4-B4 -> 2500
A8: 10-year wealth difference | B8: =B5-C5 -> 36219.673
A9: I access gate | B9: =AND(Inputs!B11,Inputs!B2>=Inputs!B9) -> FALSE
A10: R published minimum met | B10: =Inputs!B2>=Inputs!B10 -> TRUE
A11: 100bp parallel-yield stress, price only | B11: =-Inputs!B12*0.01 -> -0.0687
A12: Decision | B12: Pass I: institutional eligibility not assumed. R remains a candidate, not a recommendation
A13: Return convention | B13: Hypothetical pre-expense return minus expense ratio. Never subtract fees again from published net returns
A14: Stress limitation | B14: First-order duration only: excludes carry, convexity, FX, spread and active changes

Sheet Sensitivity
A1: Gross return assumption | B1: I terminal wealth: net fees | C1: R terminal wealth: net fees | D1: I less R
A2: -0.02 | B2: =Inputs!B2*(1+A2-Inputs!B5)^Inputs!B4 -> 762899.33 | C2: =Inputs!B2*(1+A2-Inputs!B6)^Inputs!B4 -> 743528.6 | D2: =B2-C2 -> 19370.734
A3: 0.05 | B3: =Inputs!B2*(1+A3-Inputs!B5)^Inputs!B4 -> 1527889.9 | C3: =Inputs!B2*(1+A3-Inputs!B6)^Inputs!B4 -> 1491670.3 | D3: =B3-C3 -> 36219.673
A4: 0.08 | B4: =Inputs!B2*(1+A4-Inputs!B5)^Inputs!B4 -> 2028669.5 | C4: =Inputs!B2*(1+A4-Inputs!B6)^Inputs!B4 -> 1981908.6 | D4: =B4-C4 -> 46760.857
A5: Illustrative no-waiver case | B5: I wealth at gross expense | C5: R wealth at gross expense
A6: Not a forecast | B6: =Inputs!B2*(1+Inputs!B3-Inputs!B7)^Inputs!B4 -> 1510406.9 | C6: =Inputs!B2*(1+Inputs!B3-Inputs!B8)^Inputs!B4 -> 1474560.9

Sheet Inputs
A1: Inputs: sourced and assumed values | B1: Value | C1: Tag | D1: Source / rationale
A2: capital | B2: 1000000 | C2: A | D2: Hypothetical US-dollar family bond sleeve after a liquidity event; not a real client
A3: gross_return | B3: 0.05 | C3: A | D3: Illustrative constant annual pre-expense return; not a forecast
A4: years | B4: 10 | C4: A | D4: Illustrative holding horizon
A5: i_net_fee | B5: 0.0067 | C5: S | D5: factsheet p1, 30 Jun 2026
A6: r_net_fee | B6: 0.0092 | C6: S | D6: factsheet p1, 30 Jun 2026
A7: i_gross_fee | B7: 0.0079 | C7: S | D7: factsheet p1
A8: r_gross_fee | B8: 0.0104 | C8: S | D8: factsheet p1
A9: i_minimum | B9: 100000 | C9: S | D9: factsheet p1: institutional investors only
A10: r_minimum | B10: 2500 | C10: S | D10: factsheet p1: retail shares
A11: family_institutional | B11: =FALSE() -> FALSE | C11: A | D11: Hypothetical direct retail family; no institutional vehicle assumed
A12: duration | B12: 6.87 | C12: S | D12: factsheet p1
A13: waiver_expiry | B13: 2027-01-31 | C13: S | D13: factsheet p1: arrangement expiration, not a promise fees revert

Sheet Sources
A1: Sources | B1: URL / detail | C1: Page / date
A2: Factsheet | B2: https://www.loomissayles.com/wp-content/uploads/2026/07/GlobalBondFund-FactSheet.pdf | C2: Pages 1-2; 30 Jun 2026
A3: Hypothetical client | B3: Retail family; US-dollar sleeve; not an actual client | C3: Assumption
A4: Model | B4: Flat annual pre-expense return and fee approximation; no taxes or cash flows | C4: Assumption
A5: Waiver | B5: 31 Jan 2027 expiry is not evidence of automatic fee rise | C5: factsheet p1
A6: Identifier discrepancy | B6: Header says LSGBXR; fund-facts table says LSGLX. Use class names, request clarification | C6: factsheet p1
